Workbook
Name UPDATE: 'Data Sheet'!$E$1

Sheet Financials

Sheet Altman's Z Score
B3: AVENUE SUPERMARTS LTD
B4: (Avenue Supermart | BSE Code : 540376)
B5: INR 4054
B6: 52 Week ( High - 4949.50 & Low - 4069.20)
B9: Avenue Supermarts Limited, d/b/a DMart, is an Indian retail corporation that operates a chain of supermarkets and hypermarkets. The company was founded by Radhakishan Damani and is based in Mumbai. As of March 2025, DMart has 415 stores across 12 states and union territories in India.
B14: Financial Summary
B60: Working Capital / Total Assets
D61: 43525 | E61: 43891 | F61: 44256 | G61: 44621 | H61: 44986 | I61: 45352 | J61: 45717
B62: Working Capital | D62: ='Data Sheet'!E65-'Data Sheet'!E60 -> 7465.87 | E62: ='Data Sheet'!F65-'Data Sheet'!F60 -> 8828.26 | F62: ='Data Sheet'!G65-'Data Sheet'!G60 -> 13085.47 | G62: ='Data Sheet'!H65-'Data Sheet'!H60 -> 12524.2 | H62: ='Data Sheet'!I65-'Data Sheet'!I60 -> 6701.81 | I62: ='Data Sheet'!J65-'Data Sheet'!J60 -> 12228 | J62: ='Data Sheet'!K65-'Data Sheet'!K60 -> -29475
B63: Total Assets | D63: ='Data Sheet'!E66 -> 305703.49 | E63: ='Data Sheet'!F66 -> 320179.39 | F63: ='Data Sheet'!G66 -> 341569.91 | G63: ='Data Sheet'!H66 -> 329061.49 | H63: ='Data Sheet'!I66 -> 334674.43 | I63: ='Data Sheet'!J66 -> 369521 | J63: ='Data Sheet'!K66 -> 376973
B64: Working Capital / Total Assets (A) | D64: =D62/D63 -> 0.024421933 | E64: =E62/E63 -> 0.027572855 | F64: =F62/F63 -> 0.038309786 | G64: =G62/G63 -> 0.038060364 | H64: =H62/H63 -> 0.020024864 | I64: =I62/I63 -> 0.033091489 | J64: =J62/J63 -> -0.078188624
B66: Retained Earnings / Total Assets
D67: 43525 | E67: 43891 | F67: 44256 | G67: 44621 | H67: 44986 | I67: 45352 | J67: 45717
B68: Retained Earnings | D68: ='Historical FS'!F34*'Historical FS'!F36*'Historical FS'!F42 -> 1859.11 | E68: ='Historical FS'!G34*'Historical FS'!G36*'Historical FS'!G42 -> 0 | F68: ='Historical FS'!H34*'Historical FS'!H36*'Historical FS'!H42 -> 7470.01 | G68: ='Historical FS'!I34*'Historical FS'!I36*'Historical FS'!I42 -> 0 | H68: ='Historical FS'!J34*'Historical FS'!J36*'Historical FS'!J42 -> 0 | I68: ='Historical FS'!K34*'Historical FS'!K36*'Historical FS'!K42 -> 21582 | J68: ='Historical FS'!L34*'Historical FS'!L36*'Historical FS'!L42 -> 19839
B69: Total Assets | D69: =D63 -> 305703.49 | E69: =E63 -> 320179.39 | F69: =F63 -> 341569.91 | G69: =G63 -> 329061.49 | H69: =H63 -> 334674.43 | I69: =I63 -> 369521 | J69: =J63 -> 376973
B70: =_xlfn.CONCAT(B66," ","(B)") -> Retained Earnings / Total Assets (B) | D70: =D68/D69 -> 0.0060814157 | E70: =E68/E69 -> 0 | F70: =F68/F69 -> 0.021869637 | G70: =G68/G69 -> 0 | H70: =H68/H69 -> 0 | I70: =I68/I69 -> 0.058405341 | J70: =J68/J69 -> 0.052627111
B72: EBIT / Total Assets
B73: EBIT | D73: ='Historical FS'!E16-'Historical FS'!E22 -> 5810.93 | E73: ='Historical FS'!F16-'Historical FS'!F22 -> 5180.26 | F73: ='Historical FS'!G16-'Historical FS'!G22 -> 1024.02 | G73: ='Historical FS'!H16-'Historical FS'!H22 -> 18109.04 | H73: ='Historical FS'!I16-'Historical FS'!I22 -> 3065.38 | I73: ='Historical FS'!J16-'Historical FS'!J22 -> -2607.8 | J73: ='Historical FS'!K16-'Historical FS'!K22 -> 27453
B74: Average Total Asset | D74: =D63 -> 305703.49 | E74: =E63 -> 320179.39 | F74: =F63 -> 341569.91 | G74: =G63 -> 329061.49 | H74: =H63 -> 334674.43 | I74: =I63 -> 369521 | J74: =J63 -> 376973
B75: =_xlfn.CONCAT(B72," ","(C)") -> EBIT / Total Assets (C) | D75: =D73/D74 -> 0.019008386 | E75: =E73/E74 -> 0.016179243 | F75: =F73/F74 -> 0.0029979807 | G75: =G73/G74 -> 0.055032389 | H75: =H73/H74 -> 0.0091592895 | I75: =I73/I74 -> -0.0070572444 | J75: =J73/J74 -> 0.072824844
B77: Market Cap / Long term liabilities
B78: Market Cap | D78: =('Data Sheet'!E90*'Data Sheet'!E70)/10000000 -> 59177.055 | E78: =('Data Sheet'!F90*'Data Sheet'!F70)/10000000 -> 25561.845 | F78: =('Data Sheet'!G90*'Data Sheet'!G70)/10000000 -> 115561.05 | G78: =('Data Sheet'!H90*'Data Sheet'!H70)/10000000 -> 166100.87 | H78: =('Data Sheet'!I90*'Data Sheet'!I70)/10000000 -> 161170.49 | I78: =('Data Sheet'!J90*'Data Sheet'!J70)/10000000 -> 380489.8 | J78: =('Data Sheet'!K90*'Data Sheet'!K70)/10000000 -> 248288.57
B79: Long Term Liabilities | D79: ='Data Sheet'!E59 -> 106175.34 | E79: ='Data Sheet'!F59 -> 124787.64 | F79: ='Data Sheet'!G59 -> 142130.57 | G79: ='Data Sheet'!H59 -> 146449.03 | H79: ='Data Sheet'!I59 -> 134113.44 | I79: ='Data Sheet'!J59 -> 107264 | J79: ='Data Sheet'!K59 -> 71540
B80: =_xlfn.CONCAT(B77," ","(D)") -> Market Cap / Long term liabilities (D) | D80: =D78/D79 -> 0.55735216 | E80: =E78/E79 -> 0.20484276 | F80: =F78/F79 -> 0.8130626 | G80: =G78/G79 -> 1.1341889 | H80: =H78/H79 -> 1.2017475 | I80: =I78/I79 -> 3.5472274 | J80: =J78/J79 -> 3.4706257
B82: Sales / Total Assets
D83: 43525 | E83: 43891 | F83: 44256 | G83: 44621 | H83: 44986 | I83: 45352 | J83: 45717
B84: Sales | D84: ='Data Sheet'!E17 -> 301938.4 | E84: ='Data Sheet'!F17 -> 261067.97 | F84: ='Data Sheet'!G17 -> 249794.75 | G84: ='Data Sheet'!H17 -> 278453.62 | H84: ='Data Sheet'!I17 -> 345966.97 | I84: ='Data Sheet'!J17 -> 434016 | J84: ='Data Sheet'!K17 -> 439695
B85: Total Asset | D85: ='Data Sheet'!E66 -> 305703.49 | E85: ='Data Sheet'!F66 -> 320179.39 | F85: ='Data Sheet'!G66 -> 341569.91 | G85: ='Data Sheet'!H66 -> 329061.49 | H85: ='Data Sheet'!I66 -> 334674.43 | I85: ='Data Sheet'!J66 -> 369521 | J85: ='Data Sheet'!K66 -> 376973
B86: =_xlfn.CONCAT(B82," ","(E)") -> Sales / Total Assets (E) | D86: =D84/D85 -> 0.98768385 | E86: =E84/E85 -> 0.81538031 | F86: =F84/F85 -> 0.73131369 | G86: =G84/G85 -> 0.84620543 | H86: =H84/H85 -> 1.0337419 | I86: =I84/I85 -> 1.1745368 | J86: =J84/J85 -> 1.1663833
B88: Altman's Z Score
D89: 43525 | E89: 43891 | F89: 44256 | G89: 44621 | H89: 44986 | I89: 45352 | J89: 45717
B90: Final Score | D90: =(1.2*D64)+(1.4*D70)+(3.3*D75)+(0.6*D80)+(1*D86) -> 1.4226431 | E90: =(1.2*E64)+(1.4*E70)+(3.3*E75)+(0.6*E80)+(1*E86) -> 1.0247649 | F90: =(1.2*F64)+(1.4*F70)+(3.3*F75)+(0.6*F80)+(1*F86) -> 1.3056338 | G90: =(1.2*G64)+(1.4*G70)+(3.3*G75)+(0.6*G80)+(1*G86) -> 1.7539981 | H90: =(1.2*H64)+(1.4*H70)+(3.3*H75)+(0.6*H80)+(1*H86) -> 1.8090459 | I90: =(1.2*I64)+(1.4*I70)+(3.3*I75)+(0.6*I80)+(1*I86) -> 3.4010615 | J90: =(1.2*J64)+(1.4*J70)+(3.3*J75)+(0.6*J80)+(1*J86) -> 3.4689323
B91: Financial Stability | D91: =IF(D90<1.81,"Distressed",IF(D90>3,"Strong","Grey Zone")) -> Distressed | E91: =IF(E90<1.81,"Distressed",IF(E90>3,"Strong","Grey Zone")) -> Distressed | F91: =IF(F90<1.81,"Distressed",IF(F90>3,"Strong","Grey Zone")) -> Distressed | G91: =IF(G90<1.81,"Distressed",IF(G90>3,"Strong","Grey Zone")) -> Distressed | H91: =IF(H90<1.81,"Distressed",IF(H90>3,"Strong","Grey Zone")) -> Distressed | I91: =IF(I90<1.81,"Distressed",IF(I90>3,"Strong","Grey Zone")) -> Strong | J91: =IF(J90<1.81,"Distressed",IF(J90>3,"Strong","Grey Zone")) -> Strong

Sheet Dupont Analysis
B3: AVENUE SUPERMARTS LTD
B4: (Avenue Supermart | BSE Code : 540376)
B5: INR 4054
B6: 52 Week ( High - 4949.50 & Low - 4069.20)
B8: About the company
B9: Avenue Supermarts Limited, d/b/a DMart, is an Indian retail corporation that operates a chain of supermarkets and hypermarkets. The company was founded by Radhakishan Damani and is based in Mumbai. As of March 2025, DMart has 415 stores across 12 states and union territories in India.
B14: Financial Summary
B60: Return on Equity (ROE)
D61: 43525 | E61: 43891 | F61: 44256 | G61: 44621 | H61: 44986 | I61: 45352 | J61: 45717
B62: Net Profit | D62: ='Historical FS'!F31 -> 1859.11 | E62: ='Historical FS'!G31 -> -6614.56 | F62: ='Historical FS'!H31 -> 7470.01 | G62: ='Historical FS'!I31 -> -10477.77 | H62: ='Historical FS'!J31 -> -13537.34 | I62: ='Historical FS'!K31 -> 23883 | J62: ='Historical FS'!L31 -> 22047
B63: Average Shareholder Equity | D63: =(('Historical FS'!F45+'Historical FS'!F46)+('Historical FS'!E45+'Historical FS'!E46))/2 -> 77803.735 | E63: =(('Historical FS'!G45+'Historical FS'!G46)+('Historical FS'!F45+'Historical FS'!F46))/2 -> 61629.045 | F63: =(('Historical FS'!H45+'Historical FS'!H46)+('Historical FS'!G45+'Historical FS'!G46))/2 -> 59162.625 | G63: =(('Historical FS'!I45+'Historical FS'!I46)+('Historical FS'!H45+'Historical FS'!H46))/2 -> 49903.98 | H63: =(('Historical FS'!J45+'Historical FS'!J46)+('Historical FS'!I45+'Historical FS'!I46))/2 -> 44941.515 | I63: =(('Historical FS'!K45+'Historical FS'!K46)+('Historical FS'!J45+'Historical FS'!J46))/2 -> 65119.895 | J63: =(('Historical FS'!L45+'Historical FS'!L46)+('Historical FS'!K45+'Historical FS'!K46))/2 -> 100531
B64: Return on Equity | D64: =D62/D63 -> 0.023894868 | E64: =E62/E63 -> -0.10732861 | F64: =F62/F63 -> 0.12626232 | G64: =G62/G63 -> -0.2099586 | H64: =H62/H63 -> -0.30122127 | I64: =I62/I63 -> 0.36675428 | J64: =J62/J63 -> 0.21930549
B66: ROE - Dupont Equation
D67: 43525 | E67: 43891 | F67: 44256 | G67: 44621 | H67: 44986 | I67: 45352 | J67: 45717
B68: =B62 -> Net Profit | D68: =D62 -> 1859.11 | E68: =E62 -> -6614.56 | F68: =F62 -> 7470.01 | G68: =G62 -> -10477.77 | H68: =H62 -> -13537.34 | I68: =I62 -> 23883 | J68: =J62 -> 22047
B69: Revenue | D69: ='Historical FS'!F5 -> 301938.4 | E69: ='Historical FS'!G5 -> 261067.97 | F69: ='Historical FS'!H5 -> 249794.75 | G69: ='Historical FS'!I5 -> 278453.62 | H69: ='Historical FS'!J5 -> 345966.97 | I69: ='Historical FS'!K5 -> 434016 | J69: ='Historical FS'!L5 -> 439695
B70: Net Profit Margin (A) | D70: =D68/D69 -> 0.0061572493 | E70: =E68/E69 -> -0.025336544 | F70: =F68/F69 -> 0.029904592 | G70: =G68/G69 -> -0.037628421 | H70: =H68/H69 -> -0.039128995 | I70: =I68/I69 -> 0.055027925 | J70: =J68/J69 -> 0.050141575
B72: Revenue | D72: ='Historical FS'!F5 -> 301938.4 | E72: ='Historical FS'!G5 -> 261067.97 | F72: ='Historical FS'!H5 -> 249794.75 | G72: ='Historical FS'!I5 -> 278453.62 | H72: ='Historical FS'!J5 -> 345966.97 | I72: ='Historical FS'!K5 -> 434016 | J72: ='Historical FS'!L5 -> 439695
B73: Average Total Asset | D73: =('Historical FS'!F62+'Historical FS'!E62)/2 -> 316447.65 | E73: =('Historical FS'!G62+'Historical FS'!F62)/2 -> 312941.44 | F73: =('Historical FS'!H62+'Historical FS'!G62)/2 -> 330874.65 | G73: =('Historical FS'!I62+'Historical FS'!H62)/2 -> 335315.7 | H73: =('Historical FS'!J62+'Historical FS'!I62)/2 -> 331867.96 | I73: =('Historical FS'!K62+'Historical FS'!J62)/2 -> 352097.72 | J73: =('Historical FS'!L62+'Historical FS'!K62)/2 -> 373247
B74: Asset Turnover Ratio (B) | D74: =D72/D73 -> 0.9541496 | E74: =E72/E73 -> 0.83423905 | F74: =F72/F73 -> 0.75495282 | G74: =G72/G73 -> 0.83042226 | H74: =H72/H73 -> 1.0424838 | I74: =I72/I73 -> 1.2326578 | J74: =J72/J73 -> 1.1780269
B76: Average Total Asset | D76: =('Historical FS'!F62+'Historical FS'!E62)/2 -> 316447.65 | E76: =('Historical FS'!G62+'Historical FS'!F62)/2 -> 312941.44 | F76: =('Historical FS'!H62+'Historical FS'!G62)/2 -> 330874.65 | G76: =('Historical FS'!I62+'Historical FS'!H62)/2 -> 335315.7 | H76: =('Historical FS'!J62+'Historical FS'!I62)/2 -> 331867.96 | I76: =('Historical FS'!K62+'Historical FS'!J62)/2 -> 352097.72 | J76: =('Historical FS'!L62+'Historical FS'!K62)/2 -> 373247
B77: Average Shareholder Equity | D77: =(('Historical FS'!F45+'Historical FS'!F46)+('Historical FS'!E46+'Historical FS'!E45))/2 -> 77803.735 | E77: =(('Historical FS'!G45+'Historical FS'!G46)+('Historical FS'!F46+'Historical FS'!F45))/2 -> 61629.045 | F77: =(('Historical FS'!H45+'Historical FS'!H46)+('Historical FS'!G46+'Historical FS'!G45))/2 -> 59162.625 | G77: =(('Historical FS'!I45+'Historical FS'!I46)+('Historical FS'!H46+'Historical FS'!H45))/2 -> 49903.98 | H77: =(('Historical FS'!J45+'Historical FS'!J46)+('Historical FS'!I46+'Historical FS'!I45))/2 -> 44941.515 | I77: =(('Historical FS'!K45+'Historical FS'!K46)+('Historical FS'!J46+'Historical FS'!J45))/2 -> 65119.895 | J77: =(('Historical FS'!L45+'Historical FS'!L46)+('Historical FS'!K46+'Historical FS'!K45))/2 -> 100531
B78: Equity Multiplier | D78: =D76/D77 -> 4.0672553 | E78: =E76/E77 -> 5.0778239 | F78: =F76/F77 -> 5.5926296 | G78: =G76/G77 -> 6.7192176 | H78: =H76/H77 -> 7.3844409 | I78: =I76/I77 -> 5.4069147 | J78: =J76/J77 -> 3.7127553
B80: Return on Equity (A*B*C) | D80: =D70*D74*D78 -> 0.023894868 | E80: =E70*E74*E78 -> -0.10732861 | F80: =F70*F74*F78 -> 0.12626232 | G80: =G70*G74*G78 -> -0.2099586 | H80: =H70*H74*H78 -> -0.30122127 | I80: =I70*I74*I78 -> 0.36675428 | J80: =J70*J74*J78 -> 0.21930549
B82: Return on Asset (ROA)
D83: 43525 | E83: 43891 | F83: 44256 | G83: 44621 | H83: 44986 | I83: 45352 | J83: 45717
B84: Net Profit | D84: =D62 -> 1859.11 | E84: =E62 -> -6614.56 | F84: =F62 -> 7470.01 | G84: =G62 -> -10477.77 | H84: =H62 -> -13537.34 | I84: =I62 -> 23883 | J84: =J62 -> 22047
B85: Average Total Asset | D85: =D73 -> 316447.65 | E85: =E73 -> 312941.44 | F85: =F73 -> 330874.65 | G85: =G73 -> 335315.7 | H85: =H73 -> 331867.96 | I85: =I73 -> 352097.72 | J85: =J73 -> 373247
B86: Return on Asset | D86: =D84/D85 -> 0.005874937 | E86: =E84/E85 -> -0.021136734 | F86: =F84/F85 -> 0.022576556 | G86: =G84/G85 -> -0.031247478 | H86: =H84/H85 -> -0.040791344 | I86: =I84/I85 -> 0.067830602 | J86: =J84/J85 -> 0.059068124
B88: ROA - Dupont Equation
D89: 43525 | E89: 43891 | F89: 44256 | G89: 44621 | H89: 44986 | I89: 45352 | J89: 45717
B90: =B84 -> Net Profit | D90: =D84 -> 1859.11 | E90: =E84 -> -6614.56 | F90: =F84 -> 7470.01 | G90: =G84 -> -10477.77 | H90: =H84 -> -13537.34 | I90: =I84 -> 23883 | J90: =J84 -> 22047
B91: Revenue | D91: =D69 -> 301938.4 | E91: =E69 -> 261067.97 | F91: =F69 -> 249794.75 | G91: =G69 -> 278453.62 | H91: =H69 -> 345966.97 | I91: =I69 -> 434016 | J91: =J69 -> 439695
B92: Net Profit Margin (A) | D92: =D90/D91 -> 0.0061572493 | E92: =E90/E91 -> -0.025336544 | F92: =F90/F91 -> 0.029904592 | G92: =G90/G91 -> -0.037628421 | H92: =H90/H91 -> -0.039128995 | I92: =I90/I91 -> 0.055027925 | J92: =J90/J91 -> 0.050141575
B94: Revenue | D94: =D72 -> 301938.4 | E94: =E72 -> 261067.97 | F94: =F72 -> 249794.75 | G94: =G72 -> 278453.62 | H94: =H72 -> 345966.97 | I94: =I72 -> 434016 | J94: =J72 -> 439695
B95: Average Total Asset | D95: =D73 -> 316447.65 | E95: =E73 -> 312941.44 | F95: =F73 -> 330874.65 | G95: =G73 -> 335315.7 | H95: =H73 -> 331867.96 | I95: =I73 -> 352097.72 | J95: =J73 -> 373247
B96: Asset Turnover Ratio (B) | D96: =D94/D95 -> 0.9541496 | E96: =E94/E95 -> 0.83423905 | F96: =F94/F95 -> 0.75495282 | G96: =G94/G95 -> 0.83042226 | H96: =H94/H95 -> 1.0424838 | I96: =I94/I95 -> 1.2326578 | J96: =J94/J95 -> 1.1780269
B98: Return on Asset (A*B) | D98: =D92*D96 -> 0.005874937 | E98: =E92*E96 -> -0.021136734 | F98: =F92*F96 -> 0.022576556 | G98: =G92*G96 -> -0.031247478 | H98: =H92*H96 -> -0.040791344 | I98: =I92*I96 -> 0.067830602 | J98: =J92*J96 -> 0.059068124

Sheet Historical FS
B2: ="Historical Financial Statements - "&'Data Sheet'!B1 -> Historical Financial Statements - TATA MOTORS LTD
B3: Years | C3: ='Data Sheet'!B16 -> 42460 | D3: ='Data Sheet'!C16 -> 42825 | E3: ='Data Sheet'!D16 -> 43190 | F3: ='Data Sheet'!E16 -> 43555 | G3: ='Data Sheet'!F16 -> 43921 | H3: ='Data Sheet'!G16 -> 44286 | I3: ='Data Sheet'!H16 -> 44651 | J3: ='Data Sheet'!I16 -> 45016 | ... L3: ='Data Sheet'!K16 -> 45747 | M3: LTM
A4: # | B4: Income Statement
B5: Sales | C5: =IFERROR('Data Sheet'!B17,0) -> 273045.6 | D5: =IFERROR('Data Sheet'!C17,0) -> 269692.51 | E5: =IFERROR('Data Sheet'!D17,0) -> 291550.48 | F5: =IFERROR('Data Sheet'!E17,0) -> 301938.4 | G5: =IFERROR('Data Sheet'!F17,0) -> 261067.97 | H5: =IFERROR('Data Sheet'!G17,0) -> 249794.75 | I5: =IFERROR('Data Sheet'!H17,0) -> 278453.62 | J5: =IFERROR('Data Sheet'!I17,0) -> 345966.97 | ... L5: =IFERROR('Data Sheet'!K17,0) -> 439695 | M5: =IFERROR(SUM('Data Sheet'!H42:K42),0) -> 441609
B6: Sales Growth | C6: ="-" -> - | D6: =IFERROR((D5-C5)/C5,0) -> -0.01228033 | E6: =IFERROR((E5-D5)/D5,0) -> 0.081047746 | F6: =IFERROR((F5-E5)/E5,0) -> 0.035629919 | G6: =IFERROR((G5-F5)/F5,0) -> -0.13536016 | H6: =IFERROR((H5-G5)/G5,0) -> -0.043181168 | I6: =IFERROR((I5-H5)/H5,0) -> 0.11472967 | J6: =IFERROR((J5-I5)/I5,0) -> 0.24245815 | K6: =IFERROR((K5-J5)/J5,0) -> 0.25450126 | ... M6: =IFERROR((M5-L5)/L5,0) -> 0.0043530174
B8: COGS | C8: =IFERROR(SUM('Data Sheet'!B18,'Data Sheet'!B20:B22,-1*'Data Sheet'!B19),0) -> 205509.07 | D8: =IFERROR(SUM('Data Sheet'!C18:C22),0) -> 220254.08 | E8: =IFERROR(SUM('Data Sheet'!D18:D22),0) -> 232522.99 | F8: =IFERROR(SUM('Data Sheet'!E18:E22),0) -> 238738.97 | G8: =IFERROR(SUM('Data Sheet'!F18:F22),0) -> 205913.69 | H8: =IFERROR(SUM('Data Sheet'!G18:G22),0) -> 185957.72 | I8: =IFERROR(SUM('Data Sheet'!H18:H22),0) -> 220119.03 | J8: =IFERROR(SUM('Data Sheet'!I18:I22),0) -> 283966.88 | K8: =IFERROR(SUM('Data Sheet'!J18:J22),0) -> 337512 | L8: =IFERROR(SUM('Data Sheet'!K18:K22),0) -> 335137 | M8: =IFERROR(SUM('Data Sheet'!H43:K43),0) -> 384424
B9: COGS % Sales | C9: =C8/C5 -> 0.75265476 | D9: =D8/D5 -> 0.81668594 | E9: =E8/E5 -> 0.79753938 | F9: =F8/F5 -> 0.79068767 | G9: =G8/G5 -> 0.78873594 | H9: =H8/H5 -> 0.74444207 | I9: =I8/I5 -> 0.79050518 | J9: =J8/J5 -> 0.82079188 | ... M9: =M8/M5 -> 0.87050762
B11: Gross Profit | C11: =C5-C8 -> 67536.53 | D11: =D5-D8 -> 49438.43 | E11: =E5-E8 -> 59027.49 | F11: =F5-F8 -> 63199.43 | G11: =G5-G8 -> 55154.28 | H11: =H5-H8 -> 63837.03 | I11: =I5-I8 -> 58334.59 | J11: =J5-J8 -> 62000.09 | ... M11: =M5-M8 -> 57185
B13: Selling and general expenses | C13: =IFERROR(SUM('Data Sheet'!B23:B24),0) -> 29141.28 | D13: =IFERROR(SUM('Data Sheet'!C23:C24),0) -> 34649.58 | E13: =IFERROR(SUM('Data Sheet'!D23:D24),0) -> 31662.97 | F13: =IFERROR(SUM('Data Sheet'!E23:E24),0) -> 34428.54 | G13: =IFERROR(SUM('Data Sheet'!F23:F24),0) -> 32704.83 | H13: =IFERROR(SUM('Data Sheet'!G23:G24),0) -> 22181.28 | I13: =IFERROR(SUM('Data Sheet'!H23:H24),0) -> 30433.52 | J13: =IFERROR(SUM('Data Sheet'!I23:I24),0) -> 39747.53 | ... M13: =IFERROR(SUM('Data Sheet'!L23:L24),0) -> 0
B14: S&G Expenses % Sales | C14: =C13/C5 -> 0.10672679 | D14: =D13/D5 -> 0.1284781 | E14: =E13/E5 -> 0.10860202 | F14: =F13/F5 -> 0.11402505 | G14: =G13/G5 -> 0.12527324 | H14: =H13/H5 -> 0.088798023 | I14: =I13/I5 -> 0.10929475 | J14: =J13/J5 -> 0.11488822 | ... M14: =M13/M5 -> 0
B16: EBIDTA | C16: =C11-C13 -> 38395.25 | D16: =D11-D13 -> 14788.85 | E16: =E11-E13 -> 27364.52 | F16: =F11-F13 -> 28770.89 | G16: =G11-G13 -> 22449.45 | H16: =H11-H13 -> 41655.75 | I16: =I11-I13 -> 27901.07 | J16: =J11-J13 -> 22252.56 | ... M16: =M11-M13 -> 57185
B17: EBIDTA % Margins | C17: =C16/C5 -> 0.14061845 | D17: =D16/D5 -> 0.054835969 | E17: =E16/E5 -> 0.0938586 | F17: =F16/F5 -> 0.095287284 | G17: =G16/G5 -> 0.085990825 | H17: =H16/H5 -> 0.16675991 | I17: =I16/I5 -> 0.10020006 | J17: =J16/J5 -> 0.064319897 | ... M17: =M16/M5 -> 0.12949238
B19: Interest | C19: =IFERROR('Data Sheet'!B27,0) -> 4889.08 | D19: =IFERROR('Data Sheet'!C27,0) -> 4238.01 | E19: =IFERROR('Data Sheet'!D27,0) -> 4681.79 | F19: =IFERROR('Data Sheet'!E27,0) -> 5758.6 | G19: =IFERROR('Data Sheet'!F27,0) -> 7243.33 | H19: =IFERROR('Data Sheet'!G27,0) -> 8097.17 | I19: =IFERROR('Data Sheet'!H27,0) -> 9311.86 | J19: =IFERROR('Data Sheet'!I27,0) -> 10225.48 | ... L19: =IFERROR('Data Sheet'!K27,0) -> 5083 | M19: =IFERROR(SUM('Data Sheet'!H46:K46),0) -> 6317
B20: Interest % Sales | C20: =C19/C5 -> 0.017905727 | D20: =D19/D5 -> 0.01571423 | E20: =E19/E5 -> 0.016058248 | F20: =F19/F5 -> 0.019072102 | G20: =G19/G5 -> 0.027744997 | H20: =H19/H5 -> 0.032415293 | I20: =I19/I5 -> 0.033441332 | J20: =J19/J5 -> 0.029556232 | ... M20: =M19/M5 -> 0.014304509
B22: Depreciation | C22: =IFERROR('Data Sheet'!B26,0) -> 16710.78 | D22: =IFERROR('Data Sheet'!C26,0) -> 17904.99 | E22: =IFERROR('Data Sheet'!D26,0) -> 21553.59 | F22: =IFERROR('Data Sheet'!E26,0) -> 23590.63 | G22: =IFERROR('Data Sheet'!F26,0) -> 21425.43 | H22: =IFERROR('Data Sheet'!G26,0) -> 23546.71 | I22: =IFERROR('Data Sheet'!H26,0) -> 24835.69 | J22: =IFERROR('Data Sheet'!I26,0) -> 24860.36 | ... L22: =IFERROR('Data Sheet'!K26,0) -> 23256 | M22: =IFERROR(SUM('Data Sheet'!H45:K45),0) -> 23273
B23: Depreciation % Sales | C23: =IFERROR(C22/C5,0) -> 0.061201426 | D23: =IFERROR(D22/D5,0) -> 0.066390387 | E23: =IFERROR(E22/E5,0) -> 0.073927472 | F23: =IFERROR(F22/F5,0) -> 0.078130605 | G23: =IFERROR(G22/G5,0) -> 0.082068398 | H23: =IFERROR(H22/H5,0) -> 0.094264231 | I23: =IFERROR(I22/I5,0) -> 0.089191478 | J23: =IFERROR(J22/J5,0) -> 0.071857611 | ... M23: =IFERROR(M22/M5,0) -> 0.052700466
B25: Earnings before taxes | C25: =IFERROR(C16-SUM(C19,C22),0) -> 16795.39 | D25: =IFERROR(D16-SUM(D19,D22),0) -> -7354.15 | E25: =IFERROR(E16-SUM(E19,E22),0) -> 1129.14 | F25: =IFERROR(F16-SUM(F19,F22),0) -> -578.34 | G25: =IFERROR(G16-SUM(G19,G22),0) -> -6219.31 | H25: =IFERROR(H16-SUM(H19,H22),0) -> 10011.87 | I25: =IFERROR(I16-SUM(I19,I22),0) -> -6246.48 | J25: =IFERROR(J16-SUM(J19,J22),0) -> -12833.28 | ... M25: =IFERROR(M16-SUM(M19,M22),0) -> 27595
B26: EBT % Sales | C26: =IFERROR(C25/C5,0) -> 0.061511301 | D26: =IFERROR(D25/D5,0) -> -0.027268648 | E26: =IFERROR(E25/E5,0) -> 0.0038728799 | F26: =IFERROR(F25/F5,0) -> -0.0019154238 | G26: =IFERROR(G25/G5,0) -> -0.02382257 | H26: =IFERROR(H25/H5,0) -> 0.040080386 | I26: =IFERROR(I25/I5,0) -> -0.022432748 | J26: =IFERROR(J25/J5,0) -> -0.037093946 | ... M26: =IFERROR(M25/M5,0) -> 0.062487404
B28: Tax | C28: =IFERROR('Data Sheet'!B29,0) -> 3025.05 | D28: =IFERROR('Data Sheet'!C29,0) -> 3251.23 | E28: =IFERROR('Data Sheet'!D29,0) -> 4341.93 | F28: =IFERROR('Data Sheet'!E29,0) -> -2437.45 | G28: =IFERROR('Data Sheet'!F29,0) -> 395.25 | H28: =IFERROR('Data Sheet'!G29,0) -> 2541.86 | I28: =IFERROR('Data Sheet'!H29,0) -> 4231.29 | J28: =IFERROR('Data Sheet'!I29,0) -> 704.06 | ... L28: =IFERROR('Data Sheet'!K29,0) -> 10502 | M28: =IFERROR(SUM('Data Sheet'!H48:K48),0) -> 10563
B29: Effective tax rate | C29: =IFERROR(C28/C25,0) -> 0.18011192 | D29: =IFERROR(D28/D25,0) -> -0.4420946 | E29: =IFERROR(E28/E25,0) -> 3.8453425 | F29: =IFERROR(F28/F25,0) -> 4.2145624 | G29: =IFERROR(G28/G25,0) -> -0.063552066 | H29: =IFERROR(H28/H25,0) -> 0.25388464 | I29: =IFERROR(I28/I25,0) -> -0.6773879 | J29: =IFERROR(J28/J25,0) -> -0.054862046 | ... M29: =IFERROR(M28/M25,0) -> 0.38278674
B31: Net Profit | C31: =IFERROR(C25-C28,0) -> 13770.34 | D31: =IFERROR(D25-D28,0) -> -10605.38 | E31: =IFERROR(E25-E28,0) -> -3212.79 | F31: =IFERROR(F25-F28,0) -> 1859.11 | G31: =IFERROR(G25-G28,0) -> -6614.56 | H31: =IFERROR(H25-H28,0) -> 7470.01 | I31: =IFERROR(I25-I28,0) -> -10477.77 | J31: =IFERROR(J25-J28,0) -> -13537.34 | ... L31: =IFERROR(L25-L28,0) -> 22047 | M31: =IFERROR(SUM('Data Sheet'!H49:K49),0) -> 22785
B32: Net Margins | C32: =IFERROR(C31/C5,0) -> 0.050432382 | D32: =IFERROR(D31/D5,0) -> -0.039323969 | E32: =IFERROR(E31/E5,0) -> -0.01101967 | F32: =IFERROR(F31/F5,0) -> 0.0061572493 | G32: =IFERROR(G31/G5,0) -> -0.025336544 | H32: =IFERROR(H31/H5,0) -> 0.029904592 | I32: =IFERROR(I31/I5,0) -> -0.037628421 | J32: =IFERROR(J31/J5,0) -> -0.039128995 | ... M32: =IFERROR(M31/M5,0) -> 0.051595416
B34: No. of Equity Shares | C34: =IFERROR('Data Sheet'!B70/10000000,0) -> 339.59303 | D34: =IFERROR('Data Sheet'!C70/10000000,0) -> 339.61007 | E34: =IFERROR('Data Sheet'!D70/10000000,0) -> 339.61007 | F34: =IFERROR('Data Sheet'!E70/10000000,0) -> 339.61007 | G34: =IFERROR('Data Sheet'!F70/10000000,0) -> 359.77262 | H34: =IFERROR('Data Sheet'!G70/10000000,0) -> 382.90607 | I34: =IFERROR('Data Sheet'!H70/10000000,0) -> 382.94149 | J34: =IFERROR('Data Sheet'!I70/10000000,0) -> 383.00972 | ... L34: =IFERROR('Data Sheet'!K70/10000000,0) -> 368.13487
B36: EPS | C36: =IFERROR(C31/C34,0) -> 40.549537 | D36: =IFERROR(D31/D34,0) -> -31.228108 | E36: =IFERROR(E31/E34,0) -> -9.4602318 | F36: =IFERROR(F31/F34,0) -> 5.4742487 | G36: =IFERROR(G31/G34,0) -> -18.38539 | H36: =IFERROR(H31/H34,0) -> 19.508727 | I36: =IFERROR(I31/I34,0) -> -27.361282 | J36: =IFERROR(J31/J34,0) -> -35.344638 | ... L36: =IFERROR(L31/L34,0) -> 59.888377
B37: EPS growth % | D37: =IFERROR((D36/C36)-1,0) -> -1.7701224 | E37: =IFERROR((E36/D36)-1,0) -> -0.69706036 | F37: =IFERROR((F36/E36)-1,0) -> -1.578659 | G37: =IFERROR((G36/F36)-1,0) -> -4.358523 | H37: =IFERROR((H36/G36)-1,0) -> -2.0610994 | I37: =IFERROR((I36/H36)-1,0) -> -2.402515 | J37: =IFERROR((J36/I36)-1,0) -> 0.29177567 | K37: =IFERROR((K36/J36)-1,0) -> -2.763129 | L37: =IFERROR((L36/K36)-1,0) -> -0.038974508
B39: Dividend per share | C39: =IFERROR('Data Sheet'!B31/'Historical FS'!C34,0) -> 0.2000041 | D39: =IFERROR('Data Sheet'!C31/'Historical FS'!D34,0) -> 0 | E39: =IFERROR('Data Sheet'!D31/'Historical FS'!E34,0) -> 0 | F39: =IFERROR('Data Sheet'!E31/'Historical FS'!F34,0) -> 0 | G39: =IFERROR('Data Sheet'!F31/'Historical FS'!G34,0) -> 0 | H39: =IFERROR('Data Sheet'!G31/'Historical FS'!H34,0) -> 0 | I39: =IFERROR('Data Sheet'!H31/'Historical FS'!I34,0) -> 0 | J39: =IFERROR('Data Sheet'!I31/'Historical FS'!J34,0) -> 2.0000015 | ... L39: =IFERROR('Data Sheet'!K31/'Historical FS'!L34,0) -> 5.9978018
B40: dividend pay ratio | C40: =IFERROR(C39/C36,0) -> 0.0049323401 | D40: =IFERROR(D39/D36,0) -> 0 | E40: =IFERROR(E39/E36,0) -> 0 | F40: =IFERROR(F39/F36,0) -> 0 | G40: =IFERROR(G39/G36,0) -> 0 | H40: =IFERROR(H39/H36,0) -> 0 | I40: =IFERROR(I39/I36,0) -> 0 | J40: =IFERROR(J39/J36,0) -> -0.05658571 | ... L40: =IFERROR(L39/L36,0) -> 0.10014968
B42: Retained earnings | C42: =IFERROR(IF(C36>C39,1-C40,0),0) -> 0.99506766 | D42: =IFERROR(IF(D36>D39,1-D40,0),0) -> 0 | E42: =IFERROR(IF(E36>E39,1-E40,0),0) -> 0 | F42: =IFERROR(IF(F36>F39,1-F40,0),0) -> 1 | G42: =IFERROR(IF(G36>G39,1-G40,0),0) -> 0 | H42: =IFERROR(IF(H36>H39,1-H40,0),0) -> 1 | I42: =IFERROR(IF(I36>I39,1-I40,0),0) -> 0 | J42: =IFERROR(IF(J36>J39,1-J40,0),0) -> 0 | ... L42: =IFERROR(IF(L36>L39,1-L40,0),0) -> 0.89985032
A44: # | B44: Balance Sheet
B45: Equity Share Capital | C45: =IFERROR('Data Sheet'!B57,0) -> 679.18 | D45: =IFERROR('Data Sheet'!C57,0) -> 679.22 | E45: =IFERROR('Data Sheet'!D57,0) -> 679.22 | F45: =IFERROR('Data Sheet'!E57,0) -> 679.22 | G45: =IFERROR('Data Sheet'!F57,0) -> 719.54 | H45: =IFERROR('Data Sheet'!G57,0) -> 765.81 | I45: =IFERROR('Data Sheet'!H57,0) -> 765.88 | J45: =IFERROR('Data Sheet'!I57,0) -> 766.02 | ... L45: =IFERROR('Data Sheet'!K57,0) -> 736
B46: Reserves | C46: =IFERROR('Data Sheet'!B58,0) -> 78273.23 | D46: =IFERROR('Data Sheet'!C58,0) -> 57382.67 | E46: =IFERROR('Data Sheet'!D58,0) -> 94748.69 | F46: =IFERROR('Data Sheet'!E58,0) -> 59500.34 | G46: =IFERROR('Data Sheet'!F58,0) -> 62358.99 | H46: =IFERROR('Data Sheet'!G58,0) -> 54480.91 | I46: =IFERROR('Data Sheet'!H58,0) -> 43795.36 | J46: =IFERROR('Data Sheet'!I58,0) -> 44555.77 | ... L46: =IFERROR('Data Sheet'!K58,0) -> 115408
B47: Borrowings | C47: =IFERROR('Data Sheet'!B59,0) -> 69359.96 | D47: =IFERROR('Data Sheet'!C59,0) -> 78603.98 | E47: =IFERROR('Data Sheet'!D59,0) -> 88950.47 | F47: =IFERROR('Data Sheet'!E59,0) -> 106175.34 | G47: =IFERROR('Data Sheet'!F59,0) -> 124787.64 | H47: =IFERROR('Data Sheet'!G59,0) -> 142130.57 | I47: =IFERROR('Data Sheet'!H59,0) -> 146449.03 | J47: =IFERROR('Data Sheet'!I59,0) -> 134113.44 | ... L47: =IFERROR('Data Sheet'!K59,0) -> 71540
B48: Other Liabilities | C48: =IFERROR('Data Sheet'!B60,0) -> 114871.75 | D48: =IFERROR('Data Sheet'!C60,0) -> 135914.49 | E48: =IFERROR('Data Sheet'!D60,0) -> 142813.43 | F48: =IFERROR('Data Sheet'!E60,0) -> 139348.59 | G48: =IFERROR('Data Sheet'!F60,0) -> 132313.22 | H48: =IFERROR('Data Sheet'!G60,0) -> 144192.62 | I48: =IFERROR('Data Sheet'!H60,0) -> 138051.22 | J48: =IFERROR('Data Sheet'!I60,0) -> 155239.2 | ... L48: =IFERROR('Data Sheet'!K60,0) -> 189289
B49: Total liabilities | C49: =IFERROR('Data Sheet'!B61,0) -> 263184.12 | D49: =IFERROR('Data Sheet'!C61,0) -> 272580.36 | E49: =IFERROR('Data Sheet'!D61,0) -> 327191.81 | F49: =IFERROR('Data Sheet'!E61,0) -> 305703.49 | G49: =IFERROR('Data Sheet'!F61,0) -> 320179.39 | H49: =IFERROR('Data Sheet'!G61,0) -> 341569.91 | I49: =IFERROR('Data Sheet'!H61,0) -> 329061.49 | J49: =IFERROR('Data Sheet'!I61,0) -> 334674.43 | ... L49: =IFERROR('Data Sheet'!K61,0) -> 376973
B51: Fixed Assets Net Block | C51: =IFERROR('Data Sheet'!B62,0) -> 107231.76 | D51: =IFERROR('Data Sheet'!C62,0) -> 95944.08 | E51: =IFERROR('Data Sheet'!D62,0) -> 121413.86 | F51: =IFERROR('Data Sheet'!E62,0) -> 111234.47 | G51: =IFERROR('Data Sheet'!F62,0) -> 127107.14 | H51: =IFERROR('Data Sheet'!G62,0) -> 138707.61 | I51: =IFERROR('Data Sheet'!H62,0) -> 138855.45 | J51: =IFERROR('Data Sheet'!I62,0) -> 132079.76 | ... L51: =IFERROR('Data Sheet'!K62,0) -> 115697
B52: Capital Work in Progress | C52: =IFERROR('Data Sheet'!B63,0) -> 25918.94 | D52: =IFERROR('Data Sheet'!C63,0) -> 33698.84 | E52: =IFERROR('Data Sheet'!D63,0) -> 40033.5 | F52: =IFERROR('Data Sheet'!E63,0) -> 31883.84 | G52: =IFERROR('Data Sheet'!F63,0) -> 35622.29 | H52: =IFERROR('Data Sheet'!G63,0) -> 20963.93 | I52: =IFERROR('Data Sheet'!H63,0) -> 10251.09 | J52: =IFERROR('Data Sheet'!I63,0) -> 14274.5 | ... L52: =IFERROR('Data Sheet'!K63,0) -> 65806
B53: Investments | C53: =IFERROR('Data Sheet'!B64,0) -> 23767.02 | D53: =IFERROR('Data Sheet'!C64,0) -> 20337.92 | E53: =IFERROR('Data Sheet'!D64,0) -> 20812.75 | F53: =IFERROR('Data Sheet'!E64,0) -> 15770.72 | G53: =IFERROR('Data Sheet'!F64,0) -> 16308.48 | H53: =IFERROR('Data Sheet'!G64,0) -> 24620.28 | I53: =IFERROR('Data Sheet'!H64,0) -> 29379.53 | J53: =IFERROR('Data Sheet'!I64,0) -> 26379.16 | ... L53: =IFERROR('Data Sheet'!K64,0) -> 35656
B54: Other Assets | C54: =IFERROR('Data Sheet'!B65,0) -> 106266.4 | D54: =IFERROR('Data Sheet'!C65,0) -> 122599.52 | E54: =IFERROR('Data Sheet'!D65,0) -> 144931.7 | F54: =IFERROR('Data Sheet'!E65,0) -> 146814.46 | G54: =IFERROR('Data Sheet'!F65,0) -> 141141.48 | H54: =IFERROR('Data Sheet'!G65,0) -> 157278.09 | I54: =IFERROR('Data Sheet'!H65,0) -> 150575.42 | J54: =IFERROR('Data Sheet'!I65,0) -> 161941.01 | ... L54: =IFERROR('Data Sheet'!K65,0) -> 159814
B55: Total non - current Assets | C55: =IFERROR(SUM('Data Sheet'!B62:B65)-SUM('Data Sheet'!B67:B69),0) -> 186497.08 | D55: =IFERROR(SUM('Data Sheet'!C62:C65)-SUM('Data Sheet'!C67:C69),0) -> 187341.62 | E55: =IFERROR(SUM('Data Sheet'!D62:D65)-SUM('Data Sheet'!D67:D69),0) -> 230546.97 | F55: =IFERROR(SUM('Data Sheet'!E62:E65)-SUM('Data Sheet'!E67:E69),0) -> 215044.77 | G55: =IFERROR(SUM('Data Sheet'!F62:F65)-SUM('Data Sheet'!F67:F69),0) -> 237822.85 | H55: =IFERROR(SUM('Data Sheet'!G62:G65)-SUM('Data Sheet'!G67:G69),0) -> 246009.78 | I55: =IFERROR(SUM('Data Sheet'!H62:H65)-SUM('Data Sheet'!H67:H69),0) -> 240709.84 | J55: =IFERROR(SUM('Data Sheet'!I62:I65)-SUM('Data Sheet'!I67:I69),0) -> 241165.51 | ... L55: =IFERROR(SUM('Data Sheet'!K62:K65)-SUM('Data Sheet'!K67:K69),0) -> 275622
B57: Receivables | C57: =IFERROR('Data Sheet'!B67,0) -> 13570.91 | D57: =IFERROR('Data Sheet'!C67,0) -> 14075.55 | E57: =IFERROR('Data Sheet'!D67,0) -> 19893.3 | F57: =IFERROR('Data Sheet'!E67,0) -> 18996.17 | G57: =IFERROR('Data Sheet'!F67,0) -> 11172.69 | H57: =IFERROR('Data Sheet'!G67,0) -> 12679.08 | I57: =IFERROR('Data Sheet'!H67,0) -> 12442.12 | J57: =IFERROR('Data Sheet'!I67,0) -> 15737.97 | ... L57: =IFERROR('Data Sheet'!K67,0) -> 13248
B58: Inventory | C58: =IFERROR('Data Sheet'!B68,0) -> 32655.73 | D58: =IFERROR('Data Sheet'!C68,0) -> 35085.31 | E58: =IFERROR('Data Sheet'!D68,0) -> 42137.63 | F58: =IFERROR('Data Sheet'!E68,0) -> 39013.73 | G58: =IFERROR('Data Sheet'!F68,0) -> 37456.88 | H58: =IFERROR('Data Sheet'!G68,0) -> 36088.59 | I58: =IFERROR('Data Sheet'!H68,0) -> 35240.34 | J58: =IFERROR('Data Sheet'!I68,0) -> 40755.39 | ... L58: =IFERROR('Data Sheet'!K68,0) -> 47269
B59: Cash & Bank | C59: =IFERROR('Data Sheet'!B69,0) -> 30460.4 | D59: =IFERROR('Data Sheet'!C69,0) -> 36077.88 | E59: =IFERROR('Data Sheet'!D69,0) -> 34613.91 | F59: =IFERROR('Data Sheet'!E69,0) -> 32648.82 | G59: =IFERROR('Data Sheet'!F69,0) -> 33726.97 | H59: =IFERROR('Data Sheet'!G69,0) -> 46792.46 | I59: =IFERROR('Data Sheet'!H69,0) -> 40669.19 | J59: =IFERROR('Data Sheet'!I69,0) -> 37015.56 | ... L59: =IFERROR('Data Sheet'!K69,0) -> 40834
B60: Total current Assets | C60: =IFERROR(SUM(C57:C59),0) -> 76687.04 | D60: =IFERROR(SUM(D57:D59),0) -> 85238.74 | E60: =IFERROR(SUM(E57:E59),0) -> 96644.84 | F60: =IFERROR(SUM(F57:F59),0) -> 90658.72 | G60: =IFERROR(SUM(G57:G59),0) -> 82356.54 | H60: =IFERROR(SUM(H57:H59),0) -> 95560.13 | I60: =IFERROR(SUM(I57:I59),0) -> 88351.65 | J60: =IFERROR(SUM(J57:J59),0) -> 93508.92 | ... L60: =IFERROR(SUM(L57:L59),0) -> 101351
B62: Total Assets | C62: =IFERROR(SUM(C55,C60),0) -> 263184.12 | D62: =IFERROR(SUM(D55,D60),0) -> 272580.36 | E62: =IFERROR(SUM(E55,E60),0) -> 327191.81 | F62: =IFERROR(SUM(F55,F60),0) -> 305703.49 | G62: =IFERROR(SUM(G55,G60),0) -> 320179.39 | H62: =IFERROR(SUM(H55,H60),0) -> 341569.91 | I62: =IFERROR(SUM(I55,I60),0) -> 329061.49 | J62: =IFERROR(SUM(J55,J60),0) -> 334674.43 | ... L62: =IFERROR(SUM(L55,L60),0) -> 376973
B64: CHECK | C64: =IF(C62=C49,TRUE,FALSE) -> TRUE | D64: =IF(D62=D49,TRUE,FALSE) -> TRUE | E64: =IF(E62=E49,TRUE,FALSE) -> TRUE | F64: =IF(F62=F49,TRUE,FALSE) -> TRUE | G64: =IF(G62=G49,TRUE,FALSE) -> TRUE | H64: =IF(H62=H49,TRUE,FALSE) -> TRUE | I64: =IF(I62=I49,TRUE,FALSE) -> TRUE | J64: =IF(J62=J49,TRUE,FALSE) -> TRUE | ... L64: =IF(L62=L49,TRUE,FALSE) -> TRUE
A66: # | B66: Cashflow Statement
B67: Operating activities
B68: Profit from operations | C68: =IFERROR('Cashflow Data'!E4,0) -> 3502 | D68: =IFERROR('Cashflow Data'!F4,0) -> 1662 | E68: =IFERROR('Cashflow Data'!G4,0) -> 4091 | F68: =IFERROR('Cashflow Data'!H4,0) -> 6167 | G68: =IFERROR('Cashflow Data'!I4,0) -> 439 | H68: =IFERROR('Cashflow Data'!J4,0) -> 1961 | I68: =IFERROR('Cashflow Data'!K4,0) -> 2683 | J68: =IFERROR('Cashflow Data'!L4,0) -> 5010 | ... L68: =IFERROR('Cashflow Data'!N4,0) -> 8615
B69: Receivables | C69: =IFERROR('Cashflow Data'!E5,0) -> -678 | D69: =IFERROR('Cashflow Data'!F5,0) -> -199 | E69: =IFERROR('Cashflow Data'!G5,0) -> -1217 | F69: =IFERROR('Cashflow Data'!H5,0) -> 164 | G69: =IFERROR('Cashflow Data'!I5,0) -> 1168 | H69: =IFERROR('Cashflow Data'!J5,0) -> -142 | I69: =IFERROR('Cashflow Data'!K5,0) -> -1016 | J69: =IFERROR('Cashflow Data'!L5,0) -> -306 | ... L69: =IFERROR('Cashflow Data'!N5,0) -> 388
B70: Inventory | C70: =IFERROR('Cashflow Data'!E6,0) -> -235 | D70: =IFERROR('Cashflow Data'!F6,0) -> -572 | E70: =IFERROR('Cashflow Data'!G6,0) -> -278 | F70: =IFERROR('Cashflow Data'!H6,0) -> 966 | G70: =IFERROR('Cashflow Data'!I6,0) -> 730 | H70: =IFERROR('Cashflow Data'!J6,0) -> -765 | I70: =IFERROR('Cashflow Data'!K6,0) -> -1201 | J70: =IFERROR('Cashflow Data'!L6,0) -> 658 | ... L70: =IFERROR('Cashflow Data'!N6,0) -> 257
B71: Payables | C71: =IFERROR('Cashflow Data'!E7,0) -> 76 | D71: =IFERROR('Cashflow Data'!F7,0) -> 2314 | E71: =IFERROR('Cashflow Data'!G7,0) -> 2764 | F71: =IFERROR('Cashflow Data'!H7,0) -> -725 | G71: =IFERROR('Cashflow Data'!I7,0) -> -2689 | H71: =IFERROR('Cashflow Data'!J7,0) -> 4965 | I71: =IFERROR('Cashflow Data'!K7,0) -> 5285 | J71: =IFERROR('Cashflow Data'!L7,0) -> -957 | ... L71: =IFERROR('Cashflow Data'!N7,0) -> -56
B72: Loans Advances | C72: =IFERROR('Cashflow Data'!E8,0) -> -55 | D72: =IFERROR('Cashflow Data'!F8,0) -> 0 | E72: =IFERROR('Cashflow Data'!G8,0) -> 0 | F72: =IFERROR('Cashflow Data'!H8,0) -> 0 | G72: =IFERROR('Cashflow Data'!I8,0) -> 0 | H72: =IFERROR('Cashflow Data'!J8,0) -> 0 | I72: =IFERROR('Cashflow Data'!K8,0) -> 0 | J72: =IFERROR('Cashflow Data'!L8,0) -> 0 | ... L72: =IFERROR('Cashflow Data'!N8,0) -> 0
B73: Other WC items | C73: =IFERROR('Cashflow Data'!E9,0) -> 115 | D73: =IFERROR('Cashflow Data'!F9,0) -> -1636 | E73: =IFERROR('Cashflow Data'!G9,0) -> -1217 | F73: =IFERROR('Cashflow Data'!H9,0) -> -97 | G73: =IFERROR('Cashflow Data'!I9,0) -> -1011 | H73: =IFERROR('Cashflow Data'!J9,0) -> 725 | I73: =IFERROR('Cashflow Data'!K9,0) -> -314 | J73: =IFERROR('Cashflow Data'!L9,0) -> 539 | ... L73: =IFERROR('Cashflow Data'!N9,0) -> 583
B74: Working capital changes | C74: =IFERROR('Cashflow Data'!E10,0) -> -776 | D74: =IFERROR('Cashflow Data'!F10,0) -> -93 | E74: =IFERROR('Cashflow Data'!G10,0) -> 52 | F74: =IFERROR('Cashflow Data'!H10,0) -> 308 | G74: =IFERROR('Cashflow Data'!I10,0) -> -1801 | H74: =IFERROR('Cashflow Data'!J10,0) -> 4783 | I74: =IFERROR('Cashflow Data'!K10,0) -> 2755 | J74: =IFERROR('Cashflow Data'!L10,0) -> -67 | ... L74: =IFERROR('Cashflow Data'!N10,0) -> 1172
B75: Direct taxes | C75: =IFERROR('Cashflow Data'!E11,0) -> -24 | D75: =IFERROR('Cashflow Data'!F11,0) -> -115 | E75: =IFERROR('Cashflow Data'!G11,0) -> -8 | F75: =IFERROR('Cashflow Data'!H11,0) -> -182 | G75: =IFERROR('Cashflow Data'!I11,0) -> -93 | H75: =IFERROR('Cashflow Data'!J11,0) -> -63 | I75: =IFERROR('Cashflow Data'!K11,0) -> -156 | J75: =IFERROR('Cashflow Data'!L11,0) -> -168 | ... L75: =IFERROR('Cashflow Data'!N11,0) -> 8
B76: Cash from operating activities | C76: =IFERROR(SUM(C68:C75),0) -> 1925 | D76: =IFERROR(SUM(D68:D75),0) -> 1361 | E76: =IFERROR(SUM(E68:E75),0) -> 4187 | F76: =IFERROR(SUM(F68:F75),0) -> 6601 | G76: =IFERROR(SUM(G68:G75),0) -> -3257 | H76: =IFERROR(SUM(H68:H75),0) -> 11464 | I76: =IFERROR(SUM(I68:I75),0) -> 8036 | J76: =IFERROR(SUM(J68:J75),0) -> 4709 | ... L76: =IFERROR(SUM(L68:L75),0) -> 10967
B78: Investing Activities
B79: Fixed assets purchased | C79: =IFERROR('Cashflow Data'!E13,0) -> -3284 | D79: =IFERROR('Cashflow Data'!F13,0) -> -3514 | E79: =IFERROR('Cashflow Data'!G13,0) -> -2823 | F79: =IFERROR('Cashflow Data'!H13,0) -> -4783 | G79: =IFERROR('Cashflow Data'!I13,0) -> -4669 | H79: =IFERROR('Cashflow Data'!J13,0) -> -1856 | I79: =IFERROR('Cashflow Data'!K13,0) -> -1831 | J79: =IFERROR('Cashflow Data'!L13,0) -> -1697 | ... L79: =IFERROR('Cashflow Data'!N13,0) -> -2043
B80: Fixed assets sold | C80: =IFERROR('Cashflow Data'!E14,0) -> 34 | D80: =IFERROR('Cashflow Data'!F14,0) -> 17 | E80: =IFERROR('Cashflow Data'!G14,0) -> 28 | F80: =IFERROR('Cashflow Data'!H14,0) -> 30 | G80: =IFERROR('Cashflow Data'!I14,0) -> 155 | H80: =IFERROR('Cashflow Data'!J14,0) -> 178 | I80: =IFERROR('Cashflow Data'!K14,0) -> 100 | J80: =IFERROR('Cashflow Data'!L14,0) -> 123 | ... L80: =IFERROR('Cashflow Data'!N14,0) -> 113
B81: Investments purchased | C81: =IFERROR('Cashflow Data'!E15,0) -> -1669 | D81: =IFERROR('Cashflow Data'!F15,0) -> -537 | E81: =IFERROR('Cashflow Data'!G15,0) -> 0 | F81: =IFERROR('Cashflow Data'!H15,0) -> 0 | G81: =IFERROR('Cashflow Data'!I15,0) -> 0 | H81: =IFERROR('Cashflow Data'!J15,0) -> -673 | I81: =IFERROR('Cashflow Data'!K15,0) -> -3560 | J81: =IFERROR('Cashflow Data'!L15,0) -> 0 | ... L81: =IFERROR('Cashflow Data'!N15,0) -> -793
B82: Investments sold | C82: =IFERROR('Cashflow Data'!E16,0) -> 832 | D82: =IFERROR('Cashflow Data'!F16,0) -> 0 | E82: =IFERROR('Cashflow Data'!G16,0) -> 1026 | F82: =IFERROR('Cashflow Data'!H16,0) -> 952 | G82: =IFERROR('Cashflow Data'!I16,0) -> 359 | H82: =IFERROR('Cashflow Data'!J16,0) -> 4 | I82: =IFERROR('Cashflow Data'!K16,0) -> 0 | J82: =IFERROR('Cashflow Data'!L16,0) -> 2079 | ... L82: =IFERROR('Cashflow Data'!N16,0) -> 35
B83: Interest received | C83: =IFERROR('Cashflow Data'!E17,0) -> 254 | D83: =IFERROR('Cashflow Data'!F17,0) -> 259 | E83: =IFERROR('Cashflow Data'!G17,0) -> 399 | F83: =IFERROR('Cashflow Data'!H17,0) -> 327 | G83: =IFERROR('Cashflow Data'!I17,0) -> 471 | H83: =IFERROR('Cashflow Data'!J17,0) -> 154 | I83: =IFERROR('Cashflow Data'!K17,0) -> 301 | J83: =IFERROR('Cashflow Data'!L17,0) -> 185 | ... L83: =IFERROR('Cashflow Data'!N17,0) -> 346
B84: Dividends received | C84: =IFERROR('Cashflow Data'!E18,0) -> 1042 | D84: =IFERROR('Cashflow Data'!F18,0) -> 673 | E84: =IFERROR('Cashflow Data'!G18,0) -> 1055 | F84: =IFERROR('Cashflow Data'!H18,0) -> 1569 | G84: =IFERROR('Cashflow Data'!I18,0) -> 241 | H84: =IFERROR('Cashflow Data'!J18,0) -> 20 | I84: =IFERROR('Cashflow Data'!K18,0) -> 80 | J84: =IFERROR('Cashflow Data'!L18,0) -> 319 | ... L84: =IFERROR('Cashflow Data'!N18,0) -> 1988
B85: Invest in subsidiaries | C85: =IFERROR('Cashflow Data'!E19,0) -> -60 | D85: =IFERROR('Cashflow Data'!F19,0) -> -139 | E85: =IFERROR('Cashflow Data'!G19,0) -> -300 | F85: =IFERROR('Cashflow Data'!H19,0) -> -838 | G85: =IFERROR('Cashflow Data'!I19,0) -> -467 | H85: =IFERROR('Cashflow Data'!J19,0) -> 0 | I85: =IFERROR('Cashflow Data'!K19,0) -> -871 | J85: =IFERROR('Cashflow Data'!L19,0) -> -191 | ... L85: =IFERROR('Cashflow Data'!N19,0) -> -1121
B86: Loans to subsidiaries | C86: =IFERROR('Cashflow Data'!E20,0) -> -78 | D86: =IFERROR('Cashflow Data'!F20,0) -> 0 | E86: =IFERROR('Cashflow Data'!G20,0) -> 0 | F86: =IFERROR('Cashflow Data'!H20,0) -> 0 | G86: =IFERROR('Cashflow Data'!I20,0) -> -8 | H86: =IFERROR('Cashflow Data'!J20,0) -> -57 | I86: =IFERROR('Cashflow Data'!K20,0) -> -51 | J86: =IFERROR('Cashflow Data'!L20,0) -> -45 | ... L86: =IFERROR('Cashflow Data'!N20,0) -> -166
B87: Investment in group cos | C87: =IFERROR('Cashflow Data'!E21,0) -> 0 | D87: =IFERROR('Cashflow Data'!F21,0) -> 0 | E87: =IFERROR('Cashflow Data'!G21,0) -> -44 | F87: =IFERROR('Cashflow Data'!H21,0) -> 0 | G87: =IFERROR('Cashflow Data'!I21,0) -> 0 | H87: =IFERROR('Cashflow Data'!J21,0) -> 0 | I87: =IFERROR('Cashflow Data'!K21,0) -> 0 | J87: =IFERROR('Cashflow Data'!L21,0) -> 0 | ... L87: =IFERROR('Cashflow Data'!N21,0) -> 0
B88: Redemp n Canc of Shares | C88: =IFERROR('Cashflow Data'!E22,0) -> 0 | D88: =IFERROR('Cashflow Data'!F22,0) -> 0 | E88: =IFERROR('Cashflow Data'!G22,0) -> 0 | F88: =IFERROR('Cashflow Data'!H22,0) -> 0 | G88: =IFERROR('Cashflow Data'!I22,0) -> 26 | H88: =IFERROR('Cashflow Data'!J22,0) -> 10 | I88: =IFERROR('Cashflow Data'!K22,0) -> 234 | J88: =IFERROR('Cashflow Data'!L22,0) -> 0 | ... L88: =IFERROR('Cashflow Data'!N22,0) -> 150
B89: Acquisition of companies | C89: =IFERROR('Cashflow Data'!E23,0) -> 0 | D89: =IFERROR('Cashflow Data'!F23,0) -> 0 | E89: =IFERROR('Cashflow Data'!G23,0) -> 0 | F89: =IFERROR('Cashflow Data'!H23,0) -> 0 | G89: =IFERROR('Cashflow Data'!I23,0) -> 0 | H89: =IFERROR('Cashflow Data'!J23,0) -> 0 | I89: =IFERROR('Cashflow Data'!K23,0) -> 0 | J89: =IFERROR('Cashflow Data'!L23,0) -> 0 | ... L89: =IFERROR('Cashflow Data'!N23,0) -> 0
B90: Inter corporate deposits | C90: =IFERROR('Cashflow Data'!E24,0) -> -35 | D90: =IFERROR('Cashflow Data'!F24,0) -> 20 | E90: =IFERROR('Cashflow Data'!G24,0) -> 60 | F90: =IFERROR('Cashflow Data'!H24,0) -> -2 | G90: =IFERROR('Cashflow Data'!I24,0) -> -10 | H90: =IFERROR('Cashflow Data'!J24,0) -> -30 | I90: =IFERROR('Cashflow Data'!K24,0) -> 0 | J90: =IFERROR('Cashflow Data'!L24,0) -> -15 | ... L90: =IFERROR('Cashflow Data'!N24,0) -> -2923
... B92: Cash from investing Activities | C92: =IFERROR('Cashflow Data'!E26,0) -> -79 | D92: =IFERROR('Cashflow Data'!F26,0) -> 1209 | E92: =IFERROR('Cashflow Data'!G26,0) -> -3106 | F92: =IFERROR('Cashflow Data'!H26,0) -> -2530 | G92: =IFERROR('Cashflow Data'!I26,0) -> 7749 | H92: =IFERROR('Cashflow Data'!J26,0) -> -3472 | I92: =IFERROR('Cashflow Data'!K26,0) -> -516 | J92: =IFERROR('Cashflow Data'!L26,0) -> -7021 | ... L92: =IFERROR('Cashflow Data'!N26,0) -> -8932
B94: Financing Activities
B95: Proceeds from shares | C95: =IFERROR('Cashflow Data'!E27,0) -> 7433 | D95: =IFERROR('Cashflow Data'!F27,0) -> 5 | E95: =IFERROR('Cashflow Data'!G27,0) -> 0 | F95: =IFERROR('Cashflow Data'!H27,0) -> 0 | G95: =IFERROR('Cashflow Data'!I27,0) -> 3889 | H95: =IFERROR('Cashflow Data'!J27,0) -> 2603 | I95: =IFERROR('Cashflow Data'!K27,0) -> 19 | J95: =IFERROR('Cashflow Data'!L27,0) -> 20 | ... L95: =IFERROR('Cashflow Data'!N27,0) -> 1108
B96: Proceeds from borrowings | C96: =IFERROR('Cashflow Data'!E28,0) -> 3587 | D96: =IFERROR('Cashflow Data'!F28,0) -> 10687 | E96: =IFERROR('Cashflow Data'!G28,0) -> 6406 | F96: =IFERROR('Cashflow Data'!H28,0) -> 8805 | G96: =IFERROR('Cashflow Data'!I28,0) -> 15462 | H96: =IFERROR('Cashflow Data'!J28,0) -> 6985 | I96: =IFERROR('Cashflow Data'!K28,0) -> 10408 | J96: =IFERROR('Cashflow Data'!L28,0) -> 887 | ... L96: =IFERROR('Cashflow Data'!N28,0) -> 2262
B97: Repayment of borrowings | C97: =IFERROR('Cashflow Data'!E29,0) -> -9013 | D97: =IFERROR('Cashflow Data'!F29,0) -> -7473 | E97: =IFERROR('Cashflow Data'!G29,0) -> -7410 | F97: =IFERROR('Cashflow Data'!H29,0) -> -8977 | G97: =IFERROR('Cashflow Data'!I29,0) -> -9128 | H97: =IFERROR('Cashflow Data'!J29,0) -> -10438 | I97: =IFERROR('Cashflow Data'!K29,0) -> -8517 | J97: =IFERROR('Cashflow Data'!L29,0) -> -5852 | ... L97: =IFERROR('Cashflow Data'!N29,0) -> -7281
B98: Interest paid fin | C98: =IFERROR('Cashflow Data'!E30,0) -> -2086 | D98: =IFERROR('Cashflow Data'!F30,0) -> -1936 | E98: =IFERROR('Cashflow Data'!G30,0) -> -2098 | F98: =IFERROR('Cashflow Data'!H30,0) -> -2355 | G98: =IFERROR('Cashflow Data'!I30,0) -> -2270 | H98: =IFERROR('Cashflow Data'!J30,0) -> -2427 | I98: =IFERROR('Cashflow Data'!K30,0) -> -2272 | J98: =IFERROR('Cashflow Data'!L30,0) -> -2008 | ... L98: =IFERROR('Cashflow Data'!N30,0) -> -1159
B99: Dividends paid | C99: =IFERROR('Cashflow Data'!E31,0) -> 0 | D99: =IFERROR('Cashflow Data'!F31,0) -> -73 | E99: =IFERROR('Cashflow Data'!G31,0) -> -3 | F99: =IFERROR('Cashflow Data'!H31,0) -> -3 | G99: =IFERROR('Cashflow Data'!I31,0) -> -4 | H99: =IFERROR('Cashflow Data'!J31,0) -> -2 | I99: =IFERROR('Cashflow Data'!K31,0) -> -2 | J99: =IFERROR('Cashflow Data'!L31,0) -> 0 | ... L99: =IFERROR('Cashflow Data'!N31,0) -> -2304
B100: Financial liabilities | C100: =IFERROR('Cashflow Data'!E32,0) -> 0 | D100: =IFERROR('Cashflow Data'!F32,0) -> 0 | E100: =IFERROR('Cashflow Data'!G32,0) -> 0 | F100: =IFERROR('Cashflow Data'!H32,0) -> 0 | G100: =IFERROR('Cashflow Data'!I32,0) -> -194 | H100: =IFERROR('Cashflow Data'!J32,0) -> -192 | I100: =IFERROR('Cashflow Data'!K32,0) -> -152 | J100: =IFERROR('Cashflow Data'!L32,0) -> -68 | ... L100: =IFERROR('Cashflow Data'!N32,0) -> -422
B101: Other financing items | C101: =IFERROR('Cashflow Data'!E33,0) -> 0 | D101: =IFERROR('Cashflow Data'!F33,0) -> 0 | E101: =IFERROR('Cashflow Data'!G33,0) -> 0 | F101: =IFERROR('Cashflow Data'!H33,0) -> 0 | G101: =IFERROR('Cashflow Data'!I33,0) -> -7 | H101: =IFERROR('Cashflow Data'!J33,0) -> 0 | I101: =IFERROR('Cashflow Data'!K33,0) -> 0 | J101: =IFERROR('Cashflow Data'!L33,0) -> 0 | ... L101: =IFERROR('Cashflow Data'!N33,0) -> -1136
B102: Cash from financing Activities | C102: =IFERROR('Cashflow Data'!E34,0) -> -639 | D102: =IFERROR('Cashflow Data'!F34,0) -> -198 | E102: =IFERROR('Cashflow Data'!G34,0) -> 318 | F102: =IFERROR('Cashflow Data'!H34,0) -> -59 | G102: =IFERROR('Cashflow Data'!I34,0) -> 1658 | H102: =IFERROR('Cashflow Data'!J34,0) -> 220 | I102: =IFERROR('Cashflow Data'!K34,0) -> 85 | J102: =IFERROR('Cashflow Data'!L34,0) -> -1329 | ... L102: =IFERROR('Cashflow Data'!N34,0) -> -2958
B104: Net cashflow | C104: =IFERROR(SUM(C95:C102),0) -> -718 | D104: =IFERROR(SUM(D95:D102),0) -> 1012 | E104: =IFERROR(SUM(E95:E102),0) -> -2787 | F104: =IFERROR(SUM(F95:F102),0) -> -2589 | G104: =IFERROR(SUM(G95:G102),0) -> 9406 | H104: =IFERROR(SUM(H95:H102),0) -> -3251 | I104: =IFERROR(SUM(I95:I102),0) -> -431 | J104: =IFERROR(SUM(J95:J102),0) -> -8350 | ... L104: =IFERROR(SUM(L95:L102),0) -> -11890

Sheet Ratio analysis
B2: ="Ratio Analysis - "&'Data Sheet'!B1 -> Ratio Analysis - TATA MOTORS LTD
B3: Years | C3: ='Data Sheet'!B16 -> 42460 | D3: ='Data Sheet'!C16 -> 42825 | E3: ='Data Sheet'!D16 -> 43190 | F3: ='Data Sheet'!E16 -> 43555 | G3: ='Data Sheet'!F16 -> 43921 | H3: ='Data Sheet'!G16 -> 44286 | I3: ='Data Sheet'!H16 -> 44651 | J3: ='Data Sheet'!I16 -> 45016 | ... L3: ='Data Sheet'!K16 -> 45747 | M3: Trend | N3: Mean | O3: Median
B4: SalesGrowth | D4: =IFERROR('Historical FS'!D6,0) -> -0.01228033 | E4: =IFERROR('Historical FS'!E6,0) -> 0.081047746 | F4: =IFERROR('Historical FS'!F6,0) -> 0.035629919 | G4: =IFERROR('Historical FS'!G6,0) -> -0.13536016 | H4: =IFERROR('Historical FS'!H6,0) -> -0.043181168 | I4: =IFERROR('Historical FS'!I6,0) -> 0.11472967 | J4: =IFERROR('Historical FS'!J6,0) -> 0.24245815 | K4: =IFERROR('Historical FS'!K6,0) -> 0.25450126 | L4: =IFERROR('Historical FS'!L6,0) -> 0.013084771 | N4: =MEDIAN(C4:L4) -> 0.035629919 | O4: =AVERAGE(C4:L4) -> 0.061181096
B5: GrossMargin | D5: =IFERROR('Historical FS'!C11/'Historical FS'!C5,0) -> 0.24734524 | E5: =IFERROR('Historical FS'!D11/'Historical FS'!D5,0) -> 0.18331406 | F5: =IFERROR('Historical FS'!E11/'Historical FS'!E5,0) -> 0.20246062 | G5: =IFERROR('Historical FS'!F11/'Historical FS'!F5,0) -> 0.20931233 | H5: =IFERROR('Historical FS'!G11/'Historical FS'!G5,0) -> 0.21126406 | I5: =IFERROR('Historical FS'!H11/'Historical FS'!H5,0) -> 0.25555793 | J5: =IFERROR('Historical FS'!I11/'Historical FS'!I5,0) -> 0.20949482 | K5: =IFERROR('Historical FS'!J11/'Historical FS'!J5,0) -> 0.17920812 | L5: =IFERROR('Historical FS'!K11/'Historical FS'!K5,0) -> 0.22235125 | N5: =MEDIAN(C5:L5) -> 0.20949482 | O5: =AVERAGE(C5:L5) -> 0.2133676
B6: EBITDA Growth | D6: =IFERROR('Historical FS'!D16/'Historical FS'!C16-1,0) -> -0.61482605 | E6: =IFERROR('Historical FS'!E16/'Historical FS'!D16-1,0) -> 0.85034807 | F6: =IFERROR('Historical FS'!F16/'Historical FS'!E16-1,0) -> 0.051393922 | G6: =IFERROR('Historical FS'!G16/'Historical FS'!F16-1,0) -> -0.21971653 | H6: =IFERROR('Historical FS'!H16/'Historical FS'!G16-1,0) -> 0.85553544 | I6: =IFERROR('Historical FS'!I16/'Historical FS'!H16-1,0) -> -0.33019883 | J6: =IFERROR('Historical FS'!J16/'Historical FS'!I16-1,0) -> -0.20244779 | K6: =IFERROR('Historical FS'!K16/'Historical FS'!J16-1,0) -> 1.4577846 | L6: =IFERROR('Historical FS'!L16/'Historical FS'!K16-1,0) -> 0.11328896 | N6: =MEDIAN(C6:L6) -> 0.051393922 | O6: =AVERAGE(C6:L6) -> 0.21790687
B7: EBIT Growth | D7: =IFERROR('Historical FS'!D25/'Historical FS'!C25-1,0) -> -1.4378672 | E7: =IFERROR('Historical FS'!E25/'Historical FS'!D25-1,0) -> -1.1535378 | F7: =IFERROR('Historical FS'!F25/'Historical FS'!E25-1,0) -> -1.5121951 | G7: =IFERROR('Historical FS'!G25/'Historical FS'!F25-1,0) -> 9.7537262 | H7: =IFERROR('Historical FS'!H25/'Historical FS'!G25-1,0) -> -2.609804 | I7: =IFERROR('Historical FS'!I25/'Historical FS'!H25-1,0) -> -1.6239074 | J7: =IFERROR('Historical FS'!J25/'Historical FS'!I25-1,0) -> 1.0544819 | K7: =IFERROR('Historical FS'!K25/'Historical FS'!J25-1,0) -> -2.547461 | L7: =IFERROR('Historical FS'!L25/'Historical FS'!K25-1,0) -> 0.63900499 | N7: =MEDIAN(C7:L7) -> -1.4378672 | O7: =AVERAGE(C7:L7) -> 0.062493397
B8: Net Profit Growth | D8: =IFERROR('Historical FS'!D31/'Historical FS'!C31-1,0) -> -1.7701611 | E8: =IFERROR('Historical FS'!E31/'Historical FS'!D31-1,0) -> -0.69706036 | F8: =IFERROR('Historical FS'!F31/'Historical FS'!E31-1,0) -> -1.578659 | G8: =IFERROR('Historical FS'!G31/'Historical FS'!F31-1,0) -> -4.5579175 | H8: =IFERROR('Historical FS'!H31/'Historical FS'!G31-1,0) -> -2.1293283 | I8: =IFERROR('Historical FS'!I31/'Historical FS'!H31-1,0) -> -2.4026447 | J8: =IFERROR('Historical FS'!J31/'Historical FS'!I31-1,0) -> 0.29200584 | K8: =IFERROR('Historical FS'!K31/'Historical FS'!J31-1,0) -> -2.7642314 | L8: =IFERROR('Historical FS'!L31/'Historical FS'!K31-1,0) -> -0.076874764 | N8: =MEDIAN(C8:L8) -> -1.7701611 | O8: =AVERAGE(C8:L8) -> -1.7427635
B9: Dividend Growth | D9: =IFERROR('Historical FS'!D39/'Historical FS'!C39-1,0) -> -1 | E9: =IFERROR('Historical FS'!E39/'Historical FS'!D39-1,0) -> 0 | F9: =IFERROR('Historical FS'!F39/'Historical FS'!E39-1,0) -> 0 | G9: =IFERROR('Historical FS'!G39/'Historical FS'!F39-1,0) -> 0 | H9: =IFERROR('Historical FS'!H39/'Historical FS'!G39-1,0) -> 0 | I9: =IFERROR('Historical FS'!I39/'Historical FS'!H39-1,0) -> 0 | J9: =IFERROR('Historical FS'!J39/'Historical FS'!I39-1,0) -> 0 | K9: =IFERROR('Historical FS'!K39/'Historical FS'!J39-1,0) -> 2.0019611 | L9: =IFERROR('Historical FS'!L39/'Historical FS'!K39-1,0) -> -0.0010201355 | N9: =MEDIAN(C9:L9) -> 0 | O9: =AVERAGE(C9:L9) -> 0.11121566
B11: Gross Margin | C11: =IFERROR('Historical FS'!C11/'Historical FS'!C5,0) -> 0.24734524 | D11: =IFERROR('Historical FS'!D11/'Historical FS'!D5,0) -> 0.18331406 | E11: =IFERROR('Historical FS'!E11/'Historical FS'!E5,0) -> 0.20246062 | F11: =IFERROR('Historical FS'!F11/'Historical FS'!F5,0) -> 0.20931233 | G11: =IFERROR('Historical FS'!G11/'Historical FS'!G5,0) -> 0.21126406 | H11: =IFERROR('Historical FS'!H11/'Historical FS'!H5,0) -> 0.25555793 | I11: =IFERROR('Historical FS'!I11/'Historical FS'!I5,0) -> 0.20949482 | J11: =IFERROR('Historical FS'!J11/'Historical FS'!J5,0) -> 0.17920812 | ... L11: =IFERROR('Historical FS'!L11/'Historical FS'!L5,0) -> 0.23779665 | N11: =MEDIAN(C11:L11) -> 0.21037944 | O11: =AVERAGE(C11:L11) -> 0.21581051
B12: Operating Margin
B13: EBITDA Margin | C13: =IFERROR('Historical FS'!C17,0) -> 0.14061845 | D13: =IFERROR('Historical FS'!D17,0) -> 0.054835969 | E13: =IFERROR('Historical FS'!E17,0) -> 0.0938586 | F13: =IFERROR('Historical FS'!F17,0) -> 0.095287284 | G13: =IFERROR('Historical FS'!G17,0) -> 0.085990825 | H13: =IFERROR('Historical FS'!H17,0) -> 0.16675991 | I13: =IFERROR('Historical FS'!I17,0) -> 0.10020006 | J13: =IFERROR('Historical FS'!J17,0) -> 0.064319897 | ... L13: =IFERROR('Historical FS'!L17,0) -> 0.13847781 | N13: =MEDIAN(C13:L13) -> 0.097743673 | O13: =AVERAGE(C13:L13) -> 0.10663626
B14: EBIT Margin | C14: =IFERROR(('Historical FS'!C16-'Historical FS'!C22)/'Historical FS'!C5,0) -> 0.079417028 | D14: =IFERROR(('Historical FS'!D16-'Historical FS'!D22)/'Historical FS'!D5,0) -> -0.011554418 | E14: =IFERROR(('Historical FS'!E16-'Historical FS'!E22)/'Historical FS'!E5,0) -> 0.019931128 | F14: =IFERROR(('Historical FS'!F16-'Historical FS'!F22)/'Historical FS'!F5,0) -> 0.017156678 | G14: =IFERROR(('Historical FS'!G16-'Historical FS'!G22)/'Historical FS'!G5,0) -> 0.0039224268 | H14: =IFERROR(('Historical FS'!H16-'Historical FS'!H22)/'Historical FS'!H5,0) -> 0.072495679 | I14: =IFERROR(('Historical FS'!I16-'Historical FS'!I22)/'Historical FS'!I5,0) -> 0.011008584 | J14: =IFERROR(('Historical FS'!J16-'Historical FS'!J22)/'Historical FS'!J5,0) -> -0.0075377138 | ... L14: =IFERROR(('Historical FS'!L16-'Historical FS'!L22)/'Historical FS'!L5,0) -> 0.0855866 | N14: =MEDIAN(C14:L14) -> 0.018543903 | O14: =AVERAGE(C14:L14) -> 0.033367942
B15: EBT Margin | C15: =IFERROR('Historical FS'!C26,0) -> 0.061511301 | D15: =IFERROR('Historical FS'!D26,0) -> -0.027268648 | E15: =IFERROR('Historical FS'!E26,0) -> 0.0038728799 | F15: =IFERROR('Historical FS'!F26,0) -> -0.0019154238 | G15: =IFERROR('Historical FS'!G26,0) -> -0.02382257 | H15: =IFERROR('Historical FS'!H26,0) -> 0.040080386 | I15: =IFERROR('Historical FS'!I26,0) -> -0.022432748 | J15: =IFERROR('Historical FS'!J26,0) -> -0.037093946 | ... L15: =IFERROR('Historical FS'!L26,0) -> 0.074026314 | N15: =MEDIAN(C15:L15) -> 0.00097872806 | O15: =AVERAGE(C15:L15) -> 0.011271392
B16: Net Profit Margin | C16: =IFERROR('Historical FS'!C32,0) -> 0.050432382 | D16: =IFERROR('Historical FS'!D32,0) -> -0.039323969 | E16: =IFERROR('Historical FS'!E32,0) -> -0.01101967 | F16: =IFERROR('Historical FS'!F32,0) -> 0.0061572493 | G16: =IFERROR('Historical FS'!G32,0) -> -0.025336544 | H16: =IFERROR('Historical FS'!H32,0) -> 0.029904592 | I16: =IFERROR('Historical FS'!I32,0) -> -0.037628421 | J16: =IFERROR('Historical FS'!J32,0) -> -0.039128995 | ... L16: =IFERROR('Historical FS'!L32,0) -> 0.050141575 | N16: =MEDIAN(C16:L16) -> -0.0024312102 | O16: =AVERAGE(C16:L16) -> 0.0039226125
B18: SalesExpenses%Sales | C18: =IFERROR('Historical FS'!C14,0) -> 0.10672679 | D18: =IFERROR('Historical FS'!D14,0) -> 0.1284781 | E18: =IFERROR('Historical FS'!E14,0) -> 0.10860202 | F18: =IFERROR('Historical FS'!F14,0) -> 0.11402505 | G18: =IFERROR('Historical FS'!G14,0) -> 0.12527324 | H18: =IFERROR('Historical FS'!H14,0) -> 0.088798023 | I18: =IFERROR('Historical FS'!I14,0) -> 0.10929475 | J18: =IFERROR('Historical FS'!J14,0) -> 0.11488822 | ... L18: =IFERROR('Historical FS'!L14,0) -> 0.099318846 | N18: =MEDIAN(C18:L18) -> 0.10894839 | O18: =AVERAGE(C18:L18) -> 0.10917425
B19: Depreciation%Sales | C19: =IFERROR('Historical FS'!C23,0) -> 0.061201426 | D19: =IFERROR('Historical FS'!D23,0) -> 0.066390387 | E19: =IFERROR('Historical FS'!E23,0) -> 0.073927472 | F19: =IFERROR('Historical FS'!F23,0) -> 0.078130605 | G19: =IFERROR('Historical FS'!G23,0) -> 0.082068398 | H19: =IFERROR('Historical FS'!H23,0) -> 0.094264231 | I19: =IFERROR('Historical FS'!I23,0) -> 0.089191478 | J19: =IFERROR('Historical FS'!J23,0) -> 0.071857611 | ... L19: =IFERROR('Historical FS'!L23,0) -> 0.052891209 | N19: =MEDIAN(C19:L19) -> 0.072892542 | O19: =AVERAGE(C19:L19) -> 0.073268318
B20: OperatingIncome%Sales | C20: =C14 -> 0.079417028 | D20: =D14 -> -0.011554418 | E20: =E14 -> 0.019931128 | F20: =F14 -> 0.017156678 | G20: =G14 -> 0.0039224268 | H20: =H14 -> 0.072495679 | I20: =I14 -> 0.011008584 | J20: =J14 -> -0.0075377138 | ... L20: =L14 -> 0.0855866 | N20: =MEDIAN(C20:L20) -> 0.018543903 | O20: =AVERAGE(C20:L20) -> 0.033367942
B22: Return on Capital Employed | C22: =IFERROR(('Historical FS'!C16-'Historical FS'!C19) / SUM('Historical FS'!C45:C47),0) -> 0.22591622 | D22: =IFERROR(('Historical FS'!D16-'Historical FS'!D19) / SUM('Historical FS'!D45:D47),0) -> 0.077201718 | E22: =IFERROR(('Historical FS'!E16-'Historical FS'!E19) / SUM('Historical FS'!E45:E47),0) -> 0.12302272 | F22: =IFERROR(('Historical FS'!F16-'Historical FS'!F19) / SUM('Historical FS'!F45:F47),0) -> 0.1383325 | G22: =IFERROR(('Historical FS'!G16-'Historical FS'!G19) / SUM('Historical FS'!G45:G47),0) -> 0.080941236 | H22: =IFERROR(('Historical FS'!H16-'Historical FS'!H19) / SUM('Historical FS'!H45:H47),0) -> 0.1700225 | I22: =IFERROR(('Historical FS'!I16-'Historical FS'!I19) / SUM('Historical FS'!I45:I47),0) -> 0.097320474 | J22: =IFERROR(('Historical FS'!J16-'Historical FS'!J19) / SUM('Historical FS'!J45:J47),0) -> 0.067027417 | ... L22: =IFERROR(('Historical FS'!L16-'Historical FS'!L19) / SUM('Historical FS'!L45:L47),0) -> 0.29733488 | N22: =MEDIAN(C22:L22) -> 0.13067761 | O22: =AVERAGE(C22:L22) -> 0.15221894
B23: Retained Earnings% | C23: =IFERROR('Historical FS'!C42,0) -> 0.99506766 | D23: =IFERROR('Historical FS'!D42,0) -> 0 | E23: =IFERROR('Historical FS'!E42,0) -> 0 | F23: =IFERROR('Historical FS'!F42,0) -> 1 | G23: =IFERROR('Historical FS'!G42,0) -> 0 | H23: =IFERROR('Historical FS'!H42,0) -> 1 | I23: =IFERROR('Historical FS'!I42,0) -> 0 | J23: =IFERROR('Historical FS'!J42,0) -> 0 | ... L23: =IFERROR('Historical FS'!L42,0) -> 0.89985032 | N23: =MEDIAN(C23:L23) -> 0.44992516 | O23: =AVERAGE(C23:L23) -> 0.47985733
B24: Return on Equity% | C24: =IFERROR('Historical FS'!C31/SUM('Historical FS'!C45:C46),0) -> 0.17441317 | D24: =IFERROR('Historical FS'!D31/SUM('Historical FS'!D45:D46),0) -> -0.18265647 | E24: =IFERROR('Historical FS'!E31/SUM('Historical FS'!E45:E46),0) -> -0.033667194 | F24: =IFERROR('Historical FS'!F31/SUM('Historical FS'!F45:F46),0) -> 0.030892715 | G24: =IFERROR('Historical FS'!G31/SUM('Historical FS'!G45:G46),0) -> -0.1048623 | H24: =IFERROR('Historical FS'!H31/SUM('Historical FS'!H45:H46),0) -> 0.13521183 | I24: =IFERROR('Historical FS'!I31/SUM('Historical FS'!I45:I46),0) -> -0.23513192 | J24: =IFERROR('Historical FS'!J31/SUM('Historical FS'!J45:J46),0) -> -0.29869385 | ... L24: =IFERROR('Historical FS'!L31/SUM('Historical FS'!L45:L46),0) -> 0.1898247 | N24: =MEDIAN(C24:L24) -> -0.0013872397 | O24: =AVERAGE(C24:L24) -> -0.004342154
B25: Self Sustained Growth Rate | C25: =IFERROR(C23*C24,0) -> 0.1735529 | D25: =IFERROR(D23*D24,0) -> 0 | E25: =IFERROR(E23*E24,0) -> 0 | F25: =IFERROR(F23*F24,0) -> 0.030892715 | G25: =IFERROR(G23*G24,0) -> 0 | H25: =IFERROR(H23*H24,0) -> 0.13521183 | I25: =IFERROR(I23*I24,0) -> 0 | J25: =IFERROR(J23*J24,0) -> 0 | ... L25: =IFERROR(L23*L24,0) -> 0.17081382 | N25: =MEDIAN(C25:L25) -> 0.015446358 | O25: =AVERAGE(C25:L25) -> 0.076462233
B26: Interest Coverage Ratio | C26: =IFERROR(('Historical FS'!C16-'Historical FS'!C19)/'Historical FS'!C19,0) -> 6.8532669 | D26: =IFERROR(('Historical FS'!D16-'Historical FS'!D19)/'Historical FS'!D19,0) -> 2.4895741 | E26: =IFERROR(('Historical FS'!E16-'Historical FS'!E19)/'Historical FS'!E19,0) -> 4.8448841 | F26: =IFERROR(('Historical FS'!F16-'Historical FS'!F19)/'Historical FS'!F19,0) -> 3.9961605 | G26: =IFERROR(('Historical FS'!G16-'Historical FS'!G19)/'Historical FS'!G19,0) -> 2.0993272 | H26: =IFERROR(('Historical FS'!H16-'Historical FS'!H19)/'Historical FS'!H19,0) -> 4.1444826 | I26: =IFERROR(('Historical FS'!I16-'Historical FS'!I19)/'Historical FS'!I19,0) -> 1.996294 | J26: =IFERROR(('Historical FS'!J16-'Historical FS'!J19)/'Historical FS'!J19,0) -> 1.1761873 | ... L26: =IFERROR(('Historical FS'!L16-'Historical FS'!L19)/'Historical FS'!L19,0) -> 10.978753 | N26: =MEDIAN(C26:L26) -> 4.0703216 | O26: =AVERAGE(C26:L26) -> 4.4780931
B28: Debtor Turnover Ratio | C28: =IFERROR('Historical FS'!C5/'Historical FS'!C57,0) -> 20.119918 | D28: =IFERROR('Historical FS'!D5/'Historical FS'!D57,0) -> 19.160353 | E28: =IFERROR('Historical FS'!E5/'Historical FS'!E57,0) -> 14.655712 | F28: =IFERROR('Historical FS'!F5/'Historical FS'!F57,0) -> 15.894699 | G28: =IFERROR('Historical FS'!G5/'Historical FS'!G57,0) -> 23.366617 | H28: =IFERROR('Historical FS'!H5/'Historical FS'!H57,0) -> 19.701331 | I28: =IFERROR('Historical FS'!I5/'Historical FS'!I57,0) -> 22.379918 | J28: =IFERROR('Historical FS'!J5/'Historical FS'!J57,0) -> 21.982948 | ... L28: =IFERROR('Historical FS'!L5/'Historical FS'!L57,0) -> 33.189538 | N28: =MEDIAN(C28:L28) -> 21.051433 | O28: =AVERAGE(C28:L28) -> 21.605368
B29: Creditor Turnover Ratio | C29: =IFERROR('Historical FS'!C5/'Historical FS'!C48,0) -> 2.3769604 | D29: =IFERROR('Historical FS'!D5/'Historical FS'!D48,0) -> 1.9842808 | E29: =IFERROR('Historical FS'!E5/'Historical FS'!E48,0) -> 2.041478 | F29: =IFERROR('Historical FS'!F5/'Historical FS'!F48,0) -> 2.1667848 | G29: =IFERROR('Historical FS'!G5/'Historical FS'!G48,0) -> 1.9731057 | H29: =IFERROR('Historical FS'!H5/'Historical FS'!H48,0) -> 1.7323685 | I29: =IFERROR('Historical FS'!I5/'Historical FS'!I48,0) -> 2.0170312 | J29: =IFERROR('Historical FS'!J5/'Historical FS'!J48,0) -> 2.2286057 | ... L29: =IFERROR('Historical FS'!L5/'Historical FS'!L48,0) -> 2.3228767 | N29: =MEDIAN(C29:L29) -> 2.1041314 | O29: =AVERAGE(C29:L29) -> 2.1290872
B30: Inventory Turnover | C30: =IFERROR('Historical FS'!C5/'Historical FS'!C58,0) -> 8.3613381 | D30: =IFERROR('Historical FS'!D5/'Historical FS'!D58,0) -> 7.6867643 | E30: =IFERROR('Historical FS'!E5/'Historical FS'!E58,0) -> 6.9190052 | F30: =IFERROR('Historical FS'!F5/'Historical FS'!F58,0) -> 7.7392856 | G30: =IFERROR('Historical FS'!G5/'Historical FS'!G58,0) -> 6.9698269 | H30: =IFERROR('Historical FS'!H5/'Historical FS'!H58,0) -> 6.9217099 | I30: =IFERROR('Historical FS'!I5/'Historical FS'!I58,0) -> 7.9015588 | J30: =IFERROR('Historical FS'!J5/'Historical FS'!J58,0) -> 8.4888642 | ... L30: =IFERROR('Historical FS'!L5/'Historical FS'!L58,0) -> 9.3019738 | N30: =MEDIAN(C30:L30) -> 7.8204222 | O30: =AVERAGE(C30:L30) -> 7.937244
B31: Fixed Asset Turnover | C31: =IFERROR('Historical FS'!C5/'Historical FS'!C51,0) -> 2.5463128 | D31: =IFERROR('Historical FS'!D5/'Historical FS'!D51,0) -> 2.8109343 | E31: =IFERROR('Historical FS'!E5/'Historical FS'!E51,0) -> 2.4012949 | F31: =IFERROR('Historical FS'!F5/'Historical FS'!F51,0) -> 2.714432 | G31: =IFERROR('Historical FS'!G5/'Historical FS'!G51,0) -> 2.0539206 | H31: =IFERROR('Historical FS'!H5/'Historical FS'!H51,0) -> 1.8008727 | I31: =IFERROR('Historical FS'!I5/'Historical FS'!I51,0) -> 2.0053489 | J31: =IFERROR('Historical FS'!J5/'Historical FS'!J51,0) -> 2.6193792 | ... L31: =IFERROR('Historical FS'!L5/'Historical FS'!L51,0) -> 3.800401 | N31: =MEDIAN(C31:L31) -> 2.582846 | O31: =AVERAGE(C31:L31) -> 2.6331377
B32: Capital Turnover Ratio | C32: =IFERROR('Historical FS'!C5/SUM('Historical FS'!C45:C47),0) -> 1.841017 | D32: =IFERROR('Historical FS'!D5/SUM('Historical FS'!D45:D47),0) -> 1.9733713 | E32: =IFERROR('Historical FS'!E5/SUM('Historical FS'!E45:E47),0) -> 1.5812618 | F32: =IFERROR('Historical FS'!F5/SUM('Historical FS'!F45:F47),0) -> 1.8150256 | G32: =IFERROR('Historical FS'!G5/SUM('Historical FS'!G45:G47),0) -> 1.3896487 | H32: =IFERROR('Historical FS'!H5/SUM('Historical FS'!H45:H47),0) -> 1.2655699 | I32: =IFERROR('Historical FS'!I5/SUM('Historical FS'!I45:I47),0) -> 1.457794 | J32: =IFERROR('Historical FS'!J5/SUM('Historical FS'!J45:J47),0) -> 1.9280883 | ... L32: =IFERROR('Historical FS'!L5/SUM('Historical FS'!L45:L47),0) -> 2.342741 | N32: =MEDIAN(C32:L32) -> 1.8280213 | O32: =AVERAGE(C32:L32) -> 1.7852877
B35: Debtor Days | C35: =IFERROR(365/C28,0) -> 18.141227 | D35: =IFERROR(365/D28,0) -> 19.049753 | E35: =IFERROR(365/E28,0) -> 24.904965 | F35: =IFERROR(365/F28,0) -> 22.963631 | G35: =IFERROR(365/G28,0) -> 15.620575 | H35: =IFERROR(365/H28,0) -> 18.526667 | I35: =IFERROR(365/I28,0) -> 16.309265 | J35: =IFERROR(365/J28,0) -> 16.603779 | ... L35: =IFERROR(365/L28,0) -> 10.997441 | N35: =MEDIAN(C35:L35) -> 17.372503 | O35: =AVERAGE(C35:L35) -> 17.737364
B36: Payable Days | C36: =IFERROR(365/C29,0) -> 153.55746 | D36: =IFERROR(365/D29,0) -> 183.94574 | E36: =IFERROR(365/E29,0) -> 178.79203 | F36: =IFERROR(365/F29,0) -> 168.45236 | G36: =IFERROR(365/G29,0) -> 184.98755 | H36: =IFERROR(365/H29,0) -> 210.69421 | I36: =IFERROR(365/I29,0) -> 180.95902 | J36: =IFERROR(365/J29,0) -> 163.77953 | ... L36: =IFERROR(365/L29,0) -> 157.13275 | N36: =MEDIAN(C36:L36) -> 173.62219 | O36: =AVERAGE(C36:L36) -> 173.14397
B37: Inventory Days | C37: =IFERROR(365/C30,0) -> 43.6533 | D37: =IFERROR(365/D30,0) -> 47.484219 | E37: =IFERROR(365/E30,0) -> 52.753249 | F37: =IFERROR(365/F30,0) -> 47.161976 | G37: =IFERROR(365/G30,0) -> 52.368589 | H37: =IFERROR(365/H30,0) -> 52.732635 | I37: =IFERROR(365/I30,0) -> 46.193417 | J37: =IFERROR(365/J30,0) -> 42.997507 | ... L37: =IFERROR(365/L30,0) -> 39.238984 | N37: =MEDIAN(C37:L37) -> 46.677696 | O37: =AVERAGE(C37:L37) -> 46.477276
B38: Cash Conversion Cycle (in days) | C38: =IFERROR(SUM(C35,C37)-C36,0) -> -91.762933 | D38: =IFERROR(SUM(D35,D37)-D36,0) -> -117.41177 | E38: =IFERROR(SUM(E35,E37)-E36,0) -> -101.13382 | F38: =IFERROR(SUM(F35,F37)-F36,0) -> -98.326751 | G38: =IFERROR(SUM(G35,G37)-G36,0) -> -116.99839 | H38: =IFERROR(SUM(H35,H37)-H36,0) -> -139.4349 | I38: =IFERROR(SUM(I35,I37)-I36,0) -> -118.45634 | J38: =IFERROR(SUM(J35,J37)-J36,0) -> -104.17824 | ... L38: =IFERROR(SUM(L35,L37)-L36,0) -> -106.89633 | N38: =MEDIAN(C38:L38) -> -105.53729 | O38: =AVERAGE(C38:L38) -> -108.92933
B40: CFO/Sales | C40: =IFERROR('Historical FS'!C76/'Historical FS'!C5,0) -> 0.0070501045 | D40: =IFERROR('Historical FS'!D76/'Historical FS'!D5,0) -> 0.0050464879 | E40: =IFERROR('Historical FS'!E76/'Historical FS'!E5,0) -> 0.014361149 | F40: =IFERROR('Historical FS'!F76/'Historical FS'!F5,0) -> 0.021862075 | G40: =IFERROR('Historical FS'!G76/'Historical FS'!G5,0) -> -0.012475678 | H40: =IFERROR('Historical FS'!H76/'Historical FS'!H5,0) -> 0.045893679 | I40: =IFERROR('Historical FS'!I76/'Historical FS'!I5,0) -> 0.028859384 | J40: =IFERROR('Historical FS'!J76/'Historical FS'!J5,0) -> 0.013611126 | ... L40: =IFERROR('Historical FS'!L76/'Historical FS'!L5,0) -> 0.02494229 | N40: =MEDIAN(C40:L40) -> 0.017603002 | O40: =AVERAGE(C40:L40) -> 0.016999547
B41: CFO/Total Assets | C41: =IFERROR('Historical FS'!C76/'Historical FS'!C62,0) -> 0.0073142711 | D41: =IFERROR('Historical FS'!D76/'Historical FS'!D62,0) -> 0.004993023 | E41: =IFERROR('Historical FS'!E76/'Historical FS'!E62,0) -> 0.012796775 | F41: =IFERROR('Historical FS'!F76/'Historical FS'!F62,0) -> 0.021592819 | G41: =IFERROR('Historical FS'!G76/'Historical FS'!G62,0) -> -0.010172422 | H41: =IFERROR('Historical FS'!H76/'Historical FS'!H62,0) -> 0.033562675 | I41: =IFERROR('Historical FS'!I76/'Historical FS'!I62,0) -> 0.024420968 | J41: =IFERROR('Historical FS'!J76/'Historical FS'!J62,0) -> 0.014070391 | ... L41: =IFERROR('Historical FS'!L76/'Historical FS'!L62,0) -> 0.029092269 | N41: =MEDIAN(C41:L41) -> 0.017831605 | O41: =AVERAGE(C41:L41) -> 0.016215382
B42: CFO/Total Debt | C42: =IFERROR('Historical FS'!C76/'Historical FS'!C47,0) -> 0.027753765 | D42: =IFERROR('Historical FS'!D76/'Historical FS'!D47,0) -> 0.017314645 | E42: =IFERROR('Historical FS'!E76/'Historical FS'!E47,0) -> 0.04707114 | F42: =IFERROR('Historical FS'!F76/'Historical FS'!F47,0) -> 0.062170745 | G42: =IFERROR('Historical FS'!G76/'Historical FS'!G47,0) -> -0.026100341 | H42: =IFERROR('Historical FS'!H76/'Historical FS'!H47,0) -> 0.080658229 | I42: =IFERROR('Historical FS'!I76/'Historical FS'!I47,0) -> 0.054872333 | J42: =IFERROR('Historical FS'!J76/'Historical FS'!J47,0) -> 0.035112066 | ... L42: =IFERROR('Historical FS'!L76/'Historical FS'!L47,0) -> 0.15329885 | N42: =MEDIAN(C42:L42) -> 0.050971737 | O42: =AVERAGE(C42:L42) -> 0.053649474

Sheet Forecasting
B2: ='Data Sheet'!B1&" - "&'Data Sheet'!A17 -> TATA MOTORS LTD - Sales | H2: ='Data Sheet'!B1&" - "&'Historical FS'!B16 -> TATA MOTORS LTD - EBIDTA
B3: Year Weight | C3: Year | D3: Sales | E3: Sales growth | H3: Year Weight | I3: Year | J3: EBIDTA | K3: EBIDTA growth
B4: =1 -> 1 | C4: ='Data Sheet'!B16 -> 42460 | D4: {=TRANSPOSE('Data Sheet'!B17:K17)} -> 273045.6 | H4: =1 -> 1 | I4: ='Data Sheet'!B16 -> 42460 | J4: {=TRANSPOSE('Historical FS'!C16:L16)} -> 38395.25
B5: =B4+1 -> 2 | C5: =C4+365 -> 42825 | D5: 269692.51 | E5: =(D5-D4)/D4 -> -0.01228033 | H5: =H4+1 -> 2 | I5: =I4+365 -> 42825 | J5: 14788.85 | K5: =(J5-J4)/J4 -> -0.61482605
B6: =B5+1 -> 3 | C6: =C5+365 -> 43190 | D6: 291550.48 | E6: =(D6-D5)/D5 -> 0.081047746 | H6: =H5+1 -> 3 | I6: =I5+365 -> 43190 | J6: 27364.52 | K6: =(J6-J5)/J5 -> 0.85034807
B7: =B6+1 -> 4 | C7: =C6+365 -> 43555 | D7: 301938.4 | E7: =(D7-D6)/D6 -> 0.035629919 | H7: =H6+1 -> 4 | I7: =I6+365 -> 43555 | J7: 28770.89 | K7: =(J7-J6)/J6 -> 0.051393922
B8: =B7+1 -> 5 | C8: =C7+365 -> 43920 | D8: 261067.97 | E8: =(D8-D7)/D7 -> -0.13536016 | H8: =H7+1 -> 5 | I8: =I7+365 -> 43920 | J8: 22449.45 | K8: =(J8-J7)/J7 -> -0.21971653
B9: =B8+1 -> 6 | C9: =C8+365 -> 44285 | D9: 249794.75 | E9: =(D9-D8)/D8 -> -0.043181168 | H9: =H8+1 -> 6 | I9: =I8+365 -> 44285 | J9: 41655.75 | K9: =(J9-J8)/J8 -> 0.85553544
B10: =B9+1 -> 7 | C10: =C9+365 -> 44650 | D10: 278453.62 | E10: =(D10-D9)/D9 -> 0.11472967 | H10: =H9+1 -> 7 | I10: =I9+365 -> 44650 | J10: 27901.07 | K10: =(J10-J9)/J9 -> -0.33019883
B11: =B10+1 -> 8 | C11: =C10+365 -> 45015 | D11: 345966.97 | E11: =(D11-D10)/D10 -> 0.24245815 | H11: =H10+1 -> 8 | I11: =I10+365 -> 45015 | J11: 22252.56 | K11: =(J11-J10)/J10 -> -0.20244779
B12: =B11+1 -> 9 | C12: =C11+365 -> 45380 | D12: 434016 | E12: =(D12-D11)/D11 -> 0.25450126 | H12: =H11+1 -> 9 | I12: =I11+365 -> 45380 | J12: 54692 | K12: =(J12-J11)/J11 -> 1.4577846
B13: =B12+1 -> 10 | C13: =C12+365 -> 45745 | D13: 439695 | E13: =(D13-D12)/D12 -> 0.013084771 | H13: =H12+1 -> 10 | I13: =I12+365 -> 45745 | J13: 60888 | K13: =(J13-J12)/J12 -> 0.11328896
B14: =B13+1 -> 11 | C14: =C13+365 -> 46110 | D14: =_xlfn.FORECAST.LINEAR(B14,_xlfn.ANCHORARRAY($D$4),$B$4:$B$13) -> 409204.26 | E14: =(D14-D13)/D13 -> -0.069345204 | H14: =H13+1 -> 11 | I14: =I13+365 -> 46110 | J14: =_xlfn.FORECAST.LINEAR(H14,_xlfn.ANCHORARRAY($J$4),$H$4:$H$13) -> 49675.629 | K14: =(J14-J13)/J13 -> -0.18414747
B15: =B14+1 -> 12 | C15: =C14+365 -> 46475 | D15: =_xlfn.FORECAST.LINEAR(B15,_xlfn.ANCHORARRAY($D$4),$B$4:$B$13) -> 426419.19 | E15: =(D15-D14)/D14 -> 0.04206929 | H15: =H14+1 -> 12 | I15: =I14+365 -> 46475 | J15: =_xlfn.FORECAST.LINEAR(H15,_xlfn.ANCHORARRAY($J$4),$H$4:$H$13) -> 52541.046 | K15: =(J15-J14)/J14 -> 0.057682556
B16: =B15+1 -> 13 | C16: =C15+365 -> 46840 | D16: =_xlfn.FORECAST.LINEAR(B16,_xlfn.ANCHORARRAY($D$4),$B$4:$B$13) -> 443634.13 | E16: =(D16-D15)/D15 -> 0.040370915 | H16: =H15+1 -> 13 | I16: =I15+365 -> 46840 | J16: =_xlfn.FORECAST.LINEAR(H16,_xlfn.ANCHORARRAY($J$4),$H$4:$H$13) -> 55406.463 | K16: =(J16-J15)/J15 -> 0.054536737
B17: =B16+1 -> 14 | C17: =C16+365 -> 47205 | D17: =_xlfn.FORECAST.LINEAR(B17,_xlfn.ANCHORARRAY($D$4),$B$4:$B$13) -> 460849.06 | E17: =(D17-D16)/D16 -> 0.038804348 | H17: =H16+1 -> 14 | I17: =I16+365 -> 47205 | J17: =_xlfn.FORECAST.LINEAR(H17,_xlfn.ANCHORARRAY($J$4),$H$4:$H$13) -> 58271.88 | K17: =(J17-J16)/J16 -> 0.051716299
B18: =B17+1 -> 15 | C18: =C17+365 -> 47570 | D18: =_xlfn.FORECAST.LINEAR(B18,_xlfn.ANCHORARRAY($D$4),$B$4:$B$13) -> 478063.99 | E18: =(D18-D17)/D17 -> 0.037354818 | H18: =H17+1 -> 15 | I18: =I17+365 -> 47570 | J18: =_xlfn.FORECAST.LINEAR(H18,_xlfn.ANCHORARRAY($J$4),$H$4:$H$13) -> 61137.298 | K18: =(J18-J17)/J17 -> 0.049173241

Sheet Common Size Statement
B2: ="Common Size Statement"&" "&" - "&'Data Sheet'!B1 -> Common Size Statement - TATA MOTORS LTD
B4: Particulars | C4: ='Data Sheet'!B16 -> 42460 | D4: ='Data Sheet'!C16 -> 42825 | E4: ='Data Sheet'!D16 -> 43190 | F4: ='Data Sheet'!E16 -> 43555 | G4: ='Data Sheet'!F16 -> 43921 | H4: ='Data Sheet'!G16 -> 44286 | I4: ='Data Sheet'!H16 -> 44651 | J4: ='Data Sheet'!I16 -> 45016 | ... L4: ='Data Sheet'!K16 -> 45747
B5: ='Data Sheet'!A17 -> Sales | C5: ='Data Sheet'!B17/'Data Sheet'!B$17 -> 1 | D5: ='Data Sheet'!C17/'Data Sheet'!C$17 -> 1 | E5: ='Data Sheet'!D17/'Data Sheet'!D$17 -> 1 | F5: ='Data Sheet'!E17/'Data Sheet'!E$17 -> 1 | G5: ='Data Sheet'!F17/'Data Sheet'!F$17 -> 1 | H5: ='Data Sheet'!G17/'Data Sheet'!G$17 -> 1 | I5: ='Data Sheet'!H17/'Data Sheet'!H$17 -> 1 | J5: ='Data Sheet'!I17/'Data Sheet'!I$17 -> 1 | ... L5: ='Data Sheet'!K17/'Data Sheet'!K$17 -> 1
B6: ='Data Sheet'!A18 -> Raw Material Cost | C6: ='Data Sheet'!B18/'Data Sheet'!B$17 -> 0.60844786 | D6: ='Data Sheet'!C18/'Data Sheet'!C$17 -> 0.64256171 | E6: ='Data Sheet'!D18/'Data Sheet'!D$17 -> 0.64447357 | F6: ='Data Sheet'!E18/'Data Sheet'!E$17 -> 0.64340246 | G6: ='Data Sheet'!F18/'Data Sheet'!F$17 -> 0.63163559 | H6: ='Data Sheet'!G18/'Data Sheet'!G$17 -> 0.6149343 | I6: ='Data Sheet'!H18/'Data Sheet'!H$17 -> 0.64389657 | J6: ='Data Sheet'!I18/'Data Sheet'!I$17 -> 0.66842005 | ... L6: ='Data Sheet'!K18/'Data Sheet'!K$17 -> 0.611674
B7: ='Data Sheet'!A19 -> Change in Inventory | C7: ='Data Sheet'!B19/'Data Sheet'!B$17 -> 0.010075204 | D7: ='Data Sheet'!C19/'Data Sheet'!C$17 -> 0.027438359 | E7: ='Data Sheet'!D19/'Data Sheet'!D$17 -> 0.007019642 | F7: ='Data Sheet'!E19/'Data Sheet'!E$17 -> -0.0068003275 | G7: ='Data Sheet'!F19/'Data Sheet'!F$17 -> -0.008546395 | H7: ='Data Sheet'!G19/'Data Sheet'!G$17 -> -0.018752035 | I7: ='Data Sheet'!H19/'Data Sheet'!H$17 -> -0.0057118668 | J7: ='Data Sheet'!I19/'Data Sheet'!I$17 -> 0.01382103 | ... L7: ='Data Sheet'!K19/'Data Sheet'!K$17 -> -0.0064499255
B8: ='Data Sheet'!A20 -> Power and Fuel | C8: ='Data Sheet'!B20/'Data Sheet'!B$17 -> 0.0041884213 | D8: ='Data Sheet'!C20/'Data Sheet'!C$17 -> 0.0043005273 | E8: ='Data Sheet'!D20/'Data Sheet'!D$17 -> 0.004486633 | F8: ='Data Sheet'!E20/'Data Sheet'!E$17 -> 0.0052524952 | G8: ='Data Sheet'!F20/'Data Sheet'!F$17 -> 0.0048452899 | H8: ='Data Sheet'!G20/'Data Sheet'!G$17 -> 0.0044551377 | I8: ='Data Sheet'!H20/'Data Sheet'!H$17 -> 0.0078228109 | J8: ='Data Sheet'!I20/'Data Sheet'!I$17 -> 0.007264653 | ... L8: ='Data Sheet'!K20/'Data Sheet'!K$17 -> 0.0055561241
B9: ='Data Sheet'!A21 -> Other Mfr. Exp | C9: ='Data Sheet'!B21/'Data Sheet'!B$17 -> 0.044320546 | D9: ='Data Sheet'!C21/'Data Sheet'!C$17 -> 0.037329068 | E9: ='Data Sheet'!D21/'Data Sheet'!D$17 -> 0.037632111 | F9: ='Data Sheet'!E21/'Data Sheet'!E$17 -> 0.038731543 | G9: ='Data Sheet'!F21/'Data Sheet'!F$17 -> 0.044208832 | H9: ='Data Sheet'!G21/'Data Sheet'!G$17 -> 0.033119871 | I9: ='Data Sheet'!H21/'Data Sheet'!H$17 -> 0.033856195 | J9: ='Data Sheet'!I21/'Data Sheet'!I$17 -> 0.03400894 | ... L9: ='Data Sheet'!K21/'Data Sheet'!K$17 -> 0.042786477
B10: ='Data Sheet'!A22 -> Employee Cost | C10: ='Data Sheet'!B22/'Data Sheet'!B$17 -> 0.10577314 | D10: ='Data Sheet'!C22/'Data Sheet'!C$17 -> 0.10505627 | E10: ='Data Sheet'!D22/'Data Sheet'!D$17 -> 0.10392742 | F10: ='Data Sheet'!E22/'Data Sheet'!E$17 -> 0.1101015 | G10: ='Data Sheet'!F22/'Data Sheet'!F$17 -> 0.11659263 | H10: ='Data Sheet'!G22/'Data Sheet'!G$17 -> 0.11068479 | I10: ='Data Sheet'!H22/'Data Sheet'!H$17 -> 0.11064148 | J10: ='Data Sheet'!I22/'Data Sheet'!I$17 -> 0.097277205 | ... L10: ='Data Sheet'!K22/'Data Sheet'!K$17 -> 0.10863667
B11: ='Data Sheet'!A23 -> Selling and admin | C11: ='Data Sheet'!B23/'Data Sheet'!B$17 -> 0.080542957 | D11: ='Data Sheet'!C23/'Data Sheet'!C$17 -> 0.11138381 | E11: ='Data Sheet'!D23/'Data Sheet'!D$17 -> 0.10634378 | F11: ='Data Sheet'!E23/'Data Sheet'!E$17 -> 0.10836581 | G11: ='Data Sheet'!F23/'Data Sheet'!F$17 -> 0.11203335 | H11: ='Data Sheet'!G23/'Data Sheet'!G$17 -> 0.092138806 | I11: ='Data Sheet'!H23/'Data Sheet'!H$17 -> 0.10488425 | J11: ='Data Sheet'!I23/'Data Sheet'!I$17 -> 0.10070091 | ... L11: ='Data Sheet'!K23/'Data Sheet'!K$17 -> 0.10711743
B12: ='Data Sheet'!A24 -> Other Expenses | C12: ='Data Sheet'!B24/'Data Sheet'!B$17 -> 0.026183832 | D12: ='Data Sheet'!C24/'Data Sheet'!C$17 -> 0.017094283 | E12: ='Data Sheet'!D24/'Data Sheet'!D$17 -> 0.0022582367 | F12: ='Data Sheet'!E24/'Data Sheet'!E$17 -> 0.0056592338 | G12: ='Data Sheet'!F24/'Data Sheet'!F$17 -> 0.013239885 | H12: ='Data Sheet'!G24/'Data Sheet'!G$17 -> -0.0033407828 | I12: ='Data Sheet'!H24/'Data Sheet'!H$17 -> 0.0044105011 | J12: ='Data Sheet'!I24/'Data Sheet'!I$17 -> 0.014187308 | ... L12: ='Data Sheet'!K24/'Data Sheet'!K$17 -> -0.0077985877
B13: ='Data Sheet'!A25 -> Other Income | C13: ='Data Sheet'!B25/'Data Sheet'!B$17 -> -0.0097771947 | D13: ='Data Sheet'!C25/'Data Sheet'!C$17 -> 0.0069304854 | E13: ='Data Sheet'!D25/'Data Sheet'!D$17 -> 0.020348895 | F13: ='Data Sheet'!E25/'Data Sheet'!E$17 -> -0.088383094 | G13: ='Data Sheet'!F25/'Data Sheet'!F$17 -> 0.00038959203 | H13: ='Data Sheet'!G25/'Data Sheet'!G$17 -> -0.044507861 | I13: ='Data Sheet'!H25/'Data Sheet'!H$17 -> 0.0087053995 | J13: ='Data Sheet'!I25/'Data Sheet'!I$17 -> 0.019261868 | ... L13: ='Data Sheet'!K25/'Data Sheet'!K$17 -> 0.026777653
B14: ='Data Sheet'!A26 -> Depreciation | C14: ='Data Sheet'!B26/'Data Sheet'!B$17 -> 0.061201426 | D14: ='Data Sheet'!C26/'Data Sheet'!C$17 -> 0.066390387 | E14: ='Data Sheet'!D26/'Data Sheet'!D$17 -> 0.073927472 | F14: ='Data Sheet'!E26/'Data Sheet'!E$17 -> 0.078130605 | G14: ='Data Sheet'!F26/'Data Sheet'!F$17 -> 0.082068398 | H14: ='Data Sheet'!G26/'Data Sheet'!G$17 -> 0.094264231 | I14: ='Data Sheet'!H26/'Data Sheet'!H$17 -> 0.089191478 | J14: ='Data Sheet'!I26/'Data Sheet'!I$17 -> 0.071857611 | ... L14: ='Data Sheet'!K26/'Data Sheet'!K$17 -> 0.052891209
B15: ='Data Sheet'!A27 -> Interest | C15: ='Data Sheet'!B27/'Data Sheet'!B$17 -> 0.017905727 | D15: ='Data Sheet'!C27/'Data Sheet'!C$17 -> 0.01571423 | E15: ='Data Sheet'!D27/'Data Sheet'!D$17 -> 0.016058248 | F15: ='Data Sheet'!E27/'Data Sheet'!E$17 -> 0.019072102 | G15: ='Data Sheet'!F27/'Data Sheet'!F$17 -> 0.027744997 | H15: ='Data Sheet'!G27/'Data Sheet'!G$17 -> 0.032415293 | I15: ='Data Sheet'!H27/'Data Sheet'!H$17 -> 0.033441332 | J15: ='Data Sheet'!I27/'Data Sheet'!I$17 -> 0.029556232 | ... L15: ='Data Sheet'!K27/'Data Sheet'!K$17 -> 0.011560286
B16: ='Data Sheet'!A28 -> Profit before tax | C16: ='Data Sheet'!B28/'Data Sheet'!B$17 -> 0.051734106 | D16: ='Data Sheet'!C28/'Data Sheet'!C$17 -> 0.034538557 | E16: ='Data Sheet'!D28/'Data Sheet'!D$17 -> 0.038261059 | F16: ='Data Sheet'!E28/'Data Sheet'!E$17 -> -0.10389917 | G16: ='Data Sheet'!F28/'Data Sheet'!F$17 -> -0.040525768 | H16: ='Data Sheet'!G28/'Data Sheet'!G$17 -> -0.041931546 | I16: ='Data Sheet'!H28/'Data Sheet'!H$17 -> -0.025151083 | J16: ='Data Sheet'!I28/'Data Sheet'!I$17 -> 0.0098099827 | ... L16: ='Data Sheet'!K28/'Data Sheet'!K$17 -> 0.087904115
... B19: ='Data Sheet'!A31 -> Dividend Amount | C19: ='Data Sheet'!B31/'Data Sheet'!B$17 -> 0.00024874966 | D19: ='Data Sheet'!C31/'Data Sheet'!C$17 -> 0 | E19: ='Data Sheet'!D31/'Data Sheet'!D$17 -> 0 | F19: ='Data Sheet'!E31/'Data Sheet'!E$17 -> 0 | G19: ='Data Sheet'!F31/'Data Sheet'!F$17 -> 0 | H19: ='Data Sheet'!G31/'Data Sheet'!G$17 -> 0 | I19: ='Data Sheet'!H31/'Data Sheet'!H$17 -> 0 | J19: ='Data Sheet'!I31/'Data Sheet'!I$17 -> 0.002214142 | ... L19: ='Data Sheet'!K31/'Data Sheet'!K$17 -> 0.0050216627
B20: EBIDTA | C20: =C18+C15+C14+C17 -> 0.13259404 | D20: =D18+D15+D14+D17 -> 0.12180016 | E20: =E18+E15+E14+E17 -> 0.13570967 | F20: =F18+F15+F14+F17 -> -0.0063405317 | G20: =G18+G15+G14+G17 -> 0.065090942 | H20: =H18+H15+H14+H17 -> 0.083005548 | I20: =I18+I15+I14+I17 -> 0.096739163 | J20: =J18+J15+J14+J17 -> 0.11042728 | ... L20: =L18+L15+L14+L17 -> 0.15163011
B22: ="Common Size Balance Sheet "&" - "&'Data Sheet'!B1 -> Common Size Balance Sheet - TATA MOTORS LTD
B24: Particulars | C24: ='Data Sheet'!B16 -> 42460 | D24: ='Data Sheet'!C16 -> 42825 | E24: ='Data Sheet'!D16 -> 43190 | F24: ='Data Sheet'!E16 -> 43555 | G24: ='Data Sheet'!F16 -> 43921 | H24: ='Data Sheet'!G16 -> 44286 | I24: ='Data Sheet'!H16 -> 44651 | J24: ='Data Sheet'!I16 -> 45016 | ... L24: ='Data Sheet'!K16 -> 45747
B26: Total Liabilities | C26: ='Data Sheet'!B61/'Data Sheet'!B$61 -> 1 | D26: ='Data Sheet'!C61/'Data Sheet'!C$61 -> 1 | E26: ='Data Sheet'!D61/'Data Sheet'!D$61 -> 1 | F26: ='Data Sheet'!E61/'Data Sheet'!E$61 -> 1 | G26: ='Data Sheet'!F61/'Data Sheet'!F$61 -> 1 | H26: ='Data Sheet'!G61/'Data Sheet'!G$61 -> 1 | I26: ='Data Sheet'!H61/'Data Sheet'!H$61 -> 1 | J26: ='Data Sheet'!I61/'Data Sheet'!I$61 -> 1 | ... L26: ='Data Sheet'!K61/'Data Sheet'!K$61 -> 1
B27: ='Data Sheet'!A57 -> Equity Share Capital | C27: ='Data Sheet'!B62/'Data Sheet'!B$61 -> 0.40744008 | D27: ='Data Sheet'!C62/'Data Sheet'!C$61 -> 0.35198457 | E27: ='Data Sheet'!D62/'Data Sheet'!D$61 -> 0.37107854 | F27: ='Data Sheet'!E62/'Data Sheet'!E$61 -> 0.36386392 | G27: ='Data Sheet'!F62/'Data Sheet'!F$61 -> 0.39698726 | H27: ='Data Sheet'!G62/'Data Sheet'!G$61 -> 0.40608849 | I27: ='Data Sheet'!H62/'Data Sheet'!H$61 -> 0.42197417 | J27: ='Data Sheet'!I62/'Data Sheet'!I$61 -> 0.39465148 | ... L27: ='Data Sheet'!K62/'Data Sheet'!K$61 -> 0.30691057
B28: ='Data Sheet'!A58 -> Reserves | C28: ='Data Sheet'!B63/'Data Sheet'!B$61 -> 0.098482158 | D28: ='Data Sheet'!C63/'Data Sheet'!C$61 -> 0.12362901 | E28: ='Data Sheet'!D63/'Data Sheet'!D$61 -> 0.12235484 | F28: ='Data Sheet'!E63/'Data Sheet'!E$61 -> 0.10429662 | G28: ='Data Sheet'!F63/'Data Sheet'!F$61 -> 0.11125729 | H28: ='Data Sheet'!G63/'Data Sheet'!G$61 -> 0.061375225 | I28: ='Data Sheet'!H63/'Data Sheet'!H$61 -> 0.031152506 | J28: ='Data Sheet'!I63/'Data Sheet'!I$61 -> 0.042651899 | ... L28: ='Data Sheet'!K63/'Data Sheet'!K$61 -> 0.17456423
B29: ='Data Sheet'!A59 -> Borrowings | C29: ='Data Sheet'!B64/'Data Sheet'!B$61 -> 0.090305676 | D29: ='Data Sheet'!C64/'Data Sheet'!C$61 -> 0.074612566 | E29: ='Data Sheet'!D64/'Data Sheet'!D$61 -> 0.063610241 | F29: ='Data Sheet'!E64/'Data Sheet'!E$61 -> 0.051588289 | G29: ='Data Sheet'!F64/'Data Sheet'!F$61 -> 0.050935446 | H29: ='Data Sheet'!G64/'Data Sheet'!G$61 -> 0.072079768 | I29: ='Data Sheet'!H64/'Data Sheet'!H$61 -> 0.089282796 | J29: ='Data Sheet'!I64/'Data Sheet'!I$61 -> 0.078820363 | ... L29: ='Data Sheet'!K64/'Data Sheet'!K$61 -> 0.094585023
B30: ='Data Sheet'!A60 -> Other Liabilities | C30: ='Data Sheet'!B65/'Data Sheet'!B$61 -> 0.40377208 | D30: ='Data Sheet'!C65/'Data Sheet'!C$61 -> 0.44977386 | E30: ='Data Sheet'!D65/'Data Sheet'!D$61 -> 0.44295638 | F30: ='Data Sheet'!E65/'Data Sheet'!E$61 -> 0.48025117 | G30: ='Data Sheet'!F65/'Data Sheet'!F$61 -> 0.44082 | H30: ='Data Sheet'!G65/'Data Sheet'!G$61 -> 0.46045651 | I30: ='Data Sheet'!H65/'Data Sheet'!H$61 -> 0.45759053 | J30: ='Data Sheet'!I65/'Data Sheet'!I$61 -> 0.48387626 | ... L30: ='Data Sheet'!K65/'Data Sheet'!K$61 -> 0.42394018
B32: Total Assets | C32: ='Data Sheet'!B66/'Data Sheet'!B$66 -> 1 | D32: ='Data Sheet'!C66/'Data Sheet'!C$66 -> 1 | E32: ='Data Sheet'!D66/'Data Sheet'!D$66 -> 1 | F32: ='Data Sheet'!E66/'Data Sheet'!E$66 -> 1 | G32: ='Data Sheet'!F66/'Data Sheet'!F$66 -> 1 | H32: ='Data Sheet'!G66/'Data Sheet'!G$66 -> 1 | I32: ='Data Sheet'!H66/'Data Sheet'!H$66 -> 1 | J32: ='Data Sheet'!I66/'Data Sheet'!I$66 -> 1 | ... L32: ='Data Sheet'!K66/'Data Sheet'!K$66 -> 1
B33: Net Block | C33: ='Data Sheet'!B62/'Data Sheet'!B$66 -> 0.40744008 | D33: ='Data Sheet'!C62/'Data Sheet'!C$66 -> 0.35198457 | E33: ='Data Sheet'!D62/'Data Sheet'!D$66 -> 0.37107854 | F33: ='Data Sheet'!E62/'Data Sheet'!E$66 -> 0.36386392 | G33: ='Data Sheet'!F62/'Data Sheet'!F$66 -> 0.39698726 | H33: ='Data Sheet'!G62/'Data Sheet'!G$66 -> 0.40608849 | I33: ='Data Sheet'!H62/'Data Sheet'!H$66 -> 0.42197417 | J33: ='Data Sheet'!I62/'Data Sheet'!I$66 -> 0.39465148 | ... L33: ='Data Sheet'!K62/'Data Sheet'!K$66 -> 0.30691057
B34: Capital Work in Progress | C34: ='Data Sheet'!B63/'Data Sheet'!B$66 -> 0.098482158 | D34: ='Data Sheet'!C63/'Data Sheet'!C$66 -> 0.12362901 | E34: ='Data Sheet'!D63/'Data Sheet'!D$66 -> 0.12235484 | F34: ='Data Sheet'!E63/'Data Sheet'!E$66 -> 0.10429662 | G34: ='Data Sheet'!F63/'Data Sheet'!F$66 -> 0.11125729 | H34: ='Data Sheet'!G63/'Data Sheet'!G$66 -> 0.061375225 | I34: ='Data Sheet'!H63/'Data Sheet'!H$66 -> 0.031152506 | J34: ='Data Sheet'!I63/'Data Sheet'!I$66 -> 0.042651899 | ... L34: ='Data Sheet'!K63/'Data Sheet'!K$66 -> 0.17456423
B35: Investments | C35: ='Data Sheet'!B64/'Data Sheet'!B$66 -> 0.090305676 | D35: ='Data Sheet'!C64/'Data Sheet'!C$66 -> 0.074612566 | E35: ='Data Sheet'!D64/'Data Sheet'!D$66 -> 0.063610241 | F35: ='Data Sheet'!E64/'Data Sheet'!E$66 -> 0.051588289 | G35: ='Data Sheet'!F64/'Data Sheet'!F$66 -> 0.050935446 | H35: ='Data Sheet'!G64/'Data Sheet'!G$66 -> 0.072079768 | I35: ='Data Sheet'!H64/'Data Sheet'!H$66 -> 0.089282796 | J35: ='Data Sheet'!I64/'Data Sheet'!I$66 -> 0.078820363 | ... L35: ='Data Sheet'!K64/'Data Sheet'!K$66 -> 0.094585023
B36: Receivables | C36: ='Data Sheet'!B67/'Data Sheet'!B$66 -> 0.051564319 | D36: ='Data Sheet'!C67/'Data Sheet'!C$66 -> 0.051638166 | E36: ='Data Sheet'!D67/'Data Sheet'!D$66 -> 0.060800116 | F36: ='Data Sheet'!E67/'Data Sheet'!E$66 -> 0.062139199 | G36: ='Data Sheet'!F67/'Data Sheet'!F$66 -> 0.034895094 | H36: ='Data Sheet'!G67/'Data Sheet'!G$66 -> 0.037120014 | I36: ='Data Sheet'!H67/'Data Sheet'!H$66 -> 0.037810927 | J36: ='Data Sheet'!I67/'Data Sheet'!I$66 -> 0.047024716 | ... L36: ='Data Sheet'!K67/'Data Sheet'!K$66 -> 0.0351431
B37: Inventory | C37: ='Data Sheet'!B68/'Data Sheet'!B$66 -> 0.12407941 | D37: ='Data Sheet'!C68/'Data Sheet'!C$66 -> 0.12871547 | E37: ='Data Sheet'!D68/'Data Sheet'!D$66 -> 0.12878571 | F37: ='Data Sheet'!E68/'Data Sheet'!E$66 -> 0.12761951 | G37: ='Data Sheet'!F68/'Data Sheet'!F$66 -> 0.11698717 | H37: ='Data Sheet'!G68/'Data Sheet'!G$66 -> 0.10565506 | I37: ='Data Sheet'!H68/'Data Sheet'!H$66 -> 0.10709348 | J37: ='Data Sheet'!I68/'Data Sheet'!I$66 -> 0.12177623 | ... L37: ='Data Sheet'!K68/'Data Sheet'!K$66 -> 0.12539094
B38: Cash & Bank | C38: ='Data Sheet'!B69/'Data Sheet'!B$66 -> 0.11573799 | D38: ='Data Sheet'!C69/'Data Sheet'!C$66 -> 0.13235686 | E38: ='Data Sheet'!D69/'Data Sheet'!D$66 -> 0.10579088 | F38: ='Data Sheet'!E69/'Data Sheet'!E$66 -> 0.10679898 | G38: ='Data Sheet'!F69/'Data Sheet'!F$66 -> 0.10533773 | H38: ='Data Sheet'!G69/'Data Sheet'!G$66 -> 0.13699234 | I38: ='Data Sheet'!H69/'Data Sheet'!H$66 -> 0.12359146 | J38: ='Data Sheet'!I69/'Data Sheet'!I$66 -> 0.1106017 | ... L38: ='Data Sheet'!K69/'Data Sheet'!K$66 -> 0.10832076
B39: Other assets | C39: ='Data Sheet'!B74/'Data Sheet'!B$66 -> 0.11239037 | D39: ='Data Sheet'!C74/'Data Sheet'!C$66 -> 0.13706336 | E39: ='Data Sheet'!D74/'Data Sheet'!D$66 -> 0.14757967 | F39: ='Data Sheet'!E74/'Data Sheet'!E$66 -> 0.18369349 | G39: ='Data Sheet'!F74/'Data Sheet'!F$66 -> 0.18360001 | H39: ='Data Sheet'!G74/'Data Sheet'!G$66 -> 0.1806891 | I39: ='Data Sheet'!H74/'Data Sheet'!H$66 -> 0.18909466 | J39: ='Data Sheet'!I74/'Data Sheet'!I$66 -> 0.20447361 | ... L39: ='Data Sheet'!K74/'Data Sheet'!K$66 -> 0.15508538

Sheet Intrinsic Growth
B2: Calculation of ROIC | E2: ='[1]Data Room>'!I1 -> 44256 | F2: ='[1]Data Room>'!J1 -> 44621 | G2: ='[1]Data Room>'!K1 -> 44986 | H2: ='[1]Data Room>'!L1 -> 45352 | I2: ='[1]Data Room>'!M1 -> 45717
B4: Current Assets
B5: ='[1]Data Room>'!A32 -> Inventories | E5: ='[1]Data Room>'!I32 -> 3799 | F5: ='[1]Data Room>'!J32 -> 6153 | G5: ='[1]Data Room>'!K32 -> 6211 | H5: ='[1]Data Room>'!L32 -> 5923 | I5: ='[1]Data Room>'!M32 -> 6719
B6: ='[1]Data Room>'!A33 -> Trade receivables - | E6: ='[1]Data Room>'!I33 -> 2602 | F6: ='[1]Data Room>'!J33 -> 3871 | G6: ='[1]Data Room>'!K33 -> 4637 | H6: ='[1]Data Room>'!L33 -> 4889 | I6: ='[1]Data Room>'!M33 -> 4314
B7: ='[1]Data Room>'!A34 -> Prov for Doubtful | E7: ='[1]Data Room>'!I34 -> -185 | F7: ='[1]Data Room>'!J34 -> -241 | G7: ='[1]Data Room>'!K34 -> -305 | H7: ='[1]Data Room>'!L34 -> -422 | I7: ='[1]Data Room>'!M34 -> -663
B8: ='[1]Data Room>'!A36 -> Loans n Advances | E8: ='[1]Data Room>'!I36 -> 11 | F8: ='[1]Data Room>'!J36 -> 8 | G8: ='[1]Data Room>'!K36 -> 12 | H8: ='[1]Data Room>'!L36 -> 17 | I8: ='[1]Data Room>'!M36 -> 22
B9: ='[1]Data Room>'!A37 -> Other asset items | E9: ='[1]Data Room>'!I37 -> 2555 | F9: ='[1]Data Room>'!J37 -> 2869 | G9: ='[1]Data Room>'!K37 -> 3024 | H9: ='[1]Data Room>'!L37 -> 3555 | I9: ='[1]Data Room>'!M37 -> 3319
B10: Total Current Assets | E10: =SUM(E5:E9) -> 8782 | F10: =SUM(F5:F9) -> 12660 | G10: =SUM(G5:G9) -> 13579 | H10: =SUM(H5:H9) -> 13962 | I10: =SUM(I5:I9) -> 13711
B13: Current Liabilities
B14: ='[1]Data Room>'!A11 -> Trade Payables | E14: ='[1]Data Room>'!I11 -> 3379 | F14: ='[1]Data Room>'!J11 -> 4164 | G14: ='[1]Data Room>'!K11 -> 3635 | H14: ='[1]Data Room>'!L11 -> 3831 | I14: ='[1]Data Room>'!M11 -> 3848
B15: ='[1]Data Room>'!A12 -> Advance from Customers | E15: ='[1]Data Room>'!I12 -> 41 | F15: ='[1]Data Room>'!J12 -> 76 | G15: ='[1]Data Room>'!K12 -> 108 | H15: ='[1]Data Room>'!L12 -> 154 | I15: ='[1]Data Room>'!M12 -> 173
B16: ='[1]Data Room>'!A13 -> Other liability items | E16: ='[1]Data Room>'!I13 -> 2613 | F16: ='[1]Data Room>'!J13 -> 2932 | G16: ='[1]Data Room>'!K13 -> 3657 | H16: ='[1]Data Room>'!L13 -> 4017 | I16: ='[1]Data Room>'!M13 -> 3985
B17: Total Current Liabilities | E17: =SUM(E14:E16) -> 6033 | F17: =SUM(F14:F16) -> 7172 | G17: =SUM(G14:G16) -> 7400 | H17: =SUM(H14:H16) -> 8002 | I17: =SUM(I14:I16) -> 8006
A19: # | B19: Net Working Capital | E19: =E10-E17 -> 2749 | F19: =F10-F17 -> 5488 | G19: =G10-G17 -> 6179 | H19: =H10-H17 -> 5960 | I19: =I10-I17 -> 5705
B21: Non-current Assets
B22: ='[1]Data Room>'!A16 -> Land | E22: ='[1]Data Room>'!I16 -> 644 | F22: ='[1]Data Room>'!J16 -> 644 | G22: ='[1]Data Room>'!K16 -> 804 | H22: ='[1]Data Room>'!L16 -> 1126 | I22: ='[1]Data Room>'!M16 -> 1050
B23: ='[1]Data Room>'!A17 -> Building | E23: ='[1]Data Room>'!I17 -> 2249 | F23: ='[1]Data Room>'!J17 -> 2325 | G23: ='[1]Data Room>'!K17 -> 2883 | H23: ='[1]Data Room>'!L17 -> 3390 | I23: ='[1]Data Room>'!M17 -> 4136
B24: ='[1]Data Room>'!A18 -> Plant Machinery | E24: ='[1]Data Room>'!I18 -> 4340 | F24: ='[1]Data Room>'!J18 -> 4531 | G24: ='[1]Data Room>'!K18 -> 4825 | H24: ='[1]Data Room>'!L18 -> 5422 | I24: ='[1]Data Room>'!M18 -> 7576
B25: ='[1]Data Room>'!A19 -> Equipments | E25: ='[1]Data Room>'!I19 -> 243 | F25: ='[1]Data Room>'!J19 -> 253 | G25: ='[1]Data Room>'!K19 -> 270 | H25: ='[1]Data Room>'!L19 -> 298 | I25: ='[1]Data Room>'!M19 -> 325
B26: ='[1]Data Room>'!A20 -> Furniture n fittings | E26: ='[1]Data Room>'!I20 -> 99 | F26: ='[1]Data Room>'!J20 -> 113 | G26: ='[1]Data Room>'!K20 -> 146 | H26: ='[1]Data Room>'!L20 -> 175 | I26: ='[1]Data Room>'!M20 -> 203
B27: ='[1]Data Room>'!A21 -> Vehicles | E27: ='[1]Data Room>'!I21 -> 38 | F27: ='[1]Data Room>'!J21 -> 32 | G27: ='[1]Data Room>'!K21 -> 36 | H27: ='[1]Data Room>'!L21 -> 40 | I27: ='[1]Data Room>'!M21 -> 39
B28: ='[1]Data Room>'!A22 -> Intangible Assets | E28: ='[1]Data Room>'!I22 -> 476 | F28: ='[1]Data Room>'!J22 -> 345 | G28: ='[1]Data Room>'!K22 -> 422 | H28: ='[1]Data Room>'!L22 -> 850 | I28: ='[1]Data Room>'!M22 -> 827
B29: ='[1]Data Room>'!A23 -> Other fixed assets | E29: ='[1]Data Room>'!I23 -> 302 | F29: ='[1]Data Room>'!J23 -> 294 | G29: ='[1]Data Room>'!K23 -> 289 | H29: ='[1]Data Room>'!L23 -> 321 | I29: ='[1]Data Room>'!M23 -> 328
B30: Gross Block | E30: =SUM(E22:E29) -> 8391 | F30: =SUM(F22:F29) -> 8537 | G30: =SUM(G22:G29) -> 9675 | H30: =SUM(H22:H29) -> 11622 | I30: =SUM(I22:I29) -> 14484
B31: Accumulated Depreceation | E31: ='[1]Data Room>'!B25 -> 1242 | F31: ='[1]Data Room>'!C25 -> 1452 | G31: ='[1]Data Room>'!D25 -> 327 | H31: ='[1]Data Room>'!E25 -> 610 | I31: ='[1]Data Room>'!F25 -> 973
B32: Net non-current assets | E32: =E30-E31 -> 7149 | F32: =F30-F31 -> 7085 | G32: =G30-G31 -> 9348 | H32: =H30-H31 -> 11012 | I32: =I30-I31 -> 13511
A34: # | B34: Invested Capital | E34: =E32+E19 -> 9898 | F34: =F32+F19 -> 12573 | G34: =G32+G19 -> 15527 | H34: =H32+H19 -> 16972 | I34: =I32+I19 -> 19216
B35: EBIT | E35: ='Historical FS'!C25+'Historical FS'!C19 -> 21684.47 | F35: ='Historical FS'!D25+'Historical FS'!D19 -> -3116.14 | G35: ='Historical FS'!E25+'Historical FS'!E19 -> 5810.93 | H35: ='Historical FS'!F25+'Historical FS'!F19 -> 5180.26 | I35: ='Historical FS'!G25+'Historical FS'!G19 -> 1024.02
A37: # | B37: ROIC | E37: =E35/E34 -> 2.1907931 | F37: =F35/F34 -> -0.24784379 | G37: =G35/G34 -> 0.3742468 | H37: =H35/H34 -> 0.3052239 | I37: =I35/I34 -> 0.053289967
B39: Calculation of Reinvestment Rate | E39: ='Data Room >'!I1 -> 44256 | F39: ='Data Room >'!J1 -> 44621 | G39: ='Data Room >'!K1 -> 44986 | H39: ='Data Room >'!L1 -> 45352 | I39: ='Data Room >'!M1 -> 45717
B41: Net Capex | E41: =-SUM('Raw FS'!I13:I14) -> 280 | F41: =-SUM('Raw FS'!J13:J14) -> 192 | G41: =-SUM('Raw FS'!K13:K14) -> 388 | H41: =-SUM('Raw FS'!L13:L14) -> 1208 | I41: =-SUM('Raw FS'!M13:M14) -> 2185
B42: Change in working capital | F42: =F19-E19 -> 2739 | G42: =G19-F19 -> 691 | H42: =H19-G19 -> -219 | I42: =I19-H19 -> -255
B44: EBIT | E44: =E35 -> 21684.47 | F44: =F35 -> -3116.14 | G44: =G35 -> 5810.93 | H44: =H35 -> 5180.26 | I44: =I35 -> 1024.02
B45: Marginal tax rate | E45: 0.25 | F45: 0.25 | G45: 0.25 | H45: 0.25 | I45: 0.25
B46: EBIT(1-T) | E46: =E44*(1-E45) -> 16263.352 | F46: =F44*(1-F45) -> -2337.105 | G46: =G44*(1-G45) -> 4358.1975 | H46: =H44*(1-H45) -> 3885.195 | I46: =I44*(1-I45) -> 768.015
B48: Reinvestment | F48: =SUM(F41:F42) -> 2931 | G48: =SUM(G41:G42) -> 1079 | H48: =SUM(H41:H42) -> 989 | I48: =SUM(I41:I42) -> 1930
B49: Reinvestment Rate | F49: =F48/F42 -> 1.0700986 | G49: =G48/G42 -> 1.5615051 | H49: =H48/H42 -> -4.5159817 | I49: =I48/I42 -> -7.5686275
G51: 4 - year average | I51: =AVERAGE(F49:I49) -> -2.3632514
G52: 4 - year median | I52: =MEDIAN(F49:I49) -> -1.7229416
B54: Calculation of Growth Rate | E54: 44256 | F54: 44621 | G54: 44986 | H54: 45352 | I54: 45717
B56: ROIC | F56: =F37 -> -0.24784379 | G56: =G37 -> 0.3742468 | H56: =H37 -> 0.3052239 | I56: =I37 -> 0.053289967
B57: Reinvestment Rate | F57: =F49 -> 1.0700986 | G57: =G49 -> 1.5615051 | H57: =H49 -> -4.5159817 | I57: =I49 -> -7.5686275
B59: Intrinsic growth Rate | F59: =F56*F57 -> -0.26521729 | G59: =G56*G57 -> 0.58438827 | H59: =H56*H57 -> -1.3783855 | I59: =I56*I57 -> -0.4033319
G61: 4 - year average | I61: =AVERAGE(F59:I59) -> -0.36563662
G62: 4 - year median | I62: =MEDIAN(F59:I59) -> -0.3342746

Sheet Raw FS
C2: 41699 | D2: 42064 | E2: 42430 | F2: 42795 | G2: 43160 | H2: 43525 | I2: 43891 | J2: 44256 | K2: 44621 | L2: 44986 | M2: 45352 | N2: 45717
B3: Cash from Operating Activity -
B4: Profit from operations | C4: 1839 | D4: 2077 | E4: 2577 | F4: 2809 | G4: 3081 | H4: 3644 | I4: 4116 | J4: 4699 | K4: 4868 | L4: 6089 | M4: 7406 | N4: 6077
B5: Receivables | C5: -157 | D5: -91 | E5: -35 | F5: -241 | G5: -150 | H5: -114 | I5: 116 | J5: -724 | K5: -1142 | L5: -582 | M5: -267 | N5: 259
B6: Inventory | C6: -184 | D6: -131 | E6: 192 | F6: -584 | G6: 16 | H6: -407 | I6: -242 | J6: -297 | K6: -2153 | L6: -44 | M6: 264 | N6: -693
B7: Payables | C7: 359 | D7: -166 | E7: 98 | F7: 464 | G7: 365 | H7: 174 | I7: -368 | J7: 961 | K7: 593 | L7: -442 | M7: 272 | N7: -318
B8: Loans Advances | C8: -37 | D8: 32 | E8: -99 | F8: 0 | G8: 0 | H8: 0 | I8: 0 | J8: 0 | K8: 0 | L8: 0 | M8: 0 | N8: 0
B9: Other WC items | C9: -4 | D9: 12 | E9: 7 | F9: -185 | G9: -191 | H9: 13 | I9: 125 | J9: -164 | K9: 202 | L9: 615 | M9: -185 | N9: 147
B10: Working capital changes | C10: -24 | D10: -344 | E10: 164 | F10: -546 | G10: 40 | H10: -335 | I10: -370 | J10: -225 | K10: -2499 | L10: -453 | M10: 83 | N10: -604
B11: Direct taxes | C11: -444 | D11: -589 | E11: -761 | F11: -843 | G11: -986 | H11: -914 | I11: -933 | J11: -1015 | K11: -1109 | L11: -1415 | M11: -1732 | N11: -1306
B12: Cash from Investing Activity -
B13: Fixed assets purchased | C13: -163 | D13: -336 | E13: -687 | F13: -611 | G13: -1358 | H13: -1067 | I13: -306 | J13: -218 | K13: -415 | L13: -1224 | M13: -2190 | N13: -1067
B14: Fixed assets sold | C14: 5 | D14: 1 | E14: 12 | F14: 2 | G14: 9 | H14: 15 | I14: 26 | J14: 26 | K14: 27 | L14: 16 | M14: 5 | N14: 8
B15: Investments purchased | C15: -1016 | D15: -243 | E15: -282 | F15: -70 | G15: -153 | H15: -325 | I15: -25 | J15: -140 | K15: 0 | L15: -146 | M15: -212 | N15: 0
B16: Investments sold | C16: 461 | D16: 246 | E16: 233 | F16: 224 | G16: 196 | H16: 485 | I16: 117 | J16: 272 | K16: 207 | L16: 444 | M16: 273 | N16: 384
B17: Interest received | C17: 5 | D17: 5 | E17: 5 | F17: 14 | G17: 20 | H17: 33 | I17: 41 | J17: 47 | K17: 56 | L17: 61 | M17: 106 | N17: 128
B18: Dividends received | C18: 91 | D18: 71 | E18: 70 | F18: 77 | G18: 43 | H18: 46 | I18: 35 | J18: 16 | K18: 15 | L18: 68 | M18: 157 | N18: 140
B19: Invest in subsidiaries | C19: 0 | D19: 0 | E19: -143 | F19: 0 | G19: -212 | H19: 0 | I19: -380 | J19: 0 | K19: 0 | L19: -398 | M19: -263 | N19: -698
B20: Loans to subsidiaries | C20: 0 | D20: 0 | E20: 0 | F20: 0 | G20: 0 | H20: -2 | I20: -6 | J20: 0 | K20: 0 | L20: 0 | M20: 0 | N20: 0
B21: Acquisition of companies | C21: 0 | D21: 0 | E21: 0 | F21: 0 | G21: 0 | H21: 0 | I21: 0 | J21: 0 | K21: -80 | L21: 0 | M21: 0 | N21: 0
B22: Other investing items | C22: 0 | D22: -36 | E22: -70 | F22: -219 | G22: 85 | H22: -18 | I22: -276 | J22: -439 | K22: -151 | L22: -219 | M22: -146 | N22: 273
B23: Cash from Financing Activity -
B24: Proceeds from shares | C24: 0 | D24: 0 | E24: 0 | F24: 0 | G24: 0 | H24: 0 | I24: 0 | J24: 0 | K24: 0 | L24: 0 | M24: 1 | N24: 0
B25: Proceeds from borrowings | C25: 1 | D25: 20 | E25: 6 | F25: 8 | G25: 0 | H25: 154 | I25: 18 | J25: 117 | K25: 86 | L25: 74 | M25: 39 | N25: 195
B26: Repayment of borrowings | C26: -8 | D26: -48 | E26: -7 | F26: -41 | G26: -2 | H26: -1 | I26: 0 | J26: -6 | K26: -8 | L26: -9 | M26: -84 | N26: -57
B27: Interest paid fin | C27: -25 | D27: -27 | E27: -20 | F27: -23 | G27: -20 | H27: -74 | I27: -77 | J27: -69 | K27: -68 | L27: -92 | M27: -120 | N27: -142
B28: Dividends paid | C28: -528 | D28: -673 | E28: -749 | F28: -914 | G28: -1185 | H28: -1022 | I28: -2090 | J28: -466 | K28: -1741 | L28: -1909 | M28: -2532 | N28: -3108
B29: Financial liabilities | C29: 0 | D29: 0 | E29: 0 | F29: 0 | G29: 0 | H29: -145 | I29: -149 | J29: -159 | K29: -183 | L29: -214 | M29: -251 | N29: -267
B30: Other financing items | C30: 0 | D30: 0 | E30: 66 | F30: 13 | G30: -32 | H30: 0 | I30: -203 | J30: 0 | K30: -75 | L30: -36 | M30: 0 | N30: -37
B31: Net Cash Flow | C31: 194 | D31: 124 | E31: 413 | F31: -120 | G31: -474 | H31: 473 | I31: -462 | J31: 2440 | K31: -1069 | L31: 640 | M31: 540 | N31: -82

Sheet Data >

Sheet Data Sheet
A1: COMPANY NAME | B1: TATA MOTORS LTD | E1: =IF(B2<>B3, "A NEW VERSION OF THE WORKSHEET IS AVAILABLE", "")
A2: LATEST VERSION | B2: 2.1 | E2: PLEASE DO NOT MAKE ANY CHANGES TO THIS SHEET
A3: CURRENT VERSION | B3: 2.1
A5: META
A6: Number of shares | B6: =IF(B9>0, B9/B8, 0) -> 368.14288
A7: Face Value | B7: 2
A8: Current Price | B8: 654.6
A9: Market Capitalization | B9: 240986.33
A15: PROFIT & LOSS
A16: Report Date | B16: 42460 | C16: 42825 | D16: 43190 | E16: 43555 | F16: 43921 | G16: 44286 | H16: 44651 | I16: 45016 | J16: 45382 | K16: 45747
A17: Sales | B17: 273045.6 | C17: 269692.51 | D17: 291550.48 | E17: 301938.4 | F17: 261067.97 | G17: 249794.75 | H17: 278453.62 | I17: 345966.97 | J17: 434016 | K17: 439695
A18: Raw Material Cost | B18: 166134.01 | C18: 173294.08 | D18: 187896.58 | E18: 194267.91 | F18: 164899.82 | G18: 153607.36 | H18: 179295.33 | I18: 231251.26 | J18: 274321 | K18: 268950
A19: Change in Inventory | B19: 2750.99 | C19: 7399.92 | D19: 2046.58 | E19: -2053.28 | F19: -2231.19 | G19: -4684.16 | H19: -1590.49 | I19: 4781.62 | J19: 1566 | K19: -2836
A20: Power and Fuel | B20: 1143.63 | C20: 1159.82 | D20: 1308.08 | E20: 1585.93 | F20: 1264.95 | G20: 1112.87 | H20: 2178.29 | I20: 2513.33 | J20: 2189 | K20: 2443
A21: Other Mfr. Exp | B21: 12101.53 | C21: 10067.37 | D21: 10971.66 | E21: 11694.54 | F21: 11541.51 | G21: 8273.17 | H21: 9427.38 | I21: 11765.97 | J21: 17446 | K21: 18813
A22: Employee Cost | B22: 28880.89 | C22: 28332.89 | D22: 30300.09 | E22: 33243.87 | F22: 30438.6 | G22: 27648.48 | H22: 30808.52 | I22: 33654.7 | J22: 41990 | K22: 47767
A23: Selling and admin | B23: 21991.9 | C23: 30039.38 | D23: 31004.58 | E23: 32719.8 | F23: 29248.32 | G23: 23015.79 | H23: 29205.4 | I23: 34839.19 | J23: 42765 | K23: 47099
A24: Other Expenses | B24: 7149.38 | C24: 4610.2 | D24: 658.39 | E24: 1708.74 | F24: 3456.51 | G24: -834.51 | H24: 1228.12 | I24: 4908.34 | J24: -953 | K24: -3429
A25: Other Income | B25: -2669.62 | C25: 1869.1 | D25: 5932.73 | E25: -26686.25 | F25: 101.71 | G25: -11117.83 | H25: 2424.05 | I25: 6663.97 | J25: 4792 | K25: 11774
A26: Depreciation | B26: 16710.78 | C26: 17904.99 | D26: 21553.59 | E26: 23590.63 | F26: 21425.43 | G26: 23546.71 | H26: 24835.69 | I26: 24860.36 | J26: 27239 | K26: 23256
A27: Interest | B27: 4889.08 | C27: 4238.01 | D27: 4681.79 | E27: 5758.6 | F27: 7243.33 | G27: 8097.17 | H27: 9311.86 | I27: 10225.48 | J27: 7594 | K27: 5083
... A30: Net profit | B30: 11579.31 | C30: 7454.36 | D30: 8988.91 | E30: -28826.23 | F30: -12070.85 | G30: -13451.39 | H30: -11441.47 | I30: 2414.29 | J30: 31399 | K30: 27830
A31: Dividend Amount | B31: 67.92 | I31: 766.02 | J31: 2301 | K31: 2208
A40: Quarters
A41: Report Date | B41: 44926 | C41: 45016 | D41: 45107 | E41: 45199 | F41: 45291 | G41: 45382 | H41: 45473 | I41: 45565 | J41: 45657 | K41: 45747
A42: Sales | B42: 88488.59 | C42: 105932.35 | D42: 102236 | E42: 105129 | F42: 110577 | G42: 119033 | H42: 108048 | I42: 101450 | J42: 112608 | K42: 119503
A43: Expenses | B43: 77668.35 | C43: 92817.95 | D43: 89019 | E43: 91362 | F43: 95159 | G43: 102348 | H43: 92263 | I43: 89291 | J43: 100185 | K43: 102685
A44: Other Income | B44: 1129.98 | C44: 1452.86 | D44: 895 | E44: 1557 | F44: 1604 | G44: 1412 | H44: 1747 | I44: 1647 | J44: 1700 | K44: 1057
A45: Depreciation | B45: 6071.78 | C45: 7050.2 | D45: 6633 | E45: 6637 | F45: 6850 | G45: 7143 | H45: 6574 | I45: 6005 | J45: 5399 | K45: 5295
A46: Interest | B46: 2675.83 | C46: 2641.67 | D46: 2615 | E46: 2652 | F46: 2485 | G46: 1645 | H46: 2088 | I46: 2034 | J46: 1119 | K46: 1076
A47: Profit before tax | B47: 3202.61 | C47: 4875.39 | D47: 4864 | E47: 6035 | F47: 7687 | G47: 9309 | H47: 8870 | I47: 5767 | J47: 7605 | K47: 11504
A48: Tax | B48: 262.83 | C48: -620.65 | D48: 1563 | E48: 2203 | F48: 542 | G48: -8219 | H48: 3178 | I48: 2317 | J48: 2120 | K48: 2948
A49: Net profit | B49: 2957.71 | C49: 5407.79 | D49: 3203 | E49: 3764 | F49: 7025 | G49: 17407 | H49: 5566 | I49: 3343 | J49: 5406 | K49: 8470
A50: Operating Profit | B50: 10820.24 | C50: 13114.4 | D50: 13217 | E50: 13767 | F50: 15418 | G50: 16685 | H50: 15785 | I50: 12159 | J50: 12423 | K50: 16818
A55: BALANCE SHEET
A56: Report Date | B56: 42460 | C56: 42825 | D56: 43190 | E56: 43555 | F56: 43921 | G56: 44286 | H56: 44651 | I56: 45016 | J56: 45382 | K56: 45747
A57: Equity Share Capital | B57: 679.18 | C57: 679.22 | D57: 679.22 | E57: 679.22 | F57: 719.54 | G57: 765.81 | H57: 765.88 | I57: 766.02 | J57: 767 | K57: 736
A58: Reserves | B58: 78273.23 | C58: 57382.67 | D58: 94748.69 | E58: 59500.34 | F58: 62358.99 | G58: 54480.91 | H58: 43795.36 | I58: 44555.77 | J58: 84151 | K58: 115408
A59: Borrowings | B59: 69359.96 | C59: 78603.98 | D59: 88950.47 | E59: 106175.34 | F59: 124787.64 | G59: 142130.57 | H59: 146449.03 | I59: 134113.44 | J59: 107264 | K59: 71540
A60: Other Liabilities | B60: 114871.75 | C60: 135914.49 | D60: 142813.43 | E60: 139348.59 | F60: 132313.22 | G60: 144192.62 | H60: 138051.22 | I60: 155239.2 | J60: 177339 | K60: 189289
A61: Total | B61: 263184.12 | C61: 272580.36 | D61: 327191.81 | E61: 305703.49 | F61: 320179.39 | G61: 341569.91 | H61: 329061.49 | I61: 334674.43 | J61: 369521 | K61: 376973
A62: Net Block | B62: 107231.76 | C62: 95944.08 | D62: 121413.86 | E62: 111234.47 | F62: 127107.14 | G62: 138707.61 | H62: 138855.45 | I62: 132079.76 | J62: 121285 | K62: 115697
A63: Capital Work in Progress | B63: 25918.94 | C63: 33698.84 | D63: 40033.5 | E63: 31883.84 | F63: 35622.29 | G63: 20963.93 | H63: 10251.09 | I63: 14274.5 | J63: 35698 | K63: 65806
A64: Investments | B64: 23767.02 | C64: 20337.92 | D64: 20812.75 | E64: 15770.72 | F64: 16308.48 | G64: 24620.28 | H64: 29379.53 | I64: 26379.16 | J64: 22971 | K64: 35656
A65: Other Assets | B65: 106266.4 | C65: 122599.52 | D65: 144931.7 | E65: 146814.46 | F65: 141141.48 | G65: 157278.09 | H65: 150575.42 | I65: 161941.01 | J65: 189567 | K65: 159814
A66: Total | B66: 263184.12 | C66: 272580.36 | D66: 327191.81 | E66: 305703.49 | F66: 320179.39 | G66: 341569.91 | H66: 329061.49 | I66: 334674.43 | J66: 369521 | K66: 376973
A67: Receivables | B67: 13570.91 | C67: 14075.55 | D67: 19893.3 | E67: 18996.17 | F67: 11172.69 | G67: 12679.08 | H67: 12442.12 | I67: 15737.97 | J67: 16952 | K67: 13248
... A70: No. of Equity Shares | B70: 3395930306 | C70: 3396100719 | D70: 3396100719 | E70: 3396100719 | F70: 3597726185 | G70: 3829060661 | H70: 3829414903 | I70: 3830097221 | J70: 3832491897 | K70: 3681348742
A71: New Bonus Shares
A72: Face value | B72: 2 | C72: 2 | D72: 2 | E72: 2 | F72: 2 | G72: 2 | H72: 2 | I72: 2 | J72: 2 | K72: 2
A74: Other assets | B74: =B65-SUM(B67:B69) -> 29579.36 | C74: =C65-SUM(C67:C69) -> 37360.78 | D74: =D65-SUM(D67:D69) -> 48286.86 | E74: =E65-SUM(E67:E69) -> 56155.74 | F74: =F65-SUM(F67:F69) -> 58784.94 | G74: =G65-SUM(G67:G69) -> 61717.96 | H74: =H65-SUM(H67:H69) -> 62223.77 | I74: =I65-SUM(I67:I69) -> 68432.09 | ... K74: =K65-SUM(K67:K69) -> 58463
A80: CASH FLOW:
A81: Report Date | B81: 42460 | C81: 42825 | D81: 43190 | E81: 43555 | F81: 43921 | G81: 44286 | H81: 44651 | I81: 45016 | J81: 45382 | K81: 45747
A82: Cash from Operating Activity | B82: 37899.54 | C82: 30199.25 | D82: 23857.42 | E82: 18890.75 | F82: 26632.94 | G82: 29000.51 | H82: 14282.83 | I82: 35388.01 | J82: 67915 | K82: 63102
A83: Cash from Investing Activity | B83: -36693.9 | C83: -39571.4 | D83: -25139.14 | E83: -20878.07 | F83: -33114.55 | G83: -25672.5 | H83: -4443.66 | I83: -15417.17 | J83: -22781 | K83: -49982
A84: Cash from Financing Activity | B84: -3795.12 | C84: 6205.3 | D84: 2011.71 | E84: 8830.37 | F84: 3389.61 | G84: 9904.2 | H84: -3380.17 | I84: -26242.9 | J84: -37006 | K84: -18786
A85: Net Cash Flow | B85: -2589.48 | C85: -3166.85 | D85: 729.99 | E85: 6843.05 | F85: -3092 | G85: 13232.21 | H85: 6459 | I85: -6272.06 | J85: 8128 | K85: -5666
A90: PRICE: | B90: 386.6 | C90: 465.85 | D90: 326.85 | E90: 174.25 | F90: 71.05 | G90: 301.8 | H90: 433.75 | I90: 420.8 | J90: 992.8 | K90: 674.45
A92: DERIVED:
A93: Adjusted Equity Shares in Cr | B93: 288.72 | C93: 288.73 | D93: 288.73 | E93: 288.73 | F93: 308.9 | G93: 332.03 | H93: 332.07 | I93: 332.13 | J93: 332.37 | K93: 368.13

Sheet Data Room >
B1: 41699 | C1: 42064 | D1: 42430 | E1: 42795 | F1: 43160 | G1: 43525 | H1: 43891 | I1: 44256 | J1: 44621 | K1: 44986 | L1: 45352 | M1: 45717
A2: Equity Capital | B2: 96 | C2: 96 | D2: 96 | E2: 96 | F2: 96 | G2: 96 | H2: 96 | I2: 96 | J2: 96 | K2: 96 | L2: 96 | M2: 96
A3: Reserves | B3: 3943 | C3: 4646 | D3: 6429 | E3: 7508 | F3: 8314 | G3: 9375 | H3: 10034 | I3: 12710 | J3: 13716 | K3: 15896 | L3: 18632 | M3: 19304
A4: Borrowings -
A5: Long term Borrowings | B5: 41 | C5: 78 | D5: 73 | E5: 41 | F5: 28 | G5: 19 | H5: 19 | I5: 15 | J5: 45 | K5: 76 | L5: 54 | M5: 260
A6: Short term Borrowings | B6: 199 | C6: 332 | D6: 231 | E6: 504 | F6: 492 | G6: 597 | H6: 321 | I6: 334 | J6: 731 | K6: 896 | L6: 1053 | M6: 604
A7: Lease Liabilities | B7: 0 | C7: 0 | D7: 0 | E7: 0 | F7: 0 | G7: 693 | H7: 764 | I7: 745 | J7: 811 | K7: 960 | L7: 1367 | M7: 1427
A8: Other Borrowings | B8: 9 | C8: 8 | D8: 20 | E8: 15 | F8: 13 | G8: 11 | H8: 15 | I8: 0 | J8: 0 | K8: 0 | L8: 0 | M8: 0
A9: Other Liabilities - | B9: 3787 | C9: 3754 | D9: 3711 | E9: 4241 | F9: 4820 | G9: 5459 | H9: 4889 | I9: 6456 | J9: 7560 | K9: 7854 | L9: 8698 | M9: 8665
A10: Non controlling int | B10: 246 | C10: 264 | D10: 384 | E10: 375 | F10: 328 | G10: 361 | H10: 404 | I10: 423 | J10: 388 | K10: 454 | L10: 695 | M10: 659
A11: Trade Payables | B11: 1746 | C11: 1549 | D11: 1565 | E11: 1923 | F11: 2160 | G11: 2394 | H11: 2137 | I11: 3379 | J11: 4164 | K11: 3635 | L11: 3831 | M11: 3848
A12: Advance from Customers | B12: 0 | C12: 5 | D12: 12 | E12: 17 | F12: 16 | G12: 13 | H12: 29 | I12: 41 | J12: 76 | K12: 108 | L12: 154 | M12: 173
A13: Other liability items | B13: 1795 | C13: 1937 | D13: 1750 | E13: 1925 | F13: 2316 | G13: 2690 | H13: 2320 | I13: 2613 | J13: 2932 | K13: 3657 | L13: 4017 | M13: 3985
A14: Total Liabilities | B14: 8075 | C14: 8914 | D14: 10559 | E14: 12405 | F14: 13763 | G14: 16249 | H14: 16138 | I14: 20355 | J14: 22958 | K14: 25779 | L14: 29901 | M14: 30355
A15: Fixed Assets -
A16: Land | B16: 247 | C16: 251 | D16: 429 | E16: 408 | F16: 586 | G16: 605 | H16: 640 | I16: 644 | J16: 644 | K16: 804 | L16: 1126 | M16: 1050
A17: Building | B17: 931 | C17: 962 | D17: 923 | E17: 931 | F17: 957 | G17: 2402 | H17: 2257 | I17: 2249 | J17: 2325 | K17: 2883 | L17: 3390 | M17: 4136
A18: Plant Machinery | B18: 2054 | C18: 2132 | D18: 1793 | E18: 1980 | F18: 2157 | G18: 4006 | H18: 4208 | I18: 4340 | J18: 4531 | K18: 4825 | L18: 5422 | M18: 7576
A19: Equipments | B19: 155 | C19: 171 | D19: 97 | E19: 119 | F19: 200 | G19: 221 | H19: 241 | I19: 243 | J19: 253 | K19: 270 | L19: 298 | M19: 325
A20: Furniture n fittings | B20: 71 | C20: 83 | D20: 49 | E20: 59 | F20: 72 | G20: 88 | H20: 94 | I20: 99 | J20: 113 | K20: 146 | L20: 175 | M20: 203
A21: Vehicles | B21: 14 | C21: 18 | D21: 11 | E21: 14 | F21: 27 | G21: 47 | H21: 43 | I21: 38 | J21: 32 | K21: 36 | L21: 40 | M21: 39
A22: Intangible Assets | B22: 203 | C22: 351 | D22: 339 | E22: 276 | F22: 468 | G22: 512 | H22: 505 | I22: 476 | J22: 345 | K22: 422 | L22: 850 | M22: 827
A23: Other fixed assets | B23: 128 | C23: 145 | D23: 103 | E23: 128 | F23: 238 | G23: 261 | H23: 293 | I23: 302 | J23: 294 | K23: 289 | L23: 321 | M23: 328
A24: Gross Block | B24: 3804 | C24: 4112 | D24: 3744 | E24: 3914 | F24: 4705 | G24: 8141 | H24: 8282 | I24: 8392 | J24: 8538 | K24: 9676 | L24: 11622 | M24: 14484
A25: Accumulated Depreciation | B25: 1242 | C25: 1452 | D25: 327 | E25: 610 | F25: 973 | G25: 1644 | H25: 2010 | I25: 2533 | J25: 3019 | K25: 3905 | L25: 4475 | M25: 5264
A26: Net Block | B26: =B24-B25 -> 2562 | C26: =C24-C25 -> 2660 | D26: =D24-D25 -> 3417 | E26: =E24-E25 -> 3304 | F26: =F24-F25 -> 3732 | G26: =G24-G25 -> 6497 | H26: =H24-H25 -> 6272 | I26: =I24-I25 -> 5859 | ... M26: =M24-M25 -> 9220
A28: CWIP | B28: 72 | C28: 196 | D28: 107 | E28: 258 | F28: 1405 | G28: 210 | H28: 140 | I28: 183 | J28: 426 | K28: 1020 | L28: 2698 | M28: 1254
A29: Investments | B29: 1424 | C29: 1588 | D29: 2712 | E29: 2652 | F29: 2141 | G29: 2569 | H29: 2019 | I29: 4737 | J29: 3248 | K29: 4262 | L29: 4588 | M29: 4725
A31: Other Assets -
A32: Inventories | B32: 2070 | C32: 2259 | D32: 1998 | E32: 2627 | F32: 2658 | G32: 3150 | H32: 3390 | I32: 3799 | J32: 6153 | K32: 6211 | L32: 5923 | M32: 6719
A33: Trade receivables - | B33: 1110 | C33: 1182 | D33: 1187 | E33: 1447 | F33: 1731 | G33: 1907 | H33: 1795 | I33: 2602 | J33: 3871 | K33: 4637 | L33: 4889 | M33: 4314
A34: Prov for Doubtful | B34: -50 | C34: -59 | D34: -67 | E34: -79 | F34: -89 | G34: -121 | H34: -155 | I34: -185 | J34: -241 | K34: -305 | L34: -422 | M34: -663
A35: Cash Equivalents | B35: 229 | C35: 204 | D35: 424 | E35: 801 | F35: 405 | G35: 445 | H35: 783 | I35: 611 | J35: 864 | K35: 844 | L35: 1084 | M35: 782
A36: Loans n Advances | B36: 7 | C36: 8 | D36: 9 | E36: 14 | F36: 13 | G36: 16 | H36: 12 | I36: 11 | J36: 8 | K36: 12 | L36: 17 | M36: 22
A37: Other asset items | B37: 603 | C37: 817 | D37: 705 | E37: 1303 | F37: 1678 | G37: 1456 | H37: 1727 | I37: 2555 | J37: 2869 | K37: 3024 | L37: 3555 | M37: 3319
A38: Total Assets | B38: 8075 | C38: 8914 | D38: 10559 | E38: 12405 | F38: 13763 | G38: 16249 | H38: 16138 | I38: 20355 | J38: 22958 | K38: 25779 | L38: 29901 | M38: 30355

Sheet Cashflow Data
B2: 41699 | C2: 42064 | D2: 42430 | E2: 42795 | F2: 43160 | G2: 43525 | H2: 43891 | I2: 44256 | J2: 44621 | K2: 44986 | L2: 45352 | M2: 45717
B3: Cash from Operating Activity - | C3: 2463 | D3: -2214 | E3: 2703 | F3: 1453 | G3: 4134 | H3: 6293 | I3: -1455 | J3: 6680 | K3: 5282 | L3: 4775 | M3: 8662 | N3: 9795
B4: Profit from operations | C4: -563 | D4: -620 | E4: 3502 | F4: 1662 | G4: 4091 | H4: 6167 | I4: 439 | J4: 1961 | K4: 2683 | L4: 5010 | M4: 8523 | N4: 8615
B5: Receivables | C5: 381 | D5: -20 | E5: -678 | F5: -199 | G5: -1217 | H5: 164 | I5: 1168 | J5: -142 | K5: -1016 | L5: -306 | M5: -553 | N5: 388
B6: Inventory | C6: 592 | D6: -940 | E6: -235 | F6: -572 | G6: -278 | H6: 966 | I6: 730 | J6: -765 | K6: -1201 | L6: 658 | M6: -541 | N6: 257
B7: Payables | C7: 1213 | D7: -843 | E7: 76 | F7: 2314 | G7: 2764 | H7: -725 | I7: -2689 | J7: 4965 | K7: 5285 | L7: -957 | M7: 315 | N7: -56
B8: Loans Advances | C8: 0 | D8: 0 | E8: -55 | F8: 0 | G8: 0 | H8: 0 | I8: 0 | J8: 0 | K8: 0 | L8: 0 | M8: 0 | N8: 0
B9: Other WC items | C9: 896 | D9: 286 | E9: 115 | F9: -1636 | G9: -1217 | H9: -97 | I9: -1011 | J9: 725 | K9: -314 | L9: 539 | M9: 1164 | N9: 583
B10: Working capital changes | C10: 3082 | D10: -1517 | E10: -776 | F10: -93 | G10: 52 | H10: 308 | I10: -1801 | J10: 4783 | K10: 2755 | L10: -67 | M10: 385 | N10: 1172
B11: Direct taxes | C11: -56 | D11: -78 | E11: -24 | F11: -115 | G11: -8 | H11: -182 | I11: -93 | J11: -63 | K11: -156 | L11: -168 | M11: -246 | N11: 8
B12: Cash from Investing Activity - | C12: 2563 | D12: 246 | E12: -3264 | F12: -2860 | G12: -710 | H12: -3822 | I12: -4637 | J12: -2988 | K12: -4681 | L12: 917 | M12: 1492 | N12: -3821
B13: Fixed assets purchased | C13: -3105 | D13: -3079 | E13: -3284 | F13: -3514 | G13: -2823 | H13: -4783 | I13: -4669 | J13: -1856 | K13: -1831 | L13: -1697 | M13: -1991 | N13: -2043
B14: Fixed assets sold | C14: 11 | D14: 25 | E14: 34 | F14: 17 | G14: 28 | H14: 30 | I14: 155 | J14: 178 | K14: 100 | L14: 123 | M14: 39 | N14: 113
... B34: Net Cash Flow | C34: -7 | D34: 663 | E34: -639 | F34: -198 | G34: 318 | H34: -59 | I34: 1658 | J34: 220 | K34: 85 | L34: -1329 | M34: 2224 | N34: -2958
