Workbook

Sheet DCF >

Sheet WACC
B2: Weighted Average Cost of Capital
B4: All figures are in INR unless stated otherwise
B6: Peer comps
H7: Debt / | I7: Debt / | J7: Levered | K7: Unlevered
B8: Name of Comp | D8: Country | E8: Total Debt | F8: Total Equity | G8: Tax Rate 1 | H8: Equity | I8: Capital | J8: Beta 2 | K8: Beta 3
B9: Avenue Super. | D9: India | E9: 819.62 | F9: 305766.46 | G9: 0.3 | H9: =E9/F9 -> 0.0026805425 | I9: =E9/(F9+E9) -> 0.0026733764 | J9: 1.05 | K9: =J9/(1+(1-G9)*H9) -> 1.0480335
B10: Vishal Mega Mart | D10: India | E10: 1729.38 | F10: 70279.65 | G10: 0.3 | H10: =E10/F10 -> 0.024607123 | I10: =E10/(F10+E10) -> 0.024016155 | J10: 1.06 | K10: =J10/(1+(1-G10)*H10) -> 1.0420507
B11: Shoppers Stop | D11: India | E11: 3314.09 | F11: 5998.38 | G11: 0.3 | H11: =E11/F11 -> 0.55249751 | I11: =E11/(F11+E11) -> 0.35587658 | J11: 0.882 | K11: =J11/(1+(1-G11)*H11) -> 0.63602027
B12: V-Mart Retail | D12: India | E12: 782.51 | F12: 5937.32 | G12: 0.3 | H12: =E12/F12 -> 0.13179515 | I12: =E12/(F12+E12) -> 0.11644789 | J12: 1.4 | K12: =J12/(1+(1-G12)*H12) -> 1.2817501
B13: Electronics Mart | D13: India | E13: 1976.45 | F13: 5060.59 | G13: 0.3 | H13: =E13/F13 -> 0.39055723 | I13: =E13/(F13+E13) -> 0.28086383 | J13: 1.3 | K13: =J13/(1+(1-G13)*H13) -> 1.0208969
F16: Average | G16: =AVERAGE(G9:G13) -> 0.3 | H16: =AVERAGE(H9:H13) -> 0.22042751 | I16: =AVERAGE(I9:I13) -> 0.15597557 | J16: =AVERAGE(J9:J13) -> 1.1384 | K16: =AVERAGE(K9:K13) -> 1.0057503
F17: Median | G17: =MEDIAN(G9:G13) -> 0.3 | H17: =MEDIAN(H9:H13) -> 0.13179515 | I17: =MEDIAN(I9:I13) -> 0.11644789 | J17: =MEDIAN(J9:J13) -> 1.06 | K17: =MEDIAN(K9:K13) -> 1.0420507
B19: Cost of Debt | H19: Cost of Equity
B21: Pre-Tax Cost of Debt | F21: 0.084 | H21: Risk Free Rate | K21: 0.0793
B22: Tax Rate | F22: =G9 -> 0.3 | H22: Equity Risk Premium | K22: 0.08
B23: Post- Tax Cost of Debt | F23: =F21*(1-F22) -> 0.0588 | H23: Levered Beta 4 | K23: =K17*(1+(1-F22)*F34) -> 1.1768502
H24: Cost of Equity | K24: =K21+K23*K22 -> 0.17344802
B27: Capital Structure | H27: Levered Beta
E29: Current | F29: Target | H29: Comps Median Unlevered Beta | K29: =K17 -> 1.0420507
B30: Total Debt | D30: =E9 -> 819.62 | E30: =D30/$D$32 -> 0.0026733764 | F30: =I16 -> 0.15597557 | H30: Target Debt / Equity | K30: =F34 -> 0.18479982
B31: Market Capitalization | D31: =F9 -> 305766.46 | E31: =D31/$D$32 -> 0.99732662 | F31: =F32-F30 -> 0.84402443 | H31: Tax Rate | K31: =F22 -> 0.3
B32: Total Capital | D32: =SUM(D30:D31) -> 306586.08 | E32: =D32/$D$32 -> 1 | F32: =E32 -> 1 | H32: Levered Beta | K32: =K29*(1+(1-K31)*K30) -> 1.1768502
B34: Debt/Equity | E34: =E30/E31 -> 0.0026805425 | F34: =F30/F31 -> 0.18479982 | H34: Weighted Average Cost of Capital
B36: Notes- | K36: Total Cost | L36: Total Weight
H37: Debt | K37: =F23 -> 0.0588 | L37: =F30 -> 0.15597557
H38: Equity | K38: =K24 -> 0.17344802 | L38: =1-L37 -> 0.84402443
H39: Weighted Average Cost of Capital | L39: =SUMPRODUCT(K37:K38,L37:L38) -> 0.15556573

Sheet Beta regression
A1: Regression - 2 years taken weekly
B3: Avenue Supermart Pvt. Ltd. | F3: Nifty | I3: Adjusted Beta
B5: Date | C5: Price | D5: Change in Price | F5: Price | G5: Change in price | I5: Raw Beta | J5: =N26 -> 1.0323078
B6: 45886 | C6: 4698.8 | F6: 24870.1 | I6: Weight | J6: 0.75
B7: 45879 | C7: 4358.2 | D7: =(C7-C6)/C6 -> -0.072486592 | F7: 24631.3 | G7: =(F7-F6)/F6 -> -0.0096018914
B8: 45872 | C8: 4170.1 | D8: =(C8-C7)/C7 -> -0.04316002 | F8: 24363.3 | G8: =(F8-F7)/F7 -> -0.010880465 | I8: Market Beta | J8: =1 -> 1
B9: 45865 | C9: 4196 | D9: =(C9-C8)/C8 -> 0.0062108822 | F9: 24565.35 | G9: =(F9-F8)/F8 -> 0.0082932115 | I9: Weight | J9: 0.25 | L9: Beta | M9: SUMMARY OUTPUT
B10: 45858 | C10: 3997 | D10: =(C10-C9)/C9 -> -0.04742612 | F10: 24837 | G10: =(F10-F9)/F9 -> 0.011058259
B11: 45851 | C11: 4048.6 | D11: =(C11-C10)/C10 -> 0.012909682 | F11: 24968.4 | G11: =(F11-F10)/F10 -> 0.005290494 | I11: Adjusted Beta | J11: =J5*J6+J8*J9 -> 1.0242309 | M11: Regression Statistics
B12: 45844 | C12: 4064.2 | D12: =(C12-C11)/C11 -> 0.0038531838 | F12: 25149.85 | G12: =(F12-F11)/F11 -> 0.0072671857 | M12: Multiple R | N12: 0.43553377
B13: 45837 | C13: 4261.1 | D13: =(C13-C12)/C12 -> 0.048447419 | F13: 25461 | G13: =(F13-F12)/F12 -> 0.012371843 | M13: R Square | N13: 0.18968966
B14: 45830 | C14: 4313.5 | D14: =(C14-C13)/C13 -> 0.012297294 | F14: 25637.8 | G14: =(F14-F13)/F13 -> 0.0069439535 | M14: Adjusted R Square | N14: 0.18166679
B15: 45823 | C15: 4300.3 | D15: =(C15-C14)/C14 -> -0.00306016 | F15: 25112.4 | G15: =(F15-F14)/F14 -> -0.020493178 | M15: Standard Error | N15: 0.037123309
B16: 45816 | C16: 4051.9 | D16: =(C16-C15)/C15 -> -0.057763412 | F16: 24718.6 | G16: =(F16-F15)/F15 -> -0.015681496 | M16: Observations | N16: 103
B17: 45809 | C17: 4201.6 | D17: =(C17-C16)/C16 -> 0.03694563 | F17: 25003.05 | G17: =(F17-F16)/F16 -> 0.011507529
B18: 45802 | C18: 4002.1 | D18: =(C18-C17)/C17 -> -0.047481912 | F18: 24750.7 | G18: =(F18-F17)/F17 -> -0.010092769 | M18: ANOVA
B19: 45795 | C19: 4140.8 | D19: =(C19-C18)/C18 -> 0.034656805 | F19: 24853.15 | G19: =(F19-F18)/F18 -> 0.0041392769 | N19: df | O19: SS | P19: MS | Q19: F | R19: Significance F
B20: 45788 | C20: 4189.7 | D20: =(C20-C19)/C19 -> 0.011809312 | F20: 25019.8 | G20: =(F20-F19)/F19 -> 0.0067053874 | M20: Regression | N20: 1 | O20: 0.032584197 | P20: 0.032584197 | Q20: 23.643603 | R20: 4.2668481e-06
B21: 45781 | C21: 3972.4 | D21: =(C21-C20)/C20 -> -0.051865289 | F21: 24008 | G21: =(F21-F20)/F20 -> -0.040439972 | M21: Residual | N21: 101 | O21: 0.13919215 | P21: 0.0013781401
B22: 45774 | C22: 4059.2 | D22: =(C22-C21)/C21 -> 0.02185077 | F22: 24346.7 | G22: =(F22-F21)/F21 -> 0.014107797 | M22: Total | N22: 102 | O22: 0.17177634
B23: 45767 | C23: 4375.2 | D23: =(C23-C22)/C22 -> 0.077847852 | F23: 24039.35 | G23: =(F23-F22)/F22 -> -0.012623887
B24: 45760 | C24: 4357.1 | D24: =(C24-C23)/C23 -> -0.0041369537 | F24: 23851.65 | G24: =(F24-F23)/F23 -> -0.0078080314 | N24: Coefficients | O24: Standard Error | P24: t Stat | Q24: P-value | R24: Lower 95% | S24: Upper 95% | T24: Lower 95.0% | U24: Upper 95.0%
B25: 45753 | C25: 4131.5 | D25: =(C25-C24)/C24 -> -0.051777558 | F25: 22828.55 | G25: =(F25-F24)/F24 -> -0.042894307 | M25: Intercept | N25: 0.00098590718 | O25: 0.0036887302 | P25: 0.26727549 | Q25: 0.78980206 | R25: -0.0063315413 | S25: 0.0083033557 | T25: -0.0063315413 | U25: 0.0083033557
B26: 45746 | C26: 4039.9 | D26: =(C26-C25)/C25 -> -0.022171124 | F26: 22904.45 | G26: =(F26-F25)/F25 -> 0.0033247841 | M26: X Variable 1 | N26: 1.0323078 | O26: 0.21230117 | P26: 4.8624688 | Q26: 4.2668481e-06 | R26: 0.61115942 | S26: 1.4534563 | T26: 0.61115942 | U26: 1.4534563
B27: 45739 | C27: 4083.2 | D27: =(C27-C26)/C26 -> 0.010718087 | F27: 23519.35 | G27: =(F27-F26)/F26 -> 0.026846312
B28: 45732 | C28: 3892.2 | D28: =(C28-C27)/C27 -> -0.046777038 | F28: 23350.4 | G28: =(F28-F27)/F27 -> -0.0071834468
B29: 45725 | C29: 3797.1 | D29: =(C29-C28)/C28 -> -0.024433482 | F29: 22397.2 | G29: =(F29-F28)/F28 -> -0.040821571
B30: 45718 | C30: 3593.6 | D30: =(C30-C29)/C29 -> -0.053593532 | F30: 22552.5 | G30: =(F30-F29)/F29 -> 0.0069339025
B31: 45711 | C31: 3403.95 | D31: =(C31-C30)/C30 -> -0.052774377 | F31: 22124.7 | G31: =(F31-F30)/F30 -> -0.018969072
B32: 45704 | C32: 3596.7 | D32: =(C32-C31)/C31 -> 0.056625391 | F32: 22795.9 | G32: =(F32-F31)/F31 -> 0.030337135
B33: 45697 | C33: 3682.65 | D33: =(C33-C32)/C32 -> 0.023896905 | F33: 22929.25 | G33: =(F33-F32)/F32 -> 0.0058497361
B34: 45690 | C34: 3743.5 | D34: =(C34-C33)/C33 -> 0.016523427 | F34: 23559.95 | G34: =(F34-F33)/F33 -> 0.027506351
B35: 45683 | C35: 3664.65 | D35: =(C35-C34)/C34 -> -0.021063176 | F35: 23508.4 | G35: =(F35-F34)/F34 -> -0.0021880352
B36: 45676 | C36: 3579.95 | D36: =(C36-C35)/C35 -> -0.023112712 | F36: 23092.2 | G36: =(F36-F35)/F35 -> -0.01770431
B37: 45669 | C37: 3620.65 | D37: =(C37-C36)/C36 -> 0.011368874 | F37: 23203.2 | G37: =(F37-F36)/F36 -> 0.0048068179
B38: 45662 | C38: 3686.25 | D38: =(C38-C37)/C37 -> 0.018118294 | F38: 23431.5 | G38: =(F38-F37)/F37 -> 0.0098391601
... B109: 45165 | C109: 3761.05 | D109: =(C109-C108)/C108 -> -0.0056445643 | F109: 19435.3 | G109: =(F109-F108)/F108 -> -0.019407213

Sheet Beta - Comps
B2: Calculation of ROIC
B4: Current Assets

Sheet Intrinsic Growth
B2: Calculation of ROIC | E2: ='Data Room>'!I1 -> 44256 | F2: ='Data Room>'!J1 -> 44621 | G2: ='Data Room>'!K1 -> 44986 | H2: ='Data Room>'!L1 -> 45352 | I2: ='Data Room>'!M1 -> 45717
B4: Current Assets
B5: ='Data Room>'!A32 -> Inventories | E5: ='Data Room>'!I32 -> 3799 | F5: ='Data Room>'!J32 -> 6153 | G5: ='Data Room>'!K32 -> 6211 | H5: ='Data Room>'!L32 -> 5923 | I5: ='Data Room>'!M32 -> 6719
B6: ='Data Room>'!A33 -> Trade receivables - | E6: ='Data Room>'!I33 -> 2602 | F6: ='Data Room>'!J33 -> 3871 | G6: ='Data Room>'!K33 -> 4637 | H6: ='Data Room>'!L33 -> 4889 | I6: ='Data Room>'!M33 -> 4314
B7: ='Data Room>'!A34 -> Prov for Doubtful | E7: ='Data Room>'!I34 -> -185 | F7: ='Data Room>'!J34 -> -241 | G7: ='Data Room>'!K34 -> -305 | H7: ='Data Room>'!L34 -> -422 | I7: ='Data Room>'!M34 -> -663
B8: ='Data Room>'!A36 -> Loans n Advances | E8: ='Data Room>'!I36 -> 11 | F8: ='Data Room>'!J36 -> 8 | G8: ='Data Room>'!K36 -> 12 | H8: ='Data Room>'!L36 -> 17 | I8: ='Data Room>'!M36 -> 22
B9: ='Data Room>'!A37 -> Other asset items | E9: ='Data Room>'!I37 -> 2555 | F9: ='Data Room>'!J37 -> 2869 | G9: ='Data Room>'!K37 -> 3024 | H9: ='Data Room>'!L37 -> 3555 | I9: ='Data Room>'!M37 -> 3319
B10: Total Current Assets | E10: =SUM(E5:E9) -> 8782 | F10: =SUM(F5:F9) -> 12660 | G10: =SUM(G5:G9) -> 13579 | H10: =SUM(H5:H9) -> 13962 | I10: =SUM(I5:I9) -> 13711
B13: Current Liabilities
B14: ='Data Room>'!A11 -> Trade Payables | E14: ='Data Room>'!I11 -> 3379 | F14: ='Data Room>'!J11 -> 4164 | G14: ='Data Room>'!K11 -> 3635 | H14: ='Data Room>'!L11 -> 3831 | I14: ='Data Room>'!M11 -> 3848
B15: ='Data Room>'!A12 -> Advance from Customers | E15: ='Data Room>'!I12 -> 41 | F15: ='Data Room>'!J12 -> 76 | G15: ='Data Room>'!K12 -> 108 | H15: ='Data Room>'!L12 -> 154 | I15: ='Data Room>'!M12 -> 173
B16: ='Data Room>'!A13 -> Other liability items | E16: ='Data Room>'!I13 -> 2613 | F16: ='Data Room>'!J13 -> 2932 | G16: ='Data Room>'!K13 -> 3657 | H16: ='Data Room>'!L13 -> 4017 | I16: ='Data Room>'!M13 -> 3985
B17: Total Current Liabilities | E17: =SUM(E14:E16) -> 6033 | F17: =SUM(F14:F16) -> 7172 | G17: =SUM(G14:G16) -> 7400 | H17: =SUM(H14:H16) -> 8002 | I17: =SUM(I14:I16) -> 8006
A19: # | B19: Net Working Capital | E19: =E10-E17 -> 2749 | F19: =F10-F17 -> 5488 | G19: =G10-G17 -> 6179 | H19: =H10-H17 -> 5960 | I19: =I10-I17 -> 5705
B21: Non-current Assets
B22: ='Data Room>'!A16 -> Land | E22: ='Data Room>'!I16 -> 644 | F22: ='Data Room>'!J16 -> 644 | G22: ='Data Room>'!K16 -> 804 | H22: ='Data Room>'!L16 -> 1126 | I22: ='Data Room>'!M16 -> 1050
B23: ='Data Room>'!A17 -> Building | E23: ='Data Room>'!I17 -> 2249 | F23: ='Data Room>'!J17 -> 2325 | G23: ='Data Room>'!K17 -> 2883 | H23: ='Data Room>'!L17 -> 3390 | I23: ='Data Room>'!M17 -> 4136
B24: ='Data Room>'!A18 -> Plant Machinery | E24: ='Data Room>'!I18 -> 4340 | F24: ='Data Room>'!J18 -> 4531 | G24: ='Data Room>'!K18 -> 4825 | H24: ='Data Room>'!L18 -> 5422 | I24: ='Data Room>'!M18 -> 7576
B25: ='Data Room>'!A19 -> Equipments | E25: ='Data Room>'!I19 -> 243 | F25: ='Data Room>'!J19 -> 253 | G25: ='Data Room>'!K19 -> 270 | H25: ='Data Room>'!L19 -> 298 | I25: ='Data Room>'!M19 -> 325
B26: ='Data Room>'!A20 -> Furniture n fittings | E26: ='Data Room>'!I20 -> 99 | F26: ='Data Room>'!J20 -> 113 | G26: ='Data Room>'!K20 -> 146 | H26: ='Data Room>'!L20 -> 175 | I26: ='Data Room>'!M20 -> 203
B27: ='Data Room>'!A21 -> Vehicles | E27: ='Data Room>'!I21 -> 38 | F27: ='Data Room>'!J21 -> 32 | G27: ='Data Room>'!K21 -> 36 | H27: ='Data Room>'!L21 -> 40 | I27: ='Data Room>'!M21 -> 39
B28: ='Data Room>'!A22 -> Intangible Assets | E28: ='Data Room>'!I22 -> 476 | F28: ='Data Room>'!J22 -> 345 | G28: ='Data Room>'!K22 -> 422 | H28: ='Data Room>'!L22 -> 850 | I28: ='Data Room>'!M22 -> 827
B29: ='Data Room>'!A23 -> Other fixed assets | E29: ='Data Room>'!I23 -> 302 | F29: ='Data Room>'!J23 -> 294 | G29: ='Data Room>'!K23 -> 289 | H29: ='Data Room>'!L23 -> 321 | I29: ='Data Room>'!M23 -> 328
B30: Gross Block | E30: =SUM(E22:E29) -> 8391 | F30: =SUM(F22:F29) -> 8537 | G30: =SUM(G22:G29) -> 9675 | H30: =SUM(H22:H29) -> 11622 | I30: =SUM(I22:I29) -> 14484
B31: Accumulated Depreceation | E31: ='Data Room>'!B25 -> 1242 | F31: ='Data Room>'!C25 -> 1452 | G31: ='Data Room>'!D25 -> 327 | H31: ='Data Room>'!E25 -> 610 | I31: ='Data Room>'!F25 -> 973
B32: Net non-current assets | E32: =E30-E31 -> 7149 | F32: =F30-F31 -> 7085 | G32: =G30-G31 -> 9348 | H32: =H30-H31 -> 11012 | I32: =I30-I31 -> 13511
A34: # | B34: Invested Capital | E34: =E32+E19 -> 9898 | F34: =F32+F19 -> 12573 | G34: =G32+G19 -> 15527 | H34: =H32+H19 -> 16972 | I34: =I32+I19 -> 19216
B35: EBIT

Sheet Data Room>
B1: 41699 | C1: 42064 | D1: 42430 | E1: 42795 | F1: 43160 | G1: 43525 | H1: 43891 | I1: 44256 | J1: 44621 | K1: 44986 | L1: 45352 | M1: 45717
A2: Equity Capital | B2: 96 | C2: 96 | D2: 96 | E2: 96 | F2: 96 | G2: 96 | H2: 96 | I2: 96 | J2: 96 | K2: 96 | L2: 96 | M2: 96
A3: Reserves | B3: 3943 | C3: 4646 | D3: 6429 | E3: 7508 | F3: 8314 | G3: 9375 | H3: 10034 | I3: 12710 | J3: 13716 | K3: 15896 | L3: 18632 | M3: 19304
A4: Borrowings -
A5: Long term Borrowings | B5: 41 | C5: 78 | D5: 73 | E5: 41 | F5: 28 | G5: 19 | H5: 19 | I5: 15 | J5: 45 | K5: 76 | L5: 54 | M5: 260
A6: Short term Borrowings | B6: 199 | C6: 332 | D6: 231 | E6: 504 | F6: 492 | G6: 597 | H6: 321 | I6: 334 | J6: 731 | K6: 896 | L6: 1053 | M6: 604
A7: Lease Liabilities | B7: 0 | C7: 0 | D7: 0 | E7: 0 | F7: 0 | G7: 693 | H7: 764 | I7: 745 | J7: 811 | K7: 960 | L7: 1367 | M7: 1427
A8: Other Borrowings | B8: 9 | C8: 8 | D8: 20 | E8: 15 | F8: 13 | G8: 11 | H8: 15 | I8: 0 | J8: 0 | K8: 0 | L8: 0 | M8: 0
A9: Other Liabilities - | B9: 3787 | C9: 3754 | D9: 3711 | E9: 4241 | F9: 4820 | G9: 5459 | H9: 4889 | I9: 6456 | J9: 7560 | K9: 7854 | L9: 8698 | M9: 8665
A10: Non controlling int | B10: 246 | C10: 264 | D10: 384 | E10: 375 | F10: 328 | G10: 361 | H10: 404 | I10: 423 | J10: 388 | K10: 454 | L10: 695 | M10: 659
A11: Trade Payables | B11: 1746 | C11: 1549 | D11: 1565 | E11: 1923 | F11: 2160 | G11: 2394 | H11: 2137 | I11: 3379 | J11: 4164 | K11: 3635 | L11: 3831 | M11: 3848
A12: Advance from Customers | B12: 0 | C12: 5 | D12: 12 | E12: 17 | F12: 16 | G12: 13 | H12: 29 | I12: 41 | J12: 76 | K12: 108 | L12: 154 | M12: 173
A13: Other liability items | B13: 1795 | C13: 1937 | D13: 1750 | E13: 1925 | F13: 2316 | G13: 2690 | H13: 2320 | I13: 2613 | J13: 2932 | K13: 3657 | L13: 4017 | M13: 3985
A14: Total Liabilities | B14: 8075 | C14: 8914 | D14: 10559 | E14: 12405 | F14: 13763 | G14: 16249 | H14: 16138 | I14: 20355 | J14: 22958 | K14: 25779 | L14: 29901 | M14: 30355
A15: Fixed Assets -
A16: Land | B16: 247 | C16: 251 | D16: 429 | E16: 408 | F16: 586 | G16: 605 | H16: 640 | I16: 644 | J16: 644 | K16: 804 | L16: 1126 | M16: 1050
A17: Building | B17: 931 | C17: 962 | D17: 923 | E17: 931 | F17: 957 | G17: 2402 | H17: 2257 | I17: 2249 | J17: 2325 | K17: 2883 | L17: 3390 | M17: 4136
A18: Plant Machinery | B18: 2054 | C18: 2132 | D18: 1793 | E18: 1980 | F18: 2157 | G18: 4006 | H18: 4208 | I18: 4340 | J18: 4531 | K18: 4825 | L18: 5422 | M18: 7576
A19: Equipments | B19: 155 | C19: 171 | D19: 97 | E19: 119 | F19: 200 | G19: 221 | H19: 241 | I19: 243 | J19: 253 | K19: 270 | L19: 298 | M19: 325
A20: Furniture n fittings | B20: 71 | C20: 83 | D20: 49 | E20: 59 | F20: 72 | G20: 88 | H20: 94 | I20: 99 | J20: 113 | K20: 146 | L20: 175 | M20: 203
A21: Vehicles | B21: 14 | C21: 18 | D21: 11 | E21: 14 | F21: 27 | G21: 47 | H21: 43 | I21: 38 | J21: 32 | K21: 36 | L21: 40 | M21: 39
A22: Intangible Assets | B22: 203 | C22: 351 | D22: 339 | E22: 276 | F22: 468 | G22: 512 | H22: 505 | I22: 476 | J22: 345 | K22: 422 | L22: 850 | M22: 827
A23: Other fixed assets | B23: 128 | C23: 145 | D23: 103 | E23: 128 | F23: 238 | G23: 261 | H23: 293 | I23: 302 | J23: 294 | K23: 289 | L23: 321 | M23: 328
A24: Gross Block | B24: 3804 | C24: 4112 | D24: 3744 | E24: 3914 | F24: 4705 | G24: 8141 | H24: 8282 | I24: 8392 | J24: 8538 | K24: 9676 | L24: 11622 | M24: 14484
A25: Accumulated Depreciation | B25: 1242 | C25: 1452 | D25: 327 | E25: 610 | F25: 973 | G25: 1644 | H25: 2010 | I25: 2533 | J25: 3019 | K25: 3905 | L25: 4475 | M25: 5264
A26: Net Block | B26: =B24-B25 -> 2562 | C26: =C24-C25 -> 2660 | D26: =D24-D25 -> 3417 | E26: =E24-E25 -> 3304 | F26: =F24-F25 -> 3732 | G26: =G24-G25 -> 6497 | H26: =H24-H25 -> 6272 | I26: =I24-I25 -> 5859 | ... M26: =M24-M25 -> 9220
A28: CWIP | B28: 72 | C28: 196 | D28: 107 | E28: 258 | F28: 1405 | G28: 210 | H28: 140 | I28: 183 | J28: 426 | K28: 1020 | L28: 2698 | M28: 1254
A29: Investments | B29: 1424 | C29: 1588 | D29: 2712 | E29: 2652 | F29: 2141 | G29: 2569 | H29: 2019 | I29: 4737 | J29: 3248 | K29: 4262 | L29: 4588 | M29: 4725
A31: Other Assets -
A32: Inventories | B32: 2070 | C32: 2259 | D32: 1998 | E32: 2627 | F32: 2658 | G32: 3150 | H32: 3390 | I32: 3799 | J32: 6153 | K32: 6211 | L32: 5923 | M32: 6719
A33: Trade receivables - | B33: 1110 | C33: 1182 | D33: 1187 | E33: 1447 | F33: 1731 | G33: 1907 | H33: 1795 | I33: 2602 | J33: 3871 | K33: 4637 | L33: 4889 | M33: 4314
A34: Prov for Doubtful | B34: -50 | C34: -59 | D34: -67 | E34: -79 | F34: -89 | G34: -121 | H34: -155 | I34: -185 | J34: -241 | K34: -305 | L34: -422 | M34: -663
A35: Cash Equivalents | B35: 229 | C35: 204 | D35: 424 | E35: 801 | F35: 405 | G35: 445 | H35: 783 | I35: 611 | J35: 864 | K35: 844 | L35: 1084 | M35: 782
A36: Loans n Advances | B36: 7 | C36: 8 | D36: 9 | E36: 14 | F36: 13 | G36: 16 | H36: 12 | I36: 11 | J36: 8 | K36: 12 | L36: 17 | M36: 22
A37: Other asset items | B37: 603 | C37: 817 | D37: 705 | E37: 1303 | F37: 1678 | G37: 1456 | H37: 1727 | I37: 2555 | J37: 2869 | K37: 3024 | L37: 3555 | M37: 3319
A38: Total Assets | B38: 8075 | C38: 8914 | D38: 10559 | E38: 12405 | F38: 13763 | G38: 16249 | H38: 16138 | I38: 20355 | J38: 22958 | K38: 25779 | L38: 29901 | M38: 30355

Sheet Datasheet
B2: Date | C2: Price | E2: Date | F2: Price | H2: S.No. | I2: Name | J2: CMP Rs. | K2: Mar Cap Rs.Cr. | L2: Debt Rs.Cr. | M2: Debt / Eq
B3: 45886 | C3: 4698.8 | E3: 45886 | F3: 24870.1 | H3: 1 | I3: Avenue Super. | J3: 4698.8 | K3: 305766.46 | L3: 819.62 | M3: 0.04
B4: 45879 | C4: 4358.2 | E4: 45879 | F4: 24631.3 | H4: 2 | I4: Vishal Mega Mart | J4: 150.67 | K4: 70279.65 | L4: 1729.38 | M4: 0.27
B5: 45872 | C5: 4170.1 | E5: 45872 | F5: 24363.3 | H5: 3 | I5: Shoppers Stop | J5: 544.05 | K5: 5998.38 | L5: 3314.09 | M5: 10.32
B6: 45865 | C6: 4196 | E6: 45865 | F6: 24565.35 | H6: 4 | I6: V-Mart Retail | J6: 747 | K6: 5937.32 | L6: 782.51 | M6: 0.97
B7: 45858 | C7: 3997 | E7: 45858 | F7: 24837 | H7: 5 | I7: Electronics Mart | J7: 131.41 | K7: 5060.59 | L7: 1976.45 | M7: 1.29
B8: 45851 | C8: 4048.6 | E8: 45851 | F8: 24968.4
B9: 45844 | C9: 4064.2 | E9: 45844 | F9: 25149.85
B10: 45837 | C10: 4261.1 | E10: 45837 | F10: 25461
B11: 45830 | C11: 4313.5 | E11: 45830 | F11: 25637.8
B12: 45823 | C12: 4300.3 | E12: 45823 | F12: 25112.4
B13: 45816 | C13: 4051.9 | E13: 45816 | F13: 24718.6
B14: 45809 | C14: 4201.6 | E14: 45809 | F14: 25003.05
B15: 45802 | C15: 4002.1 | E15: 45802 | F15: 24750.7
B16: 45795 | C16: 4140.8 | E16: 45795 | F16: 24853.15
B17: 45788 | C17: 4189.7 | E17: 45788 | F17: 25019.8
B18: 45781 | C18: 3972.4 | E18: 45781 | F18: 24008
B19: 45774 | C19: 4059.2 | E19: 45774 | F19: 24346.7
... B106: 45165 | C106: 3761.05 | E106: 45165 | F106: 19435.3
